Workbook

Sheet Sheet4
D2: Kozma | E2: Luiza
D3: Alphatec x Petrobras | E3: Vitória
D4: Precatórios Valecard | E4: AP | N4: =COUNTIFS(Pipe!G:G,Sheet4!$O4) -> 245 | O4: 2024
D5: TANAC | E5: Mauad | N5: =COUNTIFS(Pipe!G:G,Sheet4!$O5) -> 372 | O5: 2025
D6: Transpetro | E6: Luiza | N6: =COUNTIFS(Pipe!G:G,Sheet4!$O6)/7*12 -> 457.71429 | O6: 2026
D7: FIDC BLUE II | E7: Todos
D8: Espólio Maria Nubia e PBR | E8: Vitória
D9: Pizzato x União Federal / IBAMA | E9: Vitória
D10: Humberto x Braskem | E10: Vitória
D11: Sussumo e Itimura vs Incra | E11: Vitória
D12: Petro-Alpha x Petrobras | E12: Vitória
D13: Jose Teixeira x INCRA | E13: Vitória

Sheet Pipe
D3: Planilha de Controle do Pipeline - Special Situations | K3: =75*60% -> 45 | P3: =900+800+800+700+500 -> 3700
E4: Não | F4: Em análise | G4: Concluído | H4: On Hold | I4: Total | M4: =120/30% -> 400
D5: Oportunidades Apresentadas | E5: =COUNTIF($N:$N,E4) -> 736 | F5: =COUNTIF($N:$N,F4) -> 38 | G5: 23 | H5: =COUNTIF($N:$N,H4) -> 100 | I5: =+E5+F5+H5 -> 874 | K5: =82*6.2 -> 508.4 | R5: =295/7 -> 42.142857
C8: # | D8: Tipo de Operação | E8: Nome | F8: Data Entrada | G8: year | H8: Contato | I8: Tipo de Contato | J8: Descrição da Oportunidade | K8: Status da Operação | L8: Valor (R$ mm) | M8: Responsável | N8: Decisão | O8: Data de Saída | P8: Feedback
C9: 1 | D9: Precatórios | E9: Precatórios do Estado do RN | F9: 45303 | G9: =+YEAR(F9) -> 2024 | H9: Thiago Cordeiro - DBV Capital | J9: 156 - Cumprimento de Sentença | K9: - | N9: Não | P9: Valor baixo e estado do RN está bem atrasado em sua fila de pagamentos (pagando fila de 2006)
C10: =+C9+1 -> 2 | D10: Precatórios | E10: Precatórios do Estado do MT | F10: 45307 | G10: =+YEAR(F10) -> 2024 | H10: Thiago Cordeiro - DBV Capital | J10: 39 - Não alimentar - Desapropriações | K10: - | N10: Não | P10: Tese conhecida do Instituto do Açúcar e do Álcool - IAA; em nossa análise, a tese está frequentemente exposta a viradas jurisprudenciais, trazendo riscos adicionais para os créditos
C11: =+C10+1 -> 3 | D11: Precatórios | E11: Precatórios do Estado do PR | F11: 45315 | G11: =+YEAR(F11) -> 2024 | H11: Emanuel Cavalcanti - Convexa Investimentos | J11: - | K11: - | N11: Não | P11: PR está bem atrasado em sua fila de pagamentos, atualmente ainda quitando precatórios do orçamento 2005/2006, o que tende a alongar o prazo para recebimento da oportunidade enviada, visto que estão inscritos no orçamento 2016
C12: =+C11+1 -> 4 | D12: Precatórios | E12: Precatórios da Camargo Correa | F12: 45306 | G12: =+YEAR(F12) -> 2024 | H12: Marco Andre Alencar | J12: 39 - Não alimentar - Desapropriações | K12: 26/01 - Sinalizamos que conseguiríamos ~25% do valor, com earn-out. Marco ficou de retornar, porém, com essas condições, há grandes chances de não seguirem com a negociação | N12: Não | P12: 23/02 - Com a possibilidade de acordo dos precatorios, nossa proposta não é atrativa para o vendedor do precatório
C13: =+C12+1 -> 5 | D13: Precatórios | E13: Precatórios do Estado do PA | F13: 45314 | G13: =+YEAR(F13) -> 2024 | H13: Stellar Capital | I13: Broker | J13: Desapropriação Propriedade Rural no Pará | K13: 02/02 - Jorio solicitou um call para passarmos pela oportunidade. 02/02 - Luiza vai responder ao email do Jorio 05/02 - Aguardando ligação do Jorio | N13: Não | P13: 23/02 - Prazo longo e risco elevado
C14: =+C13+1 -> 6 | D14: Crédito para Operação | E14: Grupo ASN | F14: 45302 | G14: =+YEAR(F14) -> 2024 | H14: Paulo Viola | J14: Empresa de cultivo de café, laranja e banana e nutrição animal, dívida de 68mm | K14: 01/01 - Realizamos reunião com Celso, para explicar que as dívidas baratas nao devem ser quitadas integralmente, entendemos que deve ser uma entrada para entao renegociá-las. Para nosso empréstimo, precisamos de novos imoveis como garantia, Celso nos retornará se ha garantias disponíveis e se há intenção de monetizá-las Falar com o Alberto sobre a operação recebida, entender com o Alberto se seria uma operação imobiliária 23/02 - Cobrar o Paulo sobre as fazendas herdadas e puxar para fazer um novo call com o Alberto e o Celso (26/02) 28/02 - Não enviaram novas infos de imoveis, somente o contrato de venda de laranja (em análise) 04/03 - Reunião com Celso e Paulo para entender a proposta indicativa que receberam às 10h30 05/03. 05/03 - Enviaram um range de valores para a taxa da operação proposta. Precisamos definir como seguir aqui. | N14: Não | P14: Não queremos tomar o risco de fazer um sale leaseback de um ativo que no momento pode ser não operacional mas que esta nos planos do Alberto. Vamos marcar um call. Call agendado para segunda feira 14h. Confirmar
C15: =+C14+1 -> 7 | D15: DIP para RJ | E15: Grupo OHAEC | F15: 45306 | G15: =+YEAR(F15) -> 2024 | H15: Andreia Alonso | J15: Grupo OHAEC, são donos do colegio Helio Alonso (Meier) e Faculdade Facha, em RJ desde abril de 2022 | K15: 02/02 - Realizamos o call com as socias do Grupo e novas solicitações de informações foram feitas 08/02 - Enviaram dados financeiros, projeções e avaliação dos imoveis de São Gonçalo e Meier (R$ 2,3mm e R$ 2mm) 23/02 - Pendente de devolutiva para o time de Facha, oportunidade em análise 26/02 - Entender com a JGP FA se a família tem mais garantia do que o que foi enviado, só com essas garantias não vamos aprovar a operação 05/03 - Pendente de feedback para Cia indicando que caso nao haja mais imoveis disponíveis não é possivel fazer o empréstimo | L15: 10 | N15: Não | P15: 14/03 - Oportunidade declinada no momento devido a falta de collateral para um potencial empréstimo
C16: =+C15+1 -> 8 | D16: DIP para RJ | E16: Grupo JS | F16: 45315 | G16: =+YEAR(F16) -> 2024 | H16: Fernando Galvão | J16: Financimanento para o Grupo JS (em RJ) dar de entrada no parcelamento dos impostos junto à PGFN | K16: - | N16: Não | P16: TIR que acenamos aos nossos investidores em Roadshow recente supera com alguma margem a TIR no caso base (que nos pareceu mais provável também) da operação. (CDI+12%)
C17: =+C16+1 -> 9 | D17: Precatórios Federais | E17: Yolanda e Elide | F17: 45314 | G17: =+YEAR(F17) -> 2024 | H17: JGP FA | J17: Yolanda e Elide - Ambos são decorrentes de desapropriação e atualmente também consta autorização no inventário da Yolanda | K17: 26/01 - Enviamos para William que estaríamos dispostos a desembolsar até 65% do valor de face 31/01 - Solicitamos os autos dos inventários da Yolanda e Elide 06/02 - Enviado o Espólio da Yolanda e Precatórios expedidos pelo TRF 2 28/02 - Pendente de confirmação se há algum representante para negociação do precatório para Elide. Para sra. Yolanda precisamos do formal de partilha para endereçar a melhor maneira de conduzir a potencial aquisição dos direitos creditórios | N17: Não | P17: Não aceitaram o preço proposto (pgto de 65% do PU - incluindo o broker)
C18: =+C17+1 -> 10 | D18: Crédito para CapEx | E18: Horizonte Minerals | F18: 45315 | G18: =+YEAR(F18) -> 2024 | H18: Moelis | J18: Financiamento para finalizar as obras da primeira planta de exploração de Niquel | K18: 15/01 - Fizemos uma primeira reunião com o CEO e COO e time Moelis para apresentação da oportunidade 30/01 - Recebemos acesso ao Data Room 22/02 - Participamos de uma apresentação do conselho sobre o novo BP. Moelis abriu oportunidade de marcar um call para tirarmos dúvida 22/02 - Sinalizaram TIR de 15% em USD 28/02 - Ainda não atualizaram o VDR com a estrutura de capital alvo da Companhia 08/03 - Definir a data para reuniao de apresentação de capital structure | N18: Não | P18: Baixa chance de montarmos essa operação por ser uma greenfield de niquel
C19: =+C18+1 -> 11 | D19: Crédito para Operação | E19: Grupo SMH | F19: 45489 | G19: =+YEAR(F19) -> 2024 | H19: JGP FA | J19: Hospital em Petropolis com numeros operacionais negativos, solicitando captação para melhoria operacional | K19: Íntegra ficou de analisar sobre uma potencial gestão interina na Companhia, pendente de resposta 23/02 - Chris vai conversar com o Lassance sobre a oportunidade 01/03 - Tivemos um call com o Vidal da IFA, para gestão interina na Cia. Time da JGP FA vai falar com o board da Cia para entender a situação atual da empresa 08/03 - Cobrar fernando de uma atualização sobre o ponto acima 22/03 - Pendente de resposta do Fernando (ainda sem resposta) 29/04 - Contrataram a Deloitte para gestão interina | M19: Christopher | N19: Não | P19: 29/04 - Contrataram a Deloitte para gestão interina
C20: =+C19+1 -> 12 | D20: Crédito para Operação | E20: Inplac | F20: - | G20: =+YEAR(F20) -> #VALUE! | H20: JGP FA | J20: Indústria de produtos plásticos que saiu da RJ em 2021 mas ainda está com necessidade de caixa | K20: Dez/23 - Solicitamos informações sobre a Cia que ainda não foram enviadas 30/01 - Fizemos um FUP sobre o envio das infos, nos enviará no inicio da semana (05/02) 23/02 - Entender se a empresa já pagou os credores da RJ e entender pq as dívidas tributárias ficaram em aberto. A empresa está operacional? Pode entrar em RJ novamente? 04/03 - Aguardar a transação tributária e entender se a cia pode entrar em RJ novamente 15/03 - Vamos ligar para a Cia diretamente 01/04 - Principal acionista mostrou interesse em dar como garantia as ações do Costao e tb vender o ativo - Pendente de feedback o William (FA) após a reunião com a Empresa. 08/04 - Esperar o mandato da FA, as informações da dívida tributária, budget 2024 e entender se as garantias do Costão entrarão na potencial transação | M20: Mollica | N20: On Hold
C21: =+C20+1 -> 13 | D21: DIP/Equity para RJ | E21: OSX | F21: 45320 | G21: =+YEAR(F21) -> 2024 | H21: Henrique (JGP) | J21: Montante requerido sera para usado para recomprar dívidas das companhias e converter dívida em equity | K21: 30/01 - Recebemos o material, porem a transação envolve equity e um valuation que não traduz a realidade da empresas. Pendente de feedback 23/02 - Mollica vai passar o feedback para o responsável da OSX | N21: Não | P21: Entendemos não ser o perfil do fundo de Special sits devido alguns pontos: (i) Operação envolvendo equity; (ii) Valuation descolado do que entendemos ser o valor justo para a empresa (Mkt cap atual R$ 17mm x valor apresentado no InfoMemo R$ 700mm)
C22: =+C21+1 -> 14 | D22: Precatório Federal | E22: José Cardoso | F22: 45322 | G22: =+YEAR(F22) -> 2024 | H22: Gregory Pagot | J22: 39 - Não alimentar - Desapropriações | K22: 31/01 - Entender se esse precatório federal seria para o orçamento de 2024 15/03 - Vamos responder ao email do Gregory | M22: Hugo | N22: Não
C23: =+C22+1 -> 15 | D23: Crédito para Pgto do Bond | E23: Andrade Gutierrez | F23: 45322 | G23: =+YEAR(F23) -> 2024 | H23: QMS Capital | J23: Companhia esta buscando um new money para poder quitar o bond com vct em 2029 e cupom de 9% | K23: 02/01 - Oportunidade em análise Vamos agendar uma reunião com Palmier para entendermos a estrutura da Transação 08/02 - Enviaram as infos solicitadas, estamos modelando para analisar o crédito da Cia 09/02 - Reunião com Palmier e Galapagos para definir os termos da potencial transação 19/02 - Reuniao com todos os times para apresentarmos os termos e condições do TS, pendente de retorno da AG 22/02 - A Companhia está pendente de enviar as projeções e o 2023FY - devem enviar ainda essa semana (04/03) 18/03 - Andrade ganhou licitação para obras da refinaria Abreu de 3.9bi | L23: 150 | M23: Christopher | N23: Não
C24: =+C23+1 -> 16 | D24: Crédito | E24: Dock Brasil | F24: 45366 | G24: =+YEAR(F24) -> 2024 | H24: JGP FA | K24: 15/03 - Time da FA até dia 22/03 deve nos enviar o modelo e InfoMemo para analisarmos a oportunidade, até 27/03. 01/04 - Time da FA esta com modelagem pronta mas ainda pendente dos acionistas darem OK nos materiais 08/04- fizemos um call para repassar os materiais, vao ajustar o modelo e nos enviarão 17/04 - Enviaram o modelo 29/04 - Vamos fazer um call com o francis para discutir o modelo e nos enviarão as notas explicativas de 2023 até sexta 06/05 - Notas explicativas serão enviadas até 07/05 31/05 - time FA pediu ajuste na proposta 10/06 - Cobrar time FA sobre a reunião com TRG | L24: =19*5 -> 95 | M24: Mollica / Christopher | N24: On Hold
C25: =+C24+1 -> 17 | D25: Precatório Federal | E25: Ouricuri | F25: 45322 | G25: =+YEAR(F25) -> 2024 | H25: Gregory Pagot | J25: 10604 - Desapropriação por Interesse Social para Reforma Agrária/Art 184 | K25: 02/02 - Em análise (Obs: Valores elevados). 02/02 - Enviamos o questionamento sobre o motivo pelo qual a Jive esta vendendo 16/02 - Respondeu que enviou a oportunidade para a Jive também, porém afirmou que não era da Jive | N25: Não | P25: Muitos cessionários e não entendemos quem é o cedente
C26: =+C25+1 -> 18 | D26: Precatórios | E26: Precatórios do Estado do RJ - Solstad Offshore | F26: 45323 | G26: =+YEAR(F26) -> 2024 | H26: Thiago Cordeiro - DBV Capital | J26: Procedimento Comum - Icms- Outros / Imposto Sobre Circulação de Mercadorias / Impostos; Antecipação de Tutela E/ou Obrigação de Fazer Ou Não Fazer Ou Dar | K26: 01/02 - Em Análise. Os cedentes vão vender tudo e avaliam proposta acima de 45% 02/02 - Solicitamos uma nova proposta dado a possibilidade de acordo com os estados 22/02 - Respondeu que propostas em torno de 40% serão analisadas 28/02 - Declinaram propostas de 42%, vamos seguir? 04/03 - Pendente de responder o Thiago, declinando a oportunidade | N26: Não
C27: =+C26+1 -> 19 | D27: Crédito para Operação | E27: Turbi | F27: 45329 | G27: =+YEAR(F27) -> 2024 | H27: ARC Capital | J27: Novo dinheiro para compra das preferenciais da ARC | K27: 08/02 - Recebemos acesso ao Data room. Oportunidade declinada | N27: Não | P27: No caso dos fundos Special Sits avaliamos que a operação não nos atende no quesito de IRR (CDI +12%), e quanto aos fundos de dívida convencional já estamos bastante alocados em papéis de rental não cabendo mais exposição ao setor
C28: =+C27+1 -> 20 | D28: CRA ou CRI | E28: St.Marche | F28: 45329 | G28: =+YEAR(F28) -> 2024 | H28: Orama IB | J28: R$ 100 milhões com 24 meses de carência de principal, prazo de 5 anos e CDI + 5%. Passaram o caso com a Gabriela e Muller, mas pela estrutura de capital da cia (PL virado e ainda bem alavancada) preferiram não avançar | K28: 09/02 - Em análise 20/02 - Fizemos um call para entender a operação, porém a Companhia não possui ativos reais para garantias. Vamos negar? | N28: Não | P28: Entendemos não ser o perfil de Special Sits, seria um caso de capital solution (necessidade de captação de equity). Entendemos que a operação envolve equity e não conseguimos viabilizar agora, caso mude a estrutura do deal, pedimos que nos avisem por favor
C29: =+C28+1 -> 21 | D29: Crédito para Operação | E29: Losinox | F29: 45330 | G29: =+YEAR(F29) -> 2024 | H29: Heartman House | J29: Companhia precisa de empréstimo de R$ 30mm para Kgiro para compra de matéria prima. Além disso, precisa de R$ 5mm no CP para suprir necessidade de caixa | K29: 09/02 - Pendente envio de informação 22/02 - Realizamos um call para entendermos melhor a operação e enviamos um info request com solicitações adicionais 29/02 - Responderam parcialmente o info request, pendente do detalhamento da dívida 04/03 - Falar com o William sobre a renovação do aluguel de Ribeirao Pires 05/03 - Pendente de renegociação do contrato com a Aperam e entender o apetite deles para um pre pagamento da dívida (R$ 6.2mm) e liberação da hipoteca 15/03 - Enviamos uma mensagem com bullets dos principais pontos de uma potencial proposta de financiamento 28/03 - Estamos aguardando atualização do William sobre a renovação do contrato de aluguel com a Aperam e a possivel quitação do emprestimo da Losinox com a Aperam. | L29: 6.5 | M29: Luiza | N29: Não
C30: =+C29+1 -> 22 | D30: Crédito para Operação | E30: Armco | G30: =+YEAR(F30) -> 1900 | H30: JGP FA | J30: Principais players no mercado brasileiro de produtos de metais planos, atuando especificamente nos segmentos de laminados a frio e sistemas de embalagem | K30: 23/02 - Cobrar do Gabriel Nobrega da FA 01/03 - Matheus (FA) irá nos enviar as infos 04/03- Ligar par ao Gabrie para entednder melhor a operação 11/03 - Solicitamos infos adicionais 14/03 - Informaram que estão com exclusividade com outra casa, no momento está em stand-by 24/06 - Focal, advisor, enviou o material de Roadshow para o Mollica, ficou de analisar para entender se seguiremos 01/07 - Vamos negar devido a estrategia de aumentar o PL com a doação de imoveis, a uma valor que nao entendemos se traduz a realidade | M30: Christopher | N30: Não | P30: 02/07 - Negamos novamente por nao fzer sentido para o SS
C31: =+C30+1 -> 23 | D31: Compra de Carteira de Crédito | E31: Comexport | G31: =+YEAR(F31) -> 1900 | H31: Leonardo Campos Melo | I31: Advogado | K31: 23/02 - Luiza esta analisando a Carteira de vencidos - 04/03 - Há um crédito para ser melhor analisado, pendente de baixar o processo 08/03 - Luiza vai falar com o leonardo campos melo 15/03 - Luiza vai falar com o leonardo campos melo | M31: Luiza | N31: Não | P31: 01/04 - Operação não faz sentido para o fundo de SS
C32: =+C31+1 -> 24 | D32: Oportunidade de Crédito estressado | E32: Hotel Trump | G32: =+YEAR(F32) -> 1900 | H32: JGP FA | J32: Hotel em RJ | K32: 23/02 - Pendente do envio de informações pelo time JGP FA 23/02 - Baixar o processo para entender o FIP por trás do hotel Fernando Kunzel vai marcar um call com o Michel para entendermos melhor do case Mollica vai falar com alguma construtora para entender a oportunidade 07/03 - Call com a Cyrela, irão verificar alguns pontos: (i) se a debenture foi comprada; (ii) possibilidade da conversão de hotel para residencial; (iii) capacidade do imovel para retrofit 19/03 - Cyrela afirmou que a area construida do hotel não pode ser convertida de hotel para residencial | N32: Não | P32: As debentures foram compradas e não entrariamos comprando cota de FIP
C33: =+C32+1 -> 25 | D33: Oportunidade de Crédito estressado | E33: Frigorífico Rainha | F33: 45337 | G33: =+YEAR(F33) -> 2024 | H33: Vela Capital | J33: Oportunidade de crédito estressado para o Frigorífico Rainha no Paraná que está em RJ | K33: Em análise. Enviaram informações financeiras, pendente do envio da apresentação da Companhia - solicitado 21/02 07/03- Solicitamos identificarem se os fornecedores são rastreaveis ou não 13/03 - Enviaram as informações sobre a rastreabilidade dos fornecedores, estamos preparando um q&a para um call na semana que vem. 19/03- Iniciamos as analises e solicitamos mais informações (não temos clareza sobre as possíveis garantias dessa operação). Além disso, sugeriram uma redução no cheque para R$ 15mm 20/03 - Enviamos perguntas preliminares para o time da Vela Capital, pendente de resposta 26/06 - Enviaram as respostas de algumas perguntas que fizemos em Março/Abril 08/07 - Vamos negar a oportunidade | L33: 50 | M33: Christopher | N33: Não | P33: i) empresa com histórico de EBITDA negativo; ii) não temos conforto com operações no setor de frigoríficos; e iii) garantias não chegam a 100% do empréstimo, além de grande parte ser operacional.
C34: =+C33+1 -> 26 | D34: Precatório Federal | E34: Belém - Desapropriação | F34: 45344 | G34: =+YEAR(F34) -> 2024 | H34: Raphael Martins (Souto Correa) | J34: Desapropriações | K34: Através de uma análise inicial (ajustar por selic) entendemos que o % máximo do PU seria 60%. | M34: Luiza | N34: Não | P34: Declinado pelo cedente. Valor abaixo do esperado
C35: =+C34+1 -> 27 | D35: Precatório Federal | E35: Marcia Cristina | F35: 45338 | G35: =+YEAR(F35) -> 2024 | H35: Gregory Pagot | J35: Não Alimentar | K35: 15/02 - Recebemos a oportunidade do precatório federal em Brasilia de R$ 34mm, precisa ser analisado. Luiza pediu a ligação do Gregory 05/03 - Gregory enviou um email perguntando sobre o precatorio | M35: Luiza | N35: Não | P35: Ativo com muitos fundos e bem enrolado
C36: =+C35+1 -> 28 | D36: Crédito para Operação | E36: OBDI | F36: 45337 | G36: =+YEAR(F36) -> 2024 | H36: JGP FA | J36: A Companhia está buscando R$30mm em um novo empréstimo para garantir um potencial contrato com a Petrobras e ter caixa para novos contratos | K36: 15/02 - Em análise 26/02 - fizemos um call com o time FA para tirarmos duvidas preliminares 28/02 - Enviaram as condições do contrato com a Petrobras, porém pendente de enviar a relação dos imóveis que podem ser dados como garantia 05/03 - Conseguiram o contrato com a Petro e vao pegar um empréstimo com um banco. Pendente de devolutiva de respostas 14/03 - Locadoras tem perdas milionárias com queda de seminovo, isso impacta diretamente o business da OBDI 21/03- solução seria disponibilizar uma linha de credito que estaria disponível caso a empresa ganhe uma licitação, porem isso dificilmente seria aprovado em comite. Estariamos disponibilizando um credito sem contrapartida de receita em um primeiro momento, alem de prejudicar a rentabilidade | L36: 30 | M36: Christopher | N36: Não | P36: 01/04 - solução seria disponibilizar uma linha de credito que estaria disponível caso a empresa ganhe uma licitação, porem isso dificilmente seria aprovado em comite. Estariamos disponibilizando um credito sem contrapartida de receita em um primeiro momento, alem de prejudicar a rentabilidade
C37: =+C36+1 -> 29 | D37: Pré-precatório | E37: Data Traffic e DNIT | F37: 45337 | G37: =+YEAR(F37) -> 2024 | H37: Vicente Barros (Amavic) | J37: - | K37: 14/03 - Fechamos o racional de precificação, pendente de alinhar o % do vf a ser proposto. Há um outro player que ja colocou a proposta mas ainda não é algo que estão buscando. 15/03 - No dia 18/03 vamos nos atualizar para entender se avançou a negociação 22/03 - Agendar reunião com Vicente Barros para entender a evolução das negociações 22/04 - Reunião com potenciais investidores para a captação do fundo monotematico para esse investimento 26/04 - Primeira parte da transação (R$ 5mm) foi liquidada | L37: 147 | M37: Christopher e Hugo | N37: Concluído
C38: =+C37+1 -> 30 | D38: Refinanciamento da Dívida | E38: HI Plataform | F38: 45338 | G38: =+YEAR(F38) -> 2024 | H38: ExFin Advisory | J38: Refinanciamento de dívida e investimentos em expansão: Investimento em produto e desenvolvimento e máquina de vendas | K38: 26/03 - Liguei para a ExFin, unica garantia oferecida é de recebiveis da operação, a principio nao ha mais imoveis e a cia esta a mercado tentando captar dívida, estão vendo ~CDI+6% 01/04 - Caso nao voltem com as respostas das garantias e taxas vamos passar a oportunidade com o time de FA e então declinar | L38: 20 | M38: Christopher | N38: não | P38: 29/04 - Declinamos pois não tinha collateral suficiente (sem imoveis) e esperavam uma taxa mto baixa, ainda não era case de SS.
C39: =+C38+1 -> 31 | D39: Credito para RJ | E39: Terra Forte | F39: 45342 | G39: =+YEAR(F39) -> 2024 | H39: Alvarez & Marsal | J39: Crédito de R$ 25-30mm para pagar credores em atraso e capital de giro para a companhia | K39: 21/02 - Recebemos as informações e fizemos o primeiro call para tirarmos dúvidas com a A&M. 22/02 - Enviaram o modelo e estamos analisando 23/02 - Vamos ajustar o NDA enviado por eles | L39: 30 | M39: Christopher | N39: Não | P39: 01/03 - Entendemos que a companhia não possui capacidade de pagamento do empréstimo devido ao tamanho da safra e o custo de plantio para a próxima safra, além de poucas garantias disponíveis (ativos alienados ao BTG)
C40: =+C39+1 -> 32 | D40: Credito para RJ | E40: Elisa Agro | F40: 45343 | G40: =+YEAR(F40) -> 2024 | H40: Alvarez & Marsal | J40: Crédito de R$ 65 mm para plantio de algodão | K40: 21/02 - Recebemos as informações e fizemos o primeiro call para tirarmos dúvidas com a A&M. 22/02 -Pendente assinatura do NDA 23/02 - Vamos alinhar internamente 29/02 - Pendente do envio de novas solicitações 08/03 - Pendente de análise do Muller 18/03 - oportunidade negada | L40: 48.5 | M40: Christopher | N40: Não | P40: Oportunidade declinada devido: (I) a falta de previsibilidade da negociação do CRA e M&A; (II) O custo de financiamento para a operação de algodão nos pareceu caro quando comparado a margem media do algodão. (iii) Além do risco da safra
C41: =+C40+1 -> 33 | D41: Capital Solution | E41: Armazem do Grão | F41: 45342 | G41: =+YEAR(F41) -> 2024 | H41: JGP FA | J41: Hoje, o grupo totaliza 12 unidades entre Petrópolis, Teresópolis e Rio de Janeiro, e faturam mais de R$ 350 milhões. O efeito da pandemia do Covid-19, em conjunto com os investimentos feitos em 2020, deixou a cia com uma grande necessidade de caixa. Com isso, tomaram empréstimos que desequilibraram muito sua estrutura de capital | K41: 21/02 - Recebemos as informações do time JGP FA (Em análise) 04/03 - Pendente as informações de 2023 e entender a relação dos imóveis disponíveis 08/03 - Confirmar com o Fernando sobre a relação com Catalunha (PE) 15/03 - Alinhar o case com o Fernando na semana do dia 18/03 28/03 - FA recebeu os numeros de 2023 e irão nos enviar na semana que vem. Além disso, a Catalunha colocou uma proposta de deb. conversivel mas foi negado pelos acionistas 08/04 - Ainda não enviaram os números de 2023, vão enviar até 10/04 | M41: Mollica/Christopher | N41: On Hold
C42: =+C41+1 -> 34 | D42: Credito para RJ | E42: Brasfio | F42: 45345 | G42: =+YEAR(F42) -> 2024 | H42: Guilherme Sertorio | J42: Necessidade de captação de R$ 10mm, garantia de um imovel (não é da recuperanda) de R$ 25mm | K42: 04/03 - Sertorio enviará a informação. Estão descumprindo o plano, pendente de envio da matrícula do imóvel no MT. 08/03 - Luiza vai cobrar do Sertorio | M42: Luiza | N42: Não
C43: =+C42+1 -> 35 | E43: Odebrecht | G43: =+YEAR(F43) -> 1900 | H43: Lucas Cive | I43: Empresário / Executivo | J43: OBD quer vender creditos contra a prefeitura do RJ R$ 360mm | K43: Luiza marcará um call para entender melhor do crédito Em análise, porém dificilmente seguiremos para uma proposta 08/03 e 15/03 - Vamo conversar internamente sobre um possivel litigation finance 01/04 - estão revalidando nosso NDA e informações dos imóveis, vamos tentar fazer uma operação estruturada com 2 imóveis. 08/04 - estamos cobrando o NDA 15/04- Pendente de recebimento de informações | M43: Luiza | N43: não | P43: Não houve devolutiva do Lucas (CFO da OBD)
C44: =+C43+1 -> 36 | D44: Credito para Empresa | E44: Laticinios Damare | G44: =+YEAR(F44) -> 1900 | H44: Paulo Viola | J44: - | K44: 26/02 - Oportunidade enviada pelo Paulo Viola (em análise) 15/03 - Preparar um q&a inicial para entender se vamos seguir olhando ou não 19/03 - solicitamos ao viola que nos envie a relação de garantias que estão disponíveis para collateralizar o empréstimo | L44: 120 | M44: Christopher | N44: Não | P44: 25/03 - Oportunidade declinada devido: (i) somente 1 garantia com valor de laudo de R$ 50mm, sendo o emprestimo de 120mm; (ii) Do valor total de empréstimo, 70mm estavam negociados com a SICOOB, com a garantia operacional
C45: =+C44+1 -> 37 | D45: Precatório | E45: Usina Santa Lydia | F45: 45349 | G45: =+YEAR(F45) -> 2024 | H45: Souto Correa | I45: Advogado | J45: - | K45: 28/02 - É um daqueles casos bilionários, embora aparentemente já tenham alguns depósitos nos autos. 15/03- Rafael esta buscando mais detalhes | M45: Luiza / Hugo | N45: Não | P45: Não vamos seguir por SS
C46: =+C45+1 -> 38 | D46: NPL | E46: Leilão de Atacado | F46: 45350 | G46: =+YEAR(F46) -> 2024 | H46: Itau BBA | J46: - | K46: 28/02 - Leilão está marcado para o dia 08 de abril, e receberão as propostas até as 11hs 08/03 - Prioridade para semana (11/03) 15/03 - mto crédito pequeno para analisar e definir um go no go até final da semana que vem 01/04 - Itau marcou uma reunião amanha 02/04 para repassarmos os créditos 08/04 - Enviamos a proposta para VC Facilitador. Pendente de fechar o contrato de cessão com a VC 15/04 - Em conversas com o Itau, Ricardo Quass esta tentando tirar desse leilao do itau e colocar no próximo (aguardar) | M46: Luiza | N46: não | P46: Itau recebeu uma proposta maior e seguiu com a proposta
C47: =+C46+1 -> 39 | D47: Precatório Sergipe | E47: Herílio Gomes da Silva | F47: 45358 | G47: =+YEAR(F47) -> 2024 | H47: DJA Invest | J47: Não Alimentar - Administrativo | K47: 07/03 - Crédito de R$ 1.3mm (valor histórico) 08/03 - sinalizamos 25% PU, podendo receber em 3 anos, pendente de resposta | M47: Luiza | N47: Não | P47: Demos preço e não tivemos resposta da DJA Invest. Valor pequeno
C48: =+C47+1 -> 40 | D48: Precatorio Estado de SP | E48: Sociedade Agricola Cabreúva | F48: 45364 | G48: =+YEAR(F48) -> 2024 | H48: JGP FA | J48: Precatório Inscrito | K48: 15/03 - Hugo pegou as cópias e informações, pendente de checar a conformidade processual e envio dos parametros para modelagem | L48: 21 | M48: Hugo | N48: Não | P48: 15/03 - Não tem o precatório expedido, há discussão
C49: =+C48+1 -> 41 | D49: Precatorio TO | E49: Jerimias Demito | F49: 45366 | G49: =+YEAR(F49) -> 2024 | H49: Jus Precatórios | I49: Broker | K49: 14/03 - Colocamos proposta de R$6.5mm, pendente de respostas 01/04- Cobramos resposta do originador, acha que o precatorio esta em 10mm entao o desagio seria mto grande 26/04 - Jeremias não esta com necessidade de CP, vamos precificar 20/05 - Vamos precificar outros 2 precatorios. Tocantins está aberto a acordo de 60% 18/06 - Precificamos e enviamos o valor indicativo para o broker 01/07 - Pendente de retorno da Luana, estamos segurando isso para dar uma resposta para data traffic 22/07 - Enviamos proposta para os precatorios da Data Traffic (STAND-BY) | M49: Hugo | N49: On Hold
C50: =+C49+1 -> 42 | D50: Tunepe | E50: Leopoldinense | F50: 45366 | G50: =+YEAR(F50) -> 2024 | H50: Alex Giglio | K50: 15/03 - Entender o risco de ser IVR 22/03 - Enviamos uma proposta de 33% do vf, aguardando resposta 01/04 - Precatorios expedidos com bloqueio Reconsiderar o preço, pagando algo na frente e pagando mais quando houver o transito em julgado da impugnação Perguntar para a Siguler como precificariam nesse caso, entraríamos juntos nessa oportunidade 15/04 - precificamos uma nova proposta, pendente de envio. Vamos enviar primeiro o Tunepe Santa Isabel, caso não saia, seguiremos com esse 30/04 - Cobrar o Alex para entender os próximos passos | L50: 52 | M50: Hugo / Christopher | N50: Não | P50: 07/05 - Expediu precatorio, perdeu valor para SS.
C51: =+C50+1 -> 43 | D51: Crédito para RJ | E51: Vitalmar | F51: 45366 | G51: =+YEAR(F51) -> 2024 | H51: JGP FA | J51: Empresa de pescados e frutos do mar em recuperação judicial | K51: 15/03 - recebemos as informações, vamos fazer um primeiro filtro e voltar com o time FA Itau disposto a vender o crédito deles (dominam a classe II) 04/04 - Tivemos uma reunião com a Cia e com o Itau, vamos aguardar o envio de demais infos (projeções, BP, resultados 1t24) até dia 09/04. 09/04 - Esperar resultado do leilão do Itau. 30/04 - Almoço da Luiza com o Itau para saber o resultado do leilao 03/06 - Reunião para update de status dia 04/06 07/06 - Irão enviar as informações ao decorrer dessa semana | M51: Christopher | N51: On Hold
C52: =+C51+1 -> 44 | D52: Precatórios | E52: Aspometron | F52: 45365 | G52: =+YEAR(F52) -> 2024 | H52: WhatsApp | J52: Precatórios da Aspometron orçamento 2024 | K52: 14/03 -Consideramos uma proposta de 65% do valor de face, pendente de envio da potencial proposta. Pendente de resposta. 01/04 - antes de seguir devemos fazer o levantamento do que aconteceu com os recursos e contas judiciais novas. 15/04 - Originador falou que há fundos oferecendo 75% em precatorios federais 2024. | L52: 40 | M52: Hugo | N52: Não | P52: Originador falou que há fundos oferecendo 75% em precatorios federais 2024.
C53: =+C52+1 -> 45 | D53: Precatório Tocantis | E53: Agropecuaria Sao Jeronimo | F53: 45365 | G53: =+YEAR(F53) -> 2024 | H53: WhatsApp | K53: 14/03 -Consideramos uma proposta de 60% do valor de face, pendente de envio da potencial proposta | L53: 61 | M53: Hugo | N53: Não | P53: 09/04 - Expectativa de preço era maior que os 60% oferecidos
C54: =+C53+1 -> 46 | D54: Precatórios Tocantis | E54: Altamiro | F54: 45365 | G54: =+YEAR(F54) -> 2024 | H54: WhatsApp | K54: 14/03 -Consideramos uma proposta de 60% do valor de face, pendente de envio da potencial proposta. 01/04 - Pendente de devolutiva do originador sobre a proposta indicativa 02/04 - Vendedor recusou, achou muito abaixo do que esperava (queria 80%) | L54: 7.4 | M54: Hugo | N54: Não | P54: 02/04 - Vendedor recusou, achou muito abaixo do que esperava (queria 80%)
C55: =+C54+1 -> 47 | D55: Precatório DF | E55: APA Net Informática | F55: 45365 | G55: =+YEAR(F55) -> 2024 | H55: Gregory Pagot | L55: 0.225 | N55: Não
C56: =+C55+1 -> 48 | D56: Apresentação de Special Sits | F56: 45366 | G56: =+YEAR(F56) -> 2024 | K56: 15/03 -Mauricio pediu que atualizassemos a apresentação para enviarmos aos players que tivemos reunião essa semana 01/04 - atualizar a tir do estrut. III 07/06 - Dividimos a apresentação e vamos enviar uma primeira versão até 14/06. 04/07 - Dividimos apresentação com o Mauricio, ja realizou alguns comentários | M56: Hugo / Christopher | N56: Concluído
C57: =+C56+1 -> 49 | D57: Precatorio TO | E57: Concremat | F57: 45366 | G57: =+YEAR(F57) -> 2024 | H57: Originação Própria | K57: 01/04 - Passamos a mesma proposta de Altamiro (60%), estamos aguardando resposta da Diretoria. 08/04 - Aguardando resposta da diretoria | M57: Hugo | N57: Não | P57: 07/05 - Não tivemos resposta da diretoria
C58: =+C57+1 -> 50 | D58: Claim | E58: Technion x Petrobras | F58: 45366 | G58: =+YEAR(F58) -> 2024 | H58: Pedro Cavalcanti Rafael Solon | I58: Companhia | J58: 13/08 - Deve entrar em RJ, vamos ver se conseguimos comprar o CRI com deságio | K58: 01/04 - Aguardando resposta do Rafael Solon 02/05 - Modelagem enviada no grupo 27/05 - Enviaremos uma proposta indicativa 17/06 - Vamos pegar um update com o Solon sobre o caso 31/07 - Reprecificar baseado no acordao 04/08 - Enviamos nova proposta 13/08 - Vamos discutir uma RJ | M58: Hugo e Christopher | N58: Não | O58: 45889 | P58: 20/08 - Daria para entrar comprando o CRI mas teria que brigar com condominio. Garantido por CF de recebivel de estacionamento e loja. Teria pouco desagio no CRI | Q58: x
C59: =+C58+1 -> 51 | E59: Jailton - Quero meus direitos | F59: 45366 | G59: =+YEAR(F59) -> 2024 | H59: JGP FA | N59: Não | P59: Declinamos por não estar alinhado com o fundo de SS.
C60: =+C59+1 -> 52 | D60: Crédito para RJ | E60: Usina Ester | F60: 45366 | G60: =+YEAR(F60) -> 2024 | H60: JGP FA | K60: 17/04 - Analisamos algumas informações e enviamos email para o broker com algumas dúvidas, pendente de resposta 06/05 - Julia alertou sobre um possivel risco de fraude da operação - entender | M60: Christopher | N60: Não | P60: 05/06 - Setor que nao ficamos mto confortavel, poucas garantias, alem da capacidade de pgto da Cia.
C61: =+C60+1 -> 53 | D61: Tunepe | E61: Pelotas | F61: 45366 | G61: =+YEAR(F61) -> 2024 | H61: Thomas | I61: Advogado | K61: Ainda não desceu do STJ, precisamos alinhar com o Thomas. | M61: Luiza | N61: Não | P61: Ainda não tem transito em julgado
C62: =+C61+1 -> 54 | D62: Acordo de negociação das fazendas | F62: 45366 | G62: =+YEAR(F62) -> 2024 | H62: Thomas | I62: Advogado | N62: Não | P62: Dívida maiores que o esperado
C63: =+C62+1 -> 55 | D63: Legal Claim | E63: Roglio | F63: 45366 | G63: =+YEAR(F63) -> 2024 | H63: Thomas | I63: Advogado | K63: 01/04 - Thomas sugeriu marcarmos uma reuniao com os clientes e Will (JGP FA) 30/04 - Laudo pouco conclusivo 20/05 - Empresa no RS | M63: JGP FA | N63: On Hold
C64: =+C63+1 -> 56 | D64: Carteira | E64: Carteira da Quadra | F64: 45366 | G64: =+YEAR(F64) -> 2024 | H64: Quadra | M64: Luiza | N64: Não
C65: =+C64+1 -> 57 | D65: Carteira de Real Estate | E65: Madureira Shopping | F65: 45366 | G65: =+YEAR(F65) -> 2024 | H65: Advogado | K65: 15/04- Vamos analisar se há algum crédito relevante | M65: Luiza | N65: Não | P65: 15/04 - Carteira pulverizada, créditos antigos e credores complicados (pizzaria, lojas de colchão)
C66: =+C65+1 -> 58 | D66: Crédito | E66: Agrovaz | F66: 45377 | G66: =+YEAR(F66) -> 2024 | H66: Paulo Viola | K66: Produtor rural precisando de financiamento de até 20MM, onde oferece como garantia um imovel rural (matricula anexo) avaliado em 20MM (17mil/hectare) na região do Tocantins | L66: 20 | M66: Christopher | N66: Não | P66: 26/04 - Voltamos com o viola informando que precisamos ter numeros organizados, minimamente com DFs confiáveis. Recebemos somente um excel com o compliado dos números até os custos.
C67: =+C66+1 -> 59 | E67: UTC | F67: 45366 | G67: =+YEAR(F67) -> 2024 | H67: BlueOak | K67: Pendente de retorno | N67: Não | P67: Prazo longo demais para o fundo e o valor sendo mto inferior ao que queriam garantir
C68: =+C67+1 -> 60 | E68: Westin | F68: 45366 | G68: =+YEAR(F68) -> 2024 | K68: Potencial acordo para o Erair | N68: Não | P68: Não vamos seguir por SS
C69: =+C68+1 -> 61 | D69: Litigation | E69: Tonay Advogados | F69: 45366 | G69: =+YEAR(F69) -> 2024 | H69: Tonay Advogados | I69: Advogado | K69: Mediação para saída do sócio 01/04 - Vamos retornar para o sócio do Tonay | M69: Luiza | N69: Não | P69: Não vamos seguir por SS
C70: =+C69+1 -> 62 | D70: Claim | E70: Pontec | F70: 45366 | G70: =+YEAR(F70) -> 2024 | H70: Mauro Teixeira (Galdino) | I70: Advogado | K70: 01/04 - Precisamos fazer a proposta e refinar o 750mil, devemos incluir no preço esse valor. 09/04 - Diligência finalizada, esperando Bernardo enviar. Hugo vai conversar com a Mellon sobre próximos passos e vamos preparar a apresentação para o comitê 15/04 - Comitê aprovado, ja investimos 750k, vamos liquidar os 4.5mm até dia 29 29/04 - Liquidamos os R$ 750k, vamos liquidar o R$ 4.5mm do restante do investimento até o fim dessa semana (03/05) 04/06 - Contratar advogado para tocar a causa e alterar a confissão de dívida 17/06 - Assinar o instrumento de transação 01/07 - Contratar advogado | N70: Concluído
C71: =+C70+1 -> 63 | D71: Crédito para RJ | E71: Usina Aysu | F71: 45366 | G71: =+YEAR(F71) -> 2024 | H71: JGP FA | K71: 20/03 - Solicitamos informações adicionais que ainda não tivemos resposta do time de Vela Capital 26/03 - Vela Capital nos retornou afirmando que a cia já conseguiu realizar a captação | M71: Mollica | N71: Não | P71: 26/03 - Vela Capital nos retornou afirmando que a cia já conseguiu realizar a captação
C72: =+C71+1 -> 64 | D72: Legal Claims | E72: Eletrobras | F72: 45366 | G72: =+YEAR(F72) -> 2024 | H72: JGP FA | K72: Desejam 71% do vf | M72: Luiza | N72: Não | P72: Desejam 71% do vf, já negado
C73: =+C72+1 -> 65 | D73: Precatório Federal | E73: Agropecuaria Tapirapuan | F73: 45366 | G73: =+YEAR(F73) -> 2024 | H73: Raphael Martins (Souto Correa) | K73: 27/03 - Indicamos no grupo uma potencial proposta variando o % do VF de 70% - 75%, pendente de envio da proposta 01/04 - Cobramos uma resposta do Raphael Martins 09/04 - Raphael voltou com 71% de vf + 2% upfront - vamos validar | L73: 16.7 | M73: Luiza | N73: Não | P73: Por estrategia interna não olharemos os precatorios federais
C74: =+C73+1 -> 66 | D74: Precatório Municipal | E74: Espólio Egon Koses | F74: 45370 | G74: =+YEAR(F74) -> 2024 | H74: Francisco Carneiro | J74: Precatório Municipal de Pinhais | K74: 19/03- Recebemos a oportunidade pelo AAI da GPX Investimentos - Pendente de análise | L74: 9.07 | M74: Hugo | N74: Não | P74: 08/04 - Esse precatório sozinho é mais que metade de tudo que foi pago nos ultimos 2 anos
C75: =+C74+1 -> 67 | D75: Precatório Federal | E75: Serruya | F75: 45370 | G75: =+YEAR(F75) -> 2024 | H75: JGP FA | I75: Consultoria | J75: Precatório Federal de Belem do Pará | K75: 22/03 - Serruya, ao que tudo indica, ainda não foi migrado (tipo Trimonte, saiu requisitório, mas não migrou). Inviável 12.5mio para 2025 (ou 2026). 01/04 - Vamos aguardar a data limite para definição do pagamento em 2025 04/04 - Considerarmos 12.5mm (59% vf). TIR Líquida ~29%. | L75: 18.9 | M75: Hugo | N75: Não | P75: 09/04 - Preço inicial solicitado é maior que os R$ 12.5mm que oferecemos, o que torna a operação pouco atrativa para SS.
C76: =+C75+1 -> 68 | D76: Precatório Federal | E76: Sindicato | F76: 45376 | G76: =+YEAR(F76) -> 2024 | H76: Thiago Peixoto (Ferro) | I76: Advogado | J76: Precatório Federal de Maceio, Alagoas (Sindicato dos Servidores) | K76: 26/03 - Indicamos uma proposta para o Thiago de 76% do vf e 1% upfront para advogados. Ainda não mencionamos o possível exito para o broker. 09/04 - Aguardando retorno do Thiago sobre a proposta do BTG mas ja sinalizamos que não seguiremos se não houver evidencias da proposta de 75%. | L76: TBD | M76: Luiza | N76: Não | P76: Por estrategia interna não olharemos os precatorios federais
C77: =+C76+1 -> 69 | D77: Precatório Estadual | E77: Família Popescu | F77: 45377 | G77: =+YEAR(F77) -> 2024 | H77: JGP FA | J77: Precatório Estadual de São Paulo | K77: 01/04 - Aguardando resposta da FA sobre a origem da oportunidade | L77: 24.5 | M77: Hugo | N77: Não | P77: 05/04 - papel foi vendido para outra casa.
C78: =+C77+1 -> 70 | D78: Precatório Federal | E78: Hidronorte | F78: 45377 | G78: =+YEAR(F78) -> 2024 | H78: JGP FA | J78: Precatório Federal de Londrina | K78: 01 /04 - Saque a partir de 1/mar/24 - precatorio pago | L78: 18.5 | M78: Luiza | N78: Não | P78: 09/04 - precatorio pago
C79: =+C78+1 -> 71 | D79: DIP | E79: BS Tecnologia | F79: 45384 | G79: =+YEAR(F79) -> 2024 | H79: Dauricio Advogados | J79: Como mencionado, a BS Tecnologia e Serviços está atualmente em processo de recuperação judicial, devido às dificuldades enfrentadas durante a pandemia de Covid-19, que resultaram em uma crise econômico-financeira. | K79: 08/04 - Em análise | L79: 5 | M79: Christopher | N79: Não | P79: Nao tivemos atualização do case
C80: =+C79+1 -> 72 | D80: Precatório Federal Brasilia | E80: Cia Açucareira Vale do Ceará Mirim | F80: 45379 | G80: =+YEAR(F80) -> 2024 | H80: JGP FA | K80: 28/03 - Precatorio enviado pela FA, transito em julgado | L80: 447.9 | M80: Luiza | N80: Não
C81: =+C80+1 -> 73 | D81: Sugestão de Parceria | E81: Wlademir Aguiar | F81: 45383 | G81: =+YEAR(F81) -> 2024 | J81: Enviou uma solicitação pelo RI para fecharmos potencial parceria | N81: Não | P81: Responder o email agradecendo e pedindo a oportunidade que ele tem para passar para nós.
C82: =+C81+1 -> 74 | D82: Capital de Giro | E82: Marimex | F82: 45390 | G82: =+YEAR(F82) -> 2024 | H82: Vega Asset | J82: Nota comercial de R$160M, para capital de giro e necessidades de curto prazo da companhia | K82: 08/04 - Em análise 15/04 - vamos aguardar a Vega enviar mais informações 30/04 - Vamos cobrar as infos da Vega 13/05 - Até o momento Vega so possui o teaser também | L82: 160 | M82: Christopher/Luiza | N82: On Hold
C83: =+C82+1 -> 75 | D83: Legal Claim | E83: Rio Turia (Bunge) | G83: =+YEAR(F83) -> 1900 | K83: 09/04 - Ainda sem parametro para precificação, aguardando conclusão da fase de liquidação 15/04 - Vamos responder ao Bruno Vilar que não conseguiremos precificar nesse momento | M83: Luiza | N83: On Hold
C84: =+C83+1 -> 76 | D84: Legal Claim | E84: Cesp (Argila) - Cerâmica da Fonte | G84: =+YEAR(F84) -> 1900 | K84: 09/04 - Expectativa do credor é elevada em relação ao preço, continuaremos monitorando a oportunidade. 15/04 - Sentença homologando o laudo, vamos esperar pra ver se as partes irão agravar | M84: Hugo | N84: Não
C85: =+C84+1 -> 77 | D85: Tunep | E85: Santa Izabel | F85: 45387 | G85: =+YEAR(F85) -> 2024 | K85: 08/04 - Em análise 11/04 - Enviamos proposta, aguardando resposta 30/04- Proposta nao aprovada por 1 diretor, para seguir precisaria da aprovação total | L85: 29.4 | M85: Christopher/Hugo | N85: Não | P85: 30/04 - Proposta nao aprovada por 1 diretor, para seguir precisaria da aprovação total
C86: =+C85+1 -> 78 | D86: Compra de Créditos | E86: Yara | F86: 45322 | G86: =+YEAR(F86) -> 2024 | H86: José Afonso (VBSO) | J86: Créditos detidos pela Yara decorrente de inadimplementos no pagamento de insumos agrícolas | K86: 02/02 - Baixar os processos indicados na apresentação Luiza analisando os relatórios da Yara 04/03 - Luiza marcou um call (06/03) sobre o processo Emgual . Os demais casos não se mostraram interessantes 08/03 - Luiza vai cobrar o Lapa (ARC) 15/03 - Retorno do Lapa até 10/abr | M86: Luiza | N86: Não | P86: 07/05 - sem retorno
C87: =+C86+1 -> 79 | D87: Capital de Giro | E87: DFG Agro | F87: 45386 | G87: =+YEAR(F87) -> 2024 | H87: Thales Neves (Zeal Soluçoes) | J87: Eles devem na casa de 250MM (total), e em aberto 40/50MM de 2023 e início 2024. Tem patrimonio, querem resolver, precisam de folego, mas precisamos limpar os atrasados, carência e prazo com boas garantias para alongar o caixa dele.Eles devem na casa de 250MM (total), e em aberto 40/50MM de 2023 e início 2024. | K87: 08/04 - Em análise 12/04 - Solicitamos uma reunião com a Cia, pendente de resposta 06/05 - Esse ativo estava no fundo da galapagos GCRA11 e também não houve o pagamento da parcela CPR-F e tb do CRA 112 | M87: Christopher | N87: Não
C88: =+C87+1 -> 80 | D88: Precatórios | E88: Bruno Ribeiro | G88: =+YEAR(F88) -> 1900 | H88: Bruno Ribeiro | K88: 08/04 - Bruno mandou diversos precatórios, precisamos voltar 30/04 - Luiza vai marcar um call com o Bruno | M88: Luiza | N88: Não
C89: =+C88+1 -> 81 | D89: Precatorio | E89: Maxpel | F89: 45385 | G89: =+YEAR(F89) -> 2024 | J89: Precatorio Federal Amazonas | K89: 04/04 - Precificamos a vf de 70%, TIR de 17% | L89: 6.7 | M89: Luiza | N89: Não | P89: 09/04 - Valor baixo para SS
C90: =+C89+1 -> 82 | D90: DIP | E90: Medlife | F90: 45391 | G90: =+YEAR(F90) -> 2024 | H90: Santander | J90: Hospitais em Volta Redonda, olhando as ações e a RJ | K90: 09/04 - Estamos olhando as ações e a RJ. Vamos tentar conversar direto com o advogado da Medlife (Chamme) 30/04 - Santander quer um preço alto e o principal sócio nao tem um bom track record | M90: Luiza | N90: Não
C91: =+C90+1 -> 83 | D91: DIP | E91: OI | G91: =+YEAR(F91) -> 1900 | H91: Cross Sell | I91: Outros | K91: 08/04 - Em análise 29/04 - Buscar cotações TRS mas estamos limitados para o Est.III. 17/06- aguardando resposta do BBM sobre o TRS | L91: 29.4 | M91: Mollica | N91: On Hold
C92: =+C91+1 -> 84 | D92: Compra de Debentures | E92: Aeris | F92: 45390 | G92: =+YEAR(F92) -> 2024 | H92: Cross Sell | I92: Outros | K92: 17/04 - Vamos aguardar a divulgação de resultado no dia 15/05. 16/05 - Compramos AERIS R$ 2mm | L92: 2 | M92: Luiza/Christopher | N92: Concluído | P92: 0.67 AERI11 @DI+18.99% 1.33 AERI 12 @DI+18.99%
C93: =+C92+1 -> 85 | D93: NPL do Itau | E93: Grupo Isdra | G93: =+YEAR(F93) -> 1900 | H93: Itau BBA | K93: 09/04 - Itau vai enviar as informações 29/04 - Leilao postergado para 16.05 30/04 - Thomas respondeu as duvidas que enviamos para ele, Luiza vai conversar 07/05 - Marcar uma conversa com o Putinato e Eduardo Isdra. 20/05 - Empresa no RS | M93: Christopher | N93: Não
C94: =+C93+1 -> 86 | D94: Precatório Federal | E94: Usina Capricho | F94: 45390 | G94: =+YEAR(F94) -> 2024 | H94: JGP FA | K94: 08/04 - Em análise | L94: 1639 | M94: Luiza | N94: Não | P94: Não gostamos da tese IAA e evitamos precatórios em valores superiores a R$ 100mm
C95: =+C94+1 -> 87 | D95: Carteira de Crédito | E95: Santader | F95: 45397 | G95: =+YEAR(F95) -> 2024 | H95: Santander | K95: 30/04 - Vamos olhar o VDR | M95: Bernardo | N95: Não | P95: 20/05 - Poucos nomes interessantes, porem devido o prazo da proposta Binding e o tempo da carteira, decidimos não seguir
C96: =+C95+1 -> 88 | D96: Compra de Créditos do CS | E96: Tuper | F96: 45401 | G96: =+YEAR(F96) -> 2024 | H96: Credit Suisse | J96: Empresa processadora de aço, que o CS esta vendendo, como plano de desinvestimento, 18 CCEs de USD 6.6MM | K96: 19/04 - Tivemos um primeiro call na semana passada. Vamos ter uma conversa com a Cia dia 24/04. 30/04 - Nova conversa com a cia para entender alguns pontos Proposta non binding até dia 08.05 06/05 - Pendente de recebimento de algumas infos (IR dos Socios, estrategia para divida de curto prazo, explicação dos mutuos) | L96: =6.6*5 -> 33 | M96: Christopher/Mollica | N96: Não | P96: 15/05- BID mto abaixo dos outros recebidos
C97: =+C96+1 -> 89 | D97: Crédito | E97: Hospital Geral El Kadri | F97: 45401 | G97: =+YEAR(F97) -> 2024 | H97: Iron Capital | I97: Consultoria | J97: 80mm de divida sendo 48mm fazenda nacional 10mm banco 7mm de fornecedores 3mm de medicos, nao pagaram impostos Renegociaram para 12.5mm, negociaçao direto com pgfn, 120x, negociou uma parcela um pouco menor e dps principal e juros | K97: 19/04 - Tivemos uma primeira conversa com o assessor, estão buscando 50mm Recebemos acesso ao data room, começar a analisar Fernando vai entender melhor do mercado de saude em campo grande | L97: 50 | M97: Christopher/Mollica | N97: Não | P97: 07/06 - Negamos a oportunidade pois alem do custo de retrofit da operação ser mto caro (Special Sits), entendemos que o HGEK não esta bem posicionado, devido a presença de Unimed e Rede Dor no MS.
C98: =+C97+1 -> 90 | D98: Crédito | E98: Brandili | F98: 45401 | G98: =+YEAR(F98) -> 2024 | H98: Manchester Investimentos | J98: Atividade principal é a fabricação e comercialização de produtos da indústria de fiação, tecelagem e malharia de confecção em geral, representação comercial, locação de imóveis próprios e participação em outras sociedades | K98: 19/04 - Recebemos a oportunidade pela Carla. A cia possui 2 imóveis para composição de garantias reais. Planta com matrículas separadas (4057 e 11851) em Apiúna/SC e o outro imóvel que é da Associação da Brandili. O Presidente da empresa mencionou que caso haja necessidade, poderá complementar garantias com um imóvel residencial localizado em Balneário Camboriú/SC. Este ainda não tenho os documentos. 29/05 - Solicitamos algumas infos adicionais, pendente de resposta 06/06 - Recebemos as respostas, vamos analisar 14/06 - Estamos agendando um call para inicio da semana 01/07 - Call agendado com a Companhia às 14h 04/07 - Enviaram novas infos, porém entendemos que não é um case de SS | L98: 50 | M98: Christopher/Mollica | N98: Não | P98: 19/07 - Entendemos nao ser um case de SS, pois ja reperfilaram grande parte da divida de CP a taxas mais atrativas. Encaminhamos para a FA, porém a Manchester já bateu o mercado e não aceitaram M&A que poderia levar a um kicker do nosso lado
C99: =+C98+1 -> 91 | D99: Precatório Estadual | E99: Precatorio Estadual da Bahia | F99: 45401 | G99: =+YEAR(F99) -> 2024 | H99: JGP FA | K99: 24/04 - Enviado pela FA - precatório de 300 MM do estado da Bahia. Cliente quer 55%, mas aceita proposta | L99: 130 | N99: Não | P99: Ja avisamos a FA que a fila de pagamento da Bahia é ruim.
C100: =+C99+1 -> 92 | D100: Ativos Judiciais | F100: 45401 | G100: =+YEAR(F100) -> 2024 | H100: Placido Castelo | L100: 126 | N100: Não | P100: Oportunidades não são boas. Não há crédito, é uma declaratória.
C101: =+C100+1 -> 93 | D101: Crédito | E101: João Felipe Jucá | F101: 45415 | G101: =+YEAR(F101) -> 2024 | H101: João Felipe Jucá | J101: Mandatado para duas oportunidades que podem se encaixar para o fundo : recebíveis de aproximadamente R$ 34 MM de uma empresa de saúde contra ente público, e um shopping no Nordeste. Aguardo o contato para apresentar essas oportunidades para avaliação. | M101: Luiza | N101: Não | P101: Ativos não faziam sentido para SS.
C102: =+C101+1 -> 94 | D102: Precatório Estadual | E102: TIGRE | F102: 45419 | G102: =+YEAR(F102) -> 2024 | H102: Bruno Ribeiro | K102: 07/05 - Já passamos uma proposta indicativa de 40%, entender melhor sobre o pagamento do estado de SP. | M102: Luiza | N102: Não | P102: Não tivemos devolutiva há mais de 1 mês
C103: =+C102+1 -> 95 | D103: Crédito | E103: Casa Bahia | F103: 45419 | G103: =+YEAR(F103) -> 2024 | H103: Alvarez & Marsal | J103: Dar uma saída para o passivo trabalhista e FIDC de crediário | K103: 07/05 - Vamos falar na semana que vem (14/05) | N103: Não
C104: =+C103+1 -> 96 | D104: Crédito | E104: Dia Supermercados | F104: 45419 | G104: =+YEAR(F104) -> 2024 | H104: Alvarez & Marsal | J104: Operação com os fornecedores | K104: 07/05 - Vamos falar na semana que vem (14/05) | N104: Não
...

Sheet Originadores
F2: Casos Trazidos
C3: # | D3: Originador | E3: Tipo de Originador | F3: 2024 | G3: =+F3+1 -> 2025 | H3: =+G3+1 -> 2026
C4: 1 | D4: 18IB | E4: Boutique | F4: =COUNTIFS(Pipe!$H:$H,Originadores!$D4,Pipe!$G:$G,Originadores!F$3) -> 0 | G4: =COUNTIFS(Pipe!$H:$H,Originadores!$D4,Pipe!$G:$G,Originadores!G$3) -> 1 | H4: =COUNTIFS(Pipe!$H:$H,Originadores!$D4,Pipe!$G:$G,Originadores!H$3) -> 0
C5: =+C4+1 -> 2 | D5: 3A Investimentos | E5: Broker | F5: =COUNTIFS(Pipe!$H:$H,Originadores!$D5,Pipe!$G:$G,Originadores!F$3) -> 1 | G5: =COUNTIFS(Pipe!$H:$H,Originadores!$D5,Pipe!$G:$G,Originadores!G$3) -> 0 | H5: =COUNTIFS(Pipe!$H:$H,Originadores!$D5,Pipe!$G:$G,Originadores!H$3) -> 0
C6: =+C5+1 -> 3 | D6: Acacio | E6: Broker | F6: =COUNTIFS(Pipe!$H:$H,Originadores!$D6,Pipe!$G:$G,Originadores!F$3) -> 1 | G6: =COUNTIFS(Pipe!$H:$H,Originadores!$D6,Pipe!$G:$G,Originadores!G$3) -> 0 | H6: =COUNTIFS(Pipe!$H:$H,Originadores!$D6,Pipe!$G:$G,Originadores!H$3) -> 0
C7: =+C6+1 -> 4 | D7: Aeté | E7: Advisor | F7: =COUNTIFS(Pipe!$H:$H,Originadores!$D7,Pipe!$G:$G,Originadores!F$3) -> 0 | G7: =COUNTIFS(Pipe!$H:$H,Originadores!$D7,Pipe!$G:$G,Originadores!G$3) -> 1 | H7: =COUNTIFS(Pipe!$H:$H,Originadores!$D7,Pipe!$G:$G,Originadores!H$3) -> 0
C8: =+C7+1 -> 5 | D8: Adriane Bueno | E8: Broker | F8: =COUNTIFS(Pipe!$H:$H,Originadores!$D8,Pipe!$G:$G,Originadores!F$3) -> 0 | G8: =COUNTIFS(Pipe!$H:$H,Originadores!$D8,Pipe!$G:$G,Originadores!G$3) -> 0 | H8: =COUNTIFS(Pipe!$H:$H,Originadores!$D8,Pipe!$G:$G,Originadores!H$3) -> 1
C9: =+C8+1 -> 6 | D9: AGI | E9: Consultoria | F9: =COUNTIFS(Pipe!$H:$H,Originadores!$D9,Pipe!$G:$G,Originadores!F$3) -> 0 | G9: =COUNTIFS(Pipe!$H:$H,Originadores!$D9,Pipe!$G:$G,Originadores!G$3) -> 2 | H9: =COUNTIFS(Pipe!$H:$H,Originadores!$D9,Pipe!$G:$G,Originadores!H$3) -> 0
C10: =+C9+1 -> 7 | D10: Alex Giglio | E10: Broker | F10: =COUNTIFS(Pipe!$H:$H,Originadores!$D10,Pipe!$G:$G,Originadores!F$3) -> 1 | G10: =COUNTIFS(Pipe!$H:$H,Originadores!$D10,Pipe!$G:$G,Originadores!G$3) -> 2 | H10: =COUNTIFS(Pipe!$H:$H,Originadores!$D10,Pipe!$G:$G,Originadores!H$3) -> 4
C11: =+C10+1 -> 8 | D11: Allievo | E11: Acionista | F11: =COUNTIFS(Pipe!$H:$H,Originadores!$D11,Pipe!$G:$G,Originadores!F$3) -> 0 | G11: =COUNTIFS(Pipe!$H:$H,Originadores!$D11,Pipe!$G:$G,Originadores!G$3) -> 3 | H11: =COUNTIFS(Pipe!$H:$H,Originadores!$D11,Pipe!$G:$G,Originadores!H$3) -> 0
C12: =+C11+1 -> 9 | D12: Alvarez & Marsal | E12: Consultoria | F12: =COUNTIFS(Pipe!$H:$H,Originadores!$D12,Pipe!$G:$G,Originadores!F$3) -> 9 | G12: =COUNTIFS(Pipe!$H:$H,Originadores!$D12,Pipe!$G:$G,Originadores!G$3) -> 10 | H12: =COUNTIFS(Pipe!$H:$H,Originadores!$D12,Pipe!$G:$G,Originadores!H$3) -> 4
C13: =+C12+1 -> 10 | D13: Andreia Alonso | E13: Broker | F13: =COUNTIFS(Pipe!$H:$H,Originadores!$D13,Pipe!$G:$G,Originadores!F$3) -> 1 | G13: =COUNTIFS(Pipe!$H:$H,Originadores!$D13,Pipe!$G:$G,Originadores!G$3) -> 0 | H13: =COUNTIFS(Pipe!$H:$H,Originadores!$D13,Pipe!$G:$G,Originadores!H$3) -> 0
C14: =+C13+1 -> 11 | D14: ANTONIO CARLOS AMORIM Advogados | E14: Advogado | F14: =COUNTIFS(Pipe!$H:$H,Originadores!$D14,Pipe!$G:$G,Originadores!F$3) -> 0 | G14: =COUNTIFS(Pipe!$H:$H,Originadores!$D14,Pipe!$G:$G,Originadores!G$3) -> 1 | H14: =COUNTIFS(Pipe!$H:$H,Originadores!$D14,Pipe!$G:$G,Originadores!H$3) -> 0
C15: =+C14+1 -> 12 | D15: Antonio Lacombe | E15: Empresário / Executivo | F15: =COUNTIFS(Pipe!$H:$H,Originadores!$D15,Pipe!$G:$G,Originadores!F$3) -> 1 | G15: =COUNTIFS(Pipe!$H:$H,Originadores!$D15,Pipe!$G:$G,Originadores!G$3) -> 0 | H15: =COUNTIFS(Pipe!$H:$H,Originadores!$D15,Pipe!$G:$G,Originadores!H$3) -> 1
C16: =+C15+1 -> 13 | D16: Antonio Marques (Refix) | E16: Broker | F16: =COUNTIFS(Pipe!$H:$H,Originadores!$D16,Pipe!$G:$G,Originadores!F$3) -> 0 | G16: =COUNTIFS(Pipe!$H:$H,Originadores!$D16,Pipe!$G:$G,Originadores!G$3) -> 1 | H16: =COUNTIFS(Pipe!$H:$H,Originadores!$D16,Pipe!$G:$G,Originadores!H$3) -> 0
... C26: =+C25+1 -> 23 | D26: Banco Santos | E26: Banco | F26: =COUNTIFS(Pipe!$H:$H,Originadores!$D26,Pipe!$G:$G,Originadores!F$3) -> 0 | G26: =COUNTIFS(Pipe!$H:$H,Originadores!$D26,Pipe!$G:$G,Originadores!G$3) -> 1 | H26: =COUNTIFS(Pipe!$H:$H,Originadores!$D26,Pipe!$G:$G,Originadores!H$3) -> 0
C27: =+C26+1 -> 24 | D27: Banco Votorantim | E27: Banco
C28: =+C27+1 -> 25 | D28: Barbara Cibele | E28: Empresário / Executivo | F28: =COUNTIFS(Pipe!$H:$H,Originadores!$D28,Pipe!$G:$G,Originadores!F$3) -> 0 | G28: =COUNTIFS(Pipe!$H:$H,Originadores!$D28,Pipe!$G:$G,Originadores!G$3) -> 1 | H28: =COUNTIFS(Pipe!$H:$H,Originadores!$D28,Pipe!$G:$G,Originadores!H$3) -> 0
C29: =+C28+1 -> 26 | D29: BB Asset | E29: Asset | F29: =COUNTIFS(Pipe!$H:$H,Originadores!$D29,Pipe!$G:$G,Originadores!F$3) -> 1 | G29: =COUNTIFS(Pipe!$H:$H,Originadores!$D29,Pipe!$G:$G,Originadores!G$3) -> 0 | H29: =COUNTIFS(Pipe!$H:$H,Originadores!$D29,Pipe!$G:$G,Originadores!H$3) -> 0
C30: =+C29+1 -> 27 | D30: Bocom BBM | E30: Banco | F30: =COUNTIFS(Pipe!$H:$H,Originadores!$D30,Pipe!$G:$G,Originadores!F$3) -> 0 | G30: =COUNTIFS(Pipe!$H:$H,Originadores!$D30,Pipe!$G:$G,Originadores!G$3) -> 0 | H30: =COUNTIFS(Pipe!$H:$H,Originadores!$D30,Pipe!$G:$G,Originadores!H$3) -> 1
C31: =+C30+1 -> 28 | D31: Beam Capital / Almeida Mota | E31: Broker | F31: =COUNTIFS(Pipe!$H:$H,Originadores!$D31,Pipe!$G:$G,Originadores!F$3) -> 0 | G31: =COUNTIFS(Pipe!$H:$H,Originadores!$D31,Pipe!$G:$G,Originadores!G$3) -> 0 | H31: =COUNTIFS(Pipe!$H:$H,Originadores!$D31,Pipe!$G:$G,Originadores!H$3) -> 3
C32: =+C31+1 -> 29 | D32: BeeCap | E32: Asset | F32: =COUNTIFS(Pipe!$H:$H,Originadores!$D32,Pipe!$G:$G,Originadores!F$3) -> 1 | G32: =COUNTIFS(Pipe!$H:$H,Originadores!$D32,Pipe!$G:$G,Originadores!G$3) -> 0 | H32: =COUNTIFS(Pipe!$H:$H,Originadores!$D32,Pipe!$G:$G,Originadores!H$3) -> 0
C33: =+C32+1 -> 30 | D33: BF Capital | E33: Broker | F33: =COUNTIFS(Pipe!$H:$H,Originadores!$D33,Pipe!$G:$G,Originadores!F$3) -> 0 | G33: =COUNTIFS(Pipe!$H:$H,Originadores!$D33,Pipe!$G:$G,Originadores!G$3) -> 0 | H33: =COUNTIFS(Pipe!$H:$H,Originadores!$D33,Pipe!$G:$G,Originadores!H$3) -> 1
C34: =+C33+1 -> 31 | D34: BFMB Partners | E34: Broker | F34: =COUNTIFS(Pipe!$H:$H,Originadores!$D34,Pipe!$G:$G,Originadores!F$3) -> 0 | G34: =COUNTIFS(Pipe!$H:$H,Originadores!$D34,Pipe!$G:$G,Originadores!G$3) -> 0 | H34: =COUNTIFS(Pipe!$H:$H,Originadores!$D34,Pipe!$G:$G,Originadores!H$3) -> 2
C35: =+C34+1 -> 32 | D35: BGF Capital | E35: Broker | F35: =COUNTIFS(Pipe!$H:$H,Originadores!$D35,Pipe!$G:$G,Originadores!F$3) -> 0 | G35: =COUNTIFS(Pipe!$H:$H,Originadores!$D35,Pipe!$G:$G,Originadores!G$3) -> 2 | H35: =COUNTIFS(Pipe!$H:$H,Originadores!$D35,Pipe!$G:$G,Originadores!H$3) -> 0
C36: =+C35+1 -> 33 | D36: BlueOak | E36: Asset | F36: =COUNTIFS(Pipe!$H:$H,Originadores!$D36,Pipe!$G:$G,Originadores!F$3) -> 1 | G36: =COUNTIFS(Pipe!$H:$H,Originadores!$D36,Pipe!$G:$G,Originadores!G$3) -> 0 | H36: =COUNTIFS(Pipe!$H:$H,Originadores!$D36,Pipe!$G:$G,Originadores!H$3) -> 0
C37: =+C36+1 -> 34 | D37: BNDES | E37: BNDES | F37: =COUNTIFS(Pipe!$H:$H,Originadores!$D37,Pipe!$G:$G,Originadores!F$3) -> 0 | G37: =COUNTIFS(Pipe!$H:$H,Originadores!$D37,Pipe!$G:$G,Originadores!G$3) -> 1 | H37: =COUNTIFS(Pipe!$H:$H,Originadores!$D37,Pipe!$G:$G,Originadores!H$3) -> 1
C38: =+C37+1 -> 35 | D38: Bruno Advogado | E38: Advogado | F38: =COUNTIFS(Pipe!$H:$H,Originadores!$D38,Pipe!$G:$G,Originadores!F$3) -> 0 | G38: =COUNTIFS(Pipe!$H:$H,Originadores!$D38,Pipe!$G:$G,Originadores!G$3) -> 1 | H38: =COUNTIFS(Pipe!$H:$H,Originadores!$D38,Pipe!$G:$G,Originadores!H$3) -> 0
C39: =+C38+1 -> 36 | D39: Bruno Ribeiro | E39: Broker | F39: =COUNTIFS(Pipe!$H:$H,Originadores!$D39,Pipe!$G:$G,Originadores!F$3) -> 4 | G39: =COUNTIFS(Pipe!$H:$H,Originadores!$D39,Pipe!$G:$G,Originadores!G$3) -> 0 | H39: =COUNTIFS(Pipe!$H:$H,Originadores!$D39,Pipe!$G:$G,Originadores!H$3) -> 0
C40: =+C39+1 -> 37 | D40: Bruno Sotter | E40: Consultoria | F40: =COUNTIFS(Pipe!$H:$H,Originadores!$D40,Pipe!$G:$G,Originadores!F$3) -> 0 | G40: =COUNTIFS(Pipe!$H:$H,Originadores!$D40,Pipe!$G:$G,Originadores!G$3) -> 0 | H40: =COUNTIFS(Pipe!$H:$H,Originadores!$D40,Pipe!$G:$G,Originadores!H$3) -> 0
C41: =+C40+1 -> 38 | D41: BTG | E41: Banco
C42: =+C41+1 -> 39 | D42: BX Capital | E42: Consultoria | F42: =COUNTIFS(Pipe!$H:$H,Originadores!$D42,Pipe!$G:$G,Originadores!F$3) -> 1 | G42: =COUNTIFS(Pipe!$H:$H,Originadores!$D42,Pipe!$G:$G,Originadores!G$3) -> 0 | H42: =COUNTIFS(Pipe!$H:$H,Originadores!$D42,Pipe!$G:$G,Originadores!H$3) -> 0
C43: =+C42+1 -> 40 | D43: Caique Melo / Aventos | E43: Empresário / Executivo | F43: =COUNTIFS(Pipe!$H:$H,Originadores!$D43,Pipe!$G:$G,Originadores!F$3) -> 1 | G43: =COUNTIFS(Pipe!$H:$H,Originadores!$D43,Pipe!$G:$G,Originadores!G$3) -> 0 | H43: =COUNTIFS(Pipe!$H:$H,Originadores!$D43,Pipe!$G:$G,Originadores!H$3) -> 0
C44: =+C43+1 -> 41 | D44: Captal - Bruno Bianchesi | E44: Broker | F44: =COUNTIFS(Pipe!$H:$H,Originadores!$D44,Pipe!$G:$G,Originadores!F$3) -> 0 | G44: =COUNTIFS(Pipe!$H:$H,Originadores!$D44,Pipe!$G:$G,Originadores!G$3) -> 1 | H44: =COUNTIFS(Pipe!$H:$H,Originadores!$D44,Pipe!$G:$G,Originadores!H$3) -> 0
C45: =+C44+1 -> 42 | D45: Carlos Coelho | E45: Broker | F45: =COUNTIFS(Pipe!$H:$H,Originadores!$D45,Pipe!$G:$G,Originadores!F$3) -> 0 | G45: =COUNTIFS(Pipe!$H:$H,Originadores!$D45,Pipe!$G:$G,Originadores!G$3) -> 0 | H45: =COUNTIFS(Pipe!$H:$H,Originadores!$D45,Pipe!$G:$G,Originadores!H$3) -> 2
C46: =+C45+1 -> 43 | D46: Carlos Libera | E46: Empresário / Executivo | F46: =COUNTIFS(Pipe!$H:$H,Originadores!$D46,Pipe!$G:$G,Originadores!F$3) -> 1 | G46: =COUNTIFS(Pipe!$H:$H,Originadores!$D46,Pipe!$G:$G,Originadores!G$3) -> 0 | H46: =COUNTIFS(Pipe!$H:$H,Originadores!$D46,Pipe!$G:$G,Originadores!H$3) -> 0
C47: =+C46+1 -> 44 | D47: Carlos Simão | E47: Empresário / Executivo | F47: =COUNTIFS(Pipe!$H:$H,Originadores!$D47,Pipe!$G:$G,Originadores!F$3) -> 0 | G47: =COUNTIFS(Pipe!$H:$H,Originadores!$D47,Pipe!$G:$G,Originadores!G$3) -> 1 | H47: =COUNTIFS(Pipe!$H:$H,Originadores!$D47,Pipe!$G:$G,Originadores!H$3) -> 0
C48: =+C47+1 -> 45 | D48: Castro Barros | E48: Advogado | F48: =COUNTIFS(Pipe!$H:$H,Originadores!$D48,Pipe!$G:$G,Originadores!F$3) -> 0 | G48: =COUNTIFS(Pipe!$H:$H,Originadores!$D48,Pipe!$G:$G,Originadores!G$3) -> 4 | H48: =COUNTIFS(Pipe!$H:$H,Originadores!$D48,Pipe!$G:$G,Originadores!H$3) -> 0
C49: =+C48+1 -> 46 | D49: Castro e Silva | E49: Advogado | F49: =COUNTIFS(Pipe!$H:$H,Originadores!$D49,Pipe!$G:$G,Originadores!F$3) -> 0 | G49: =COUNTIFS(Pipe!$H:$H,Originadores!$D49,Pipe!$G:$G,Originadores!G$3) -> 1 | H49: =COUNTIFS(Pipe!$H:$H,Originadores!$D49,Pipe!$G:$G,Originadores!H$3) -> 0
C50: =+C49+1 -> 47 | D50: Cartesia Investimentos | E50: Asset | F50: =COUNTIFS(Pipe!$H:$H,Originadores!$D50,Pipe!$G:$G,Originadores!F$3) -> 0 | G50: =COUNTIFS(Pipe!$H:$H,Originadores!$D50,Pipe!$G:$G,Originadores!G$3) -> 0 | H50: =COUNTIFS(Pipe!$H:$H,Originadores!$D50,Pipe!$G:$G,Originadores!H$3) -> 1
C51: =+C50+1 -> 48 | D51: CM Capital (Broker) | E51: Broker | F51: =COUNTIFS(Pipe!$H:$H,Originadores!$D51,Pipe!$G:$G,Originadores!F$3) -> 0 | G51: =COUNTIFS(Pipe!$H:$H,Originadores!$D51,Pipe!$G:$G,Originadores!G$3) -> 3 | H51: =COUNTIFS(Pipe!$H:$H,Originadores!$D51,Pipe!$G:$G,Originadores!H$3) -> 0
C52: =+C51+1 -> 49 | D52: Connectas Capital | E52: Broker | F52: =COUNTIFS(Pipe!$H:$H,Originadores!$D52,Pipe!$G:$G,Originadores!F$3) -> 1 | G52: =COUNTIFS(Pipe!$H:$H,Originadores!$D52,Pipe!$G:$G,Originadores!G$3) -> 20 | H52: =COUNTIFS(Pipe!$H:$H,Originadores!$D52,Pipe!$G:$G,Originadores!H$3) -> 6
C53: =+C52+1 -> 50 | D53: Convexa Investimentos | E53: Broker | F53: =COUNTIFS(Pipe!$H:$H,Originadores!$D53,Pipe!$G:$G,Originadores!F$3) -> 0 | G53: =COUNTIFS(Pipe!$H:$H,Originadores!$D53,Pipe!$G:$G,Originadores!G$3) -> 1 | H53: =COUNTIFS(Pipe!$H:$H,Originadores!$D53,Pipe!$G:$G,Originadores!H$3) -> 0
C54: =+C53+1 -> 51 | D54: Credit Suisse | E54: Banco | F54: =COUNTIFS(Pipe!$H:$H,Originadores!$D54,Pipe!$G:$G,Originadores!F$3) -> 1 | G54: =COUNTIFS(Pipe!$H:$H,Originadores!$D54,Pipe!$G:$G,Originadores!G$3) -> 0 | H54: =COUNTIFS(Pipe!$H:$H,Originadores!$D54,Pipe!$G:$G,Originadores!H$3) -> 0
C55: =+C54+1 -> 52 | D55: Criteria Investimentos | F55: =COUNTIFS(Pipe!$H:$H,Originadores!$D55,Pipe!$G:$G,Originadores!F$3) -> 0 | G55: =COUNTIFS(Pipe!$H:$H,Originadores!$D55,Pipe!$G:$G,Originadores!G$3) -> 0 | H55: =COUNTIFS(Pipe!$H:$H,Originadores!$D55,Pipe!$G:$G,Originadores!H$3) -> 2
C56: =+C55+1 -> 53 | D56: CVPM | E56: Boutique | F56: =COUNTIFS(Pipe!$H:$H,Originadores!$D56,Pipe!$G:$G,Originadores!F$3) -> 0 | G56: =COUNTIFS(Pipe!$H:$H,Originadores!$D56,Pipe!$G:$G,Originadores!G$3) -> 1 | H56: =COUNTIFS(Pipe!$H:$H,Originadores!$D56,Pipe!$G:$G,Originadores!H$3) -> 1
C57: =+C56+1 -> 54 | D57: CWB Finance | E57: Broker | F57: =COUNTIFS(Pipe!$H:$H,Originadores!$D57,Pipe!$G:$G,Originadores!F$3) -> 0 | G57: =COUNTIFS(Pipe!$H:$H,Originadores!$D57,Pipe!$G:$G,Originadores!G$3) -> 2 | H57: =COUNTIFS(Pipe!$H:$H,Originadores!$D57,Pipe!$G:$G,Originadores!H$3) -> 3
C58: =+C57+1 -> 55 | D58: Daniel Baril | E58: Broker | F58: =COUNTIFS(Pipe!$H:$H,Originadores!$D58,Pipe!$G:$G,Originadores!F$3) -> 0 | G58: =COUNTIFS(Pipe!$H:$H,Originadores!$D58,Pipe!$G:$G,Originadores!G$3) -> 0 | H58: =COUNTIFS(Pipe!$H:$H,Originadores!$D58,Pipe!$G:$G,Originadores!H$3) -> 1
C59: =+C58+1 -> 56 | D59: Daniel Levy | E59: Empresário / Executivo | F59: =COUNTIFS(Pipe!$H:$H,Originadores!$D59,Pipe!$G:$G,Originadores!F$3) -> 0 | G59: =COUNTIFS(Pipe!$H:$H,Originadores!$D59,Pipe!$G:$G,Originadores!G$3) -> 0 | H59: =COUNTIFS(Pipe!$H:$H,Originadores!$D59,Pipe!$G:$G,Originadores!H$3) -> 1
C60: =+C59+1 -> 57 | D60: Danilo Caixeiro | E60: Empresário / Executivo | F60: =COUNTIFS(Pipe!$H:$H,Originadores!$D60,Pipe!$G:$G,Originadores!F$3) -> 0 | G60: =COUNTIFS(Pipe!$H:$H,Originadores!$D60,Pipe!$G:$G,Originadores!G$3) -> 1 | H60: =COUNTIFS(Pipe!$H:$H,Originadores!$D60,Pipe!$G:$G,Originadores!H$3) -> 0
C61: =+C60+1 -> 58 | D61: Data Traffic | E61: Empresário / Executivo | F61: =COUNTIFS(Pipe!$H:$H,Originadores!$D61,Pipe!$G:$G,Originadores!F$3) -> 2 | G61: =COUNTIFS(Pipe!$H:$H,Originadores!$D61,Pipe!$G:$G,Originadores!G$3) -> 0 | H61: =COUNTIFS(Pipe!$H:$H,Originadores!$D61,Pipe!$G:$G,Originadores!H$3) -> 0
C62: =+C61+1 -> 59 | D62: Dauricio Advogados | E62: Advogado | F62: =COUNTIFS(Pipe!$H:$H,Originadores!$D62,Pipe!$G:$G,Originadores!F$3) -> 1 | G62: =COUNTIFS(Pipe!$H:$H,Originadores!$D62,Pipe!$G:$G,Originadores!G$3) -> 0 | H62: =COUNTIFS(Pipe!$H:$H,Originadores!$D62,Pipe!$G:$G,Originadores!H$3) -> 0
C63: =+C62+1 -> 60 | D63: DCM Vinci | E63: Asset | F63: =COUNTIFS(Pipe!$H:$H,Originadores!$D63,Pipe!$G:$G,Originadores!F$3) -> 0 | G63: =COUNTIFS(Pipe!$H:$H,Originadores!$D63,Pipe!$G:$G,Originadores!G$3) -> 0 | H63: =COUNTIFS(Pipe!$H:$H,Originadores!$D63,Pipe!$G:$G,Originadores!H$3) -> 2
C64: =+C63+1 -> 61 | D64: De luca | E64: Advogado | F64: =COUNTIFS(Pipe!$H:$H,Originadores!$D64,Pipe!$G:$G,Originadores!F$3) -> 0 | G64: =COUNTIFS(Pipe!$H:$H,Originadores!$D64,Pipe!$G:$G,Originadores!G$3) -> 1 | H64: =COUNTIFS(Pipe!$H:$H,Originadores!$D64,Pipe!$G:$G,Originadores!H$3) -> 0
C65: =+C64+1 -> 62 | D65: Dealmaker | E65: Boutique | F65: =COUNTIFS(Pipe!$H:$H,Originadores!$D65,Pipe!$G:$G,Originadores!F$3) -> 0 | G65: =COUNTIFS(Pipe!$H:$H,Originadores!$D65,Pipe!$G:$G,Originadores!G$3) -> 1 | H65: =COUNTIFS(Pipe!$H:$H,Originadores!$D65,Pipe!$G:$G,Originadores!H$3) -> 0
C66: =+C65+1 -> 63 | D66: Deyvid Oliveira | E66: Advisor | F66: =COUNTIFS(Pipe!$H:$H,Originadores!$D66,Pipe!$G:$G,Originadores!F$3) -> 1 | G66: =COUNTIFS(Pipe!$H:$H,Originadores!$D66,Pipe!$G:$G,Originadores!G$3) -> 1 | H66: =COUNTIFS(Pipe!$H:$H,Originadores!$D66,Pipe!$G:$G,Originadores!H$3) -> 0
C67: =+C66+1 -> 64 | D67: Diego Ressureição | E67: Empresário / Executivo | F67: =COUNTIFS(Pipe!$H:$H,Originadores!$D67,Pipe!$G:$G,Originadores!F$3) -> 1 | G67: =COUNTIFS(Pipe!$H:$H,Originadores!$D67,Pipe!$G:$G,Originadores!G$3) -> 0 | H67: =COUNTIFS(Pipe!$H:$H,Originadores!$D67,Pipe!$G:$G,Originadores!H$3) -> 0
... C307: =+C306+1 -> 304 | D307: Zera.AG | E307: Boutique | F307: =COUNTIFS(Pipe!$H:$H,Originadores!$D307,Pipe!$G:$G,Originadores!F$3) -> 0 | G307: =COUNTIFS(Pipe!$H:$H,Originadores!$D307,Pipe!$G:$G,Originadores!G$3) -> 2 | H307: =COUNTIFS(Pipe!$H:$H,Originadores!$D307,Pipe!$G:$G,Originadores!H$3) -> 1
J314: =43*6.5 -> 279.5

Sheet Analise Originação 2025
C2: 2024 | D2: 2025 | K2: Tipo de Operação | L2: Nome | M2: Data Entrada | N2: a | O2: a | P2: a | Q2: De Para | Z2: > Infos Auxiliares | AD2: > Gráfico
B3: Casos Recebidos | C3: 260 | D3: =+COUNTIF(N:N,"2025") -> 372 | K3: Crédito | L3: Minter | M3: 45663 | N3: =YEAR(M3) -> 2025 | O3: JGP FA | P3: Advisor | Q3: =+INDEX($AA$3:$AA$19,MATCH(P3,$Z$3:$Z$19,0)) -> Consultoria | U3: Consultoria | V3: =COUNTIF($Q$3:$Q$374,U3) -> 132 | W3: =+V3/$V$10 -> 0.35483871 | Z3: Advisor | AA3: Consultoria | AD3: Consultoria | AE3: =+W3 -> 0.35483871 | AK3: JGP FA
B4: Casos Pre analisados | C4: 90 | D4: =+$D$3*E4 -> 128.76923 | E4: =+C4/$C$3 -> 0.34615385 | K4: Crédito RJ | L4: Portal Agro | M4: 45663 | N4: =YEAR(M4) -> 2025 | O4: X2W | P4: Advisor | Q4: =+INDEX($AA$3:$AA$19,MATCH(P4,$Z$3:$Z$19,0)) -> Consultoria | U4: Broker | V4: =COUNTIF($Q$3:$Q$374,U4) -> 114 | W4: =+V4/$V$10 -> 0.30645161 | Z4: Acionista | AA4: Empresários / Executivo | AD4: Broker | AE4: =+W4 -> 0.30645161 | AK4: X2W
B5: Casos Aprofundados | C5: 70 | D5: =+$D$3*E5 -> 100.15385 | E5: =+C5/$C$3 -> 0.26923077 | K5: Crédito RJ | L5: Hospital Lucio Rebelo | M5: 45663 | N5: =YEAR(M5) -> 2025 | O5: Dyamonte | P5: Advisor | Q5: =+INDEX($AA$3:$AA$19,MATCH(P5,$Z$3:$Z$19,0)) -> Consultoria | U5: Empresários / Executivo | V5: =COUNTIF($Q$3:$Q$374,U5) -> 33 | W5: =+V5/$V$10 -> 0.088709677 | Z5: Broker | AA5: Broker | AD5: Escritório Adv. | AE5: =+W8 -> 0.14247312 | AK5: Dyamonte
B6: Propostas Enviadas | C6: 15 | D6: =+$D$3*E6 -> 21.461538 | E6: =+C6/$C$3 -> 0.057692308 | K6: Crédito Estruturado | L6: Projesan | M6: 45663 | N6: =YEAR(M6) -> 2025 | O6: Heartman House | P6: Advisor | Q6: =+INDEX($AA$3:$AA$19,MATCH(P6,$Z$3:$Z$19,0)) -> Consultoria | U6: Outros | V6: =COUNTIF($Q$3:$Q$374,U6) -> 8 | W6: =+V6/$V$10 -> 0.021505376 | Z6: Advogado | AA6: Escritório Adv. | AD6: Empresários / Executivo | AE6: =+W5 -> 0.088709677 | AK6: Heartman House
B7: Investimentos Realizados | C7: 9 | D7: 6 | E7: =+C7/$C$3 -> 0.034615385 | F7: =+D7/D3 -> 0.016129032 | K7: Precatorio Estadual | L7: Precatório de Fortaleza | M7: 45670 | N7: =YEAR(M7) -> 2025 | O7: Enio | P7: Broker | Q7: =+INDEX($AA$3:$AA$19,MATCH(P7,$Z$3:$Z$19,0)) -> Broker | U7: Asset | V7: =COUNTIF($Q$3:$Q$374,U7) -> 17 | W7: =+V7/$V$10 -> 0.045698925 | Z7: Originação Própria | AA7: Originação Própria | AD7: Asset | AE7: =+W7 -> 0.045698925 | AK7: Aeté
K8: Crédito | L8: Blendpaper | M8: 45673 | N8: =YEAR(M8) -> 2025 | O8: JGP FA | P8: Advisor | Q8: =+INDEX($AA$3:$AA$19,MATCH(P8,$Z$3:$Z$19,0)) -> Consultoria | U8: Escritório Adv. | V8: =COUNTIF($Q$3:$Q$374,U8) -> 53 | W8: =+V8/$V$10 -> 0.14247312 | Z8: Banco | AA8: Banco | AD8: Banco | AE8: =+W9 -> 0.040322581 | AK8: Alvarez & Marsal
K9: Precatório Federal | L9: Caixa Prev | M9: 45674 | N9: =YEAR(M9) -> 2025 | O9: JGP FA | P9: Advisor | Q9: =+INDEX($AA$3:$AA$19,MATCH(P9,$Z$3:$Z$19,0)) -> Consultoria | U9: Banco | V9: =COUNTIF($Q$3:$Q$374,U9) -> 15 | W9: =+V9/$V$10 -> 0.040322581 | Z9: Gestora | AA9: Asset | AD9: Outros | AE9: =+W6 -> 0.021505376 | AK9: Renato Gorni - RMR Corporate
K10: Direito Creditórios | L10: Jari Celulose | M10: 45674 | N10: =YEAR(M10) -> 2025 | O10: Aeté | P10: Advisor | Q10: =+INDEX($AA$3:$AA$19,MATCH(P10,$Z$3:$Z$19,0)) -> Consultoria | U10: Total | V10: =+SUM(V3:V9) -> 372 | Z10: Empresário / Executivo | AA10: Empresários / Executivo | AK10: Stark Investment Banking
K11: Crédito Estruturado | L11: Bravante | M11: 45674 | N11: =YEAR(M11) -> 2025 | O11: Alvarez & Marsal | P11: Advisor | Q11: =+INDEX($AA$3:$AA$19,MATCH(P11,$Z$3:$Z$19,0)) -> Consultoria | Z11: Boutique | AA11: Consultoria | AK11: IFINC
K12: Crédito Estruturado | L12: Superfrio | M12: 45674 | N12: =YEAR(M12) -> 2025 | O12: Alvarez & Marsal | P12: Advisor | Q12: =+INDEX($AA$3:$AA$19,MATCH(P12,$Z$3:$Z$19,0)) -> Consultoria | Z12: Consultoria | AA12: Consultoria | AK12: Penaforte
K13: Crédito | L13: Allievo | M13: 45674 | N13: =YEAR(M13) -> 2025 | O13: Allievo | P13: Acionista | Q13: =+INDEX($AA$3:$AA$19,MATCH(P13,$Z$3:$Z$19,0)) -> Empresários / Executivo | Z13: JGP FA | AA13: Consultoria | AK13: Rio Investimentos
K14: Precatório Municipal | L14: Formosa | M14: 45674 | N14: =YEAR(M14) -> 2025 | O14: Renato Gorni - RMR Corporate | P14: Advisor | Q14: =+INDEX($AA$3:$AA$19,MATCH(P14,$Z$3:$Z$19,0)) -> Consultoria | Z14: Asset | AA14: Asset | AK14: Franklin Templaton
K15: Crédito Estruturado | L15: Itagres | M15: 45680 | N15: =YEAR(M15) -> 2025 | O15: Stark Investment Banking | P15: Advisor | Q15: =+INDEX($AA$3:$AA$19,MATCH(P15,$Z$3:$Z$19,0)) -> Consultoria | Z15: Empresário/Executivo | AA15: Empresários / Executivo | AK15: RFA
K16: Crédito | L16: Serra Azul | M16: 45680 | N16: =YEAR(M16) -> 2025 | O16: Stark Investment Banking | P16: Advisor | Q16: =+INDEX($AA$3:$AA$19,MATCH(P16,$Z$3:$Z$19,0)) -> Consultoria | Z16: Executivo/empresário | AA16: Empresários / Executivo | AK16: FTI
K17: Crédito | L17: Conduzvale | M17: 45680 | N17: =YEAR(M17) -> 2025 | O17: Stark Investment Banking | P17: Advisor | Q17: =+INDEX($AA$3:$AA$19,MATCH(P17,$Z$3:$Z$19,0)) -> Consultoria | Z17: Executivo | AA17: Empresários / Executivo | AK17: Makalu
K18: Crédito | L18: Villa Lisboa | M18: 45680 | N18: =YEAR(M18) -> 2025 | O18: Stark Investment Banking | P18: Advisor | Q18: =+INDEX($AA$3:$AA$19,MATCH(P18,$Z$3:$Z$19,0)) -> Consultoria | Z18: Fundo | AA18: Asset | AK18: CVPM
K19: Formulário de Referência/Leme Forense | M19: 45688 | N19: =YEAR(M19) -> 2025 | Q19: Outros | Z19: BNDES | AA19: Banco | AK19: Houlihan Lokey
K20: Crédito | L20: Ultracheese | M20: 45679 | N20: =YEAR(M20) -> 2025 | O20: Nippur | P20: Broker | Q20: =+INDEX($AA$3:$AA$19,MATCH(P20,$Z$3:$Z$19,0)) -> Broker | AK20: Jonatas Couri (EQI)
K21: Crédito | L21: Elisa Agro | M21: 45679 | N21: =YEAR(M21) -> 2025 | O21: Alvarez & Marsal | P21: Advisor | Q21: =+INDEX($AA$3:$AA$19,MATCH(P21,$Z$3:$Z$19,0)) -> Consultoria | AK21: Troesser
K22: Precatório Federal | L22: Frango Norte | M22: 45679 | N22: =YEAR(M22) -> 2025 | O22: Renato Gorni - RMR Corporate | P22: Broker | Q22: =+INDEX($AA$3:$AA$19,MATCH(P22,$Z$3:$Z$19,0)) -> Broker | AK22: Laplace
K23: Precatório Federal | L23: Precatorio Santa Cruz | M23: 45679 | N23: =YEAR(M23) -> 2025 | O23: Connectas Capital | P23: Broker | Q23: =+INDEX($AA$3:$AA$19,MATCH(P23,$Z$3:$Z$19,0)) -> Broker
K24: SITE RI | M24: 45688 | N24: =YEAR(M24) -> 2025 | O24: PAGOOS | Q24: Broker
K25: Crédito | L25: Construtora OAB | M25: 45679 | N25: =YEAR(M25) -> 2025 | O25: Stark Investment Banking | P25: Advisor | Q25: =+INDEX($AA$3:$AA$19,MATCH(P25,$Z$3:$Z$19,0)) -> Consultoria | AK25: Triunfae
K26: Crédito Trabalhista | L26: Galileu e Assespa | M26: 45684 | N26: =YEAR(M26) -> 2025 | O26: Alvarez & Marsal | P26: Advisor | Q26: =+INDEX($AA$3:$AA$19,MATCH(P26,$Z$3:$Z$19,0)) -> Consultoria | AK26: Zera.AG
K27: Pré-Precatório Federal | L27: Aspometron | M27: 45684 | N27: =YEAR(M27) -> 2025 | O27: Empresário | P27: Empresário / Executivo | Q27: =+INDEX($AA$3:$AA$19,MATCH(P27,$Z$3:$Z$19,0)) -> Empresários / Executivo
K28: Crédito | L28: Fribarreiras | M28: 45684 | N28: =YEAR(M28) -> 2025 | Q28: Consultoria | AK28: Integra Associados
K29: DIP | L29: Grupo Lagos de Itaipava | M29: 45687 | N29: =YEAR(M29) -> 2025 | O29: IFINC | P29: Advisor | Q29: =+INDEX($AA$3:$AA$19,MATCH(P29,$Z$3:$Z$19,0)) -> Consultoria | AK29: Ecowa
K30: Direito Creditórios | L30: São Paulo | M30: 45686 | N30: =YEAR(M30) -> 2025 | O30: Penaforte | P30: Advisor | Q30: =+INDEX($AA$3:$AA$19,MATCH(P30,$Z$3:$Z$19,0)) -> Consultoria | AK30: Dealmaker
K31: Direito Creditórios | L31: MRV | M31: 45686 | N31: =YEAR(M31) -> 2025 | O31: Penaforte | P31: Advisor | Q31: =+INDEX($AA$3:$AA$19,MATCH(P31,$Z$3:$Z$19,0)) -> Consultoria | AK31: Leandro Gomes (MA7)
K32: Precatório Estadual | L32: Precatórios do RN | M32: 45685 | N32: =YEAR(M32) -> 2025 | O32: Octo Capital | P32: Broker | Q32: =+INDEX($AA$3:$AA$19,MATCH(P32,$Z$3:$Z$19,0)) -> Broker
K33: Direitos Creditórios | L33: Coimex | M33: 45685 | N33: =YEAR(M33) -> 2025 | O33: Alvarez & Marsal | P33: Advisor | Q33: =+INDEX($AA$3:$AA$19,MATCH(P33,$Z$3:$Z$19,0)) -> Consultoria | AK33: Letro Consultoria
K34: Direitos Creditórios | L34: Construtora Moraes Sampaio | M34: 45685 | N34: =YEAR(M34) -> 2025 | O34: Rio Investimentos | P34: Advisor | Q34: =+INDEX($AA$3:$AA$19,MATCH(P34,$Z$3:$Z$19,0)) -> Consultoria | AK34: Hayden Capital
K35: Direitos Creditórios | L35: Condominio x Gafisa | M35: 45685 | N35: =YEAR(M35) -> 2025 | O35: Rio Investimentos | P35: Advisor | Q35: =+INDEX($AA$3:$AA$19,MATCH(P35,$Z$3:$Z$19,0)) -> Consultoria | AK35: AGI
K36: Precatório Federal | L36: Clinica Reviver | M36: 45685 | N36: =YEAR(M36) -> 2025 | O36: Nippur/FA | P36: Broker | Q36: =+INDEX($AA$3:$AA$19,MATCH(P36,$Z$3:$Z$19,0)) -> Broker | AK36: FGA
K37: Precatório Federal | L37: Instituto de Saúde e Educação Vida | M37: 45685 | N37: =YEAR(M37) -> 2025 | O37: Nippur/FA | P37: Broker | Q37: =+INDEX($AA$3:$AA$19,MATCH(P37,$Z$3:$Z$19,0)) -> Broker
K38: Crédito Estruturado | L38: Aluguel de Freezer da Metalfrio | M38: 45686 | N38: =YEAR(M38) -> 2025 | O38: Oriz | P38: Asset | Q38: =+INDEX($AA$3:$AA$19,MATCH(P38,$Z$3:$Z$19,0)) -> Asset
K39: Precatório Estadual | L39: Sealion | M39: 45685 | N39: =YEAR(M39) -> 2025 | O39: Marco Andre Alencar | P39: Broker | Q39: =+INDEX($AA$3:$AA$19,MATCH(P39,$Z$3:$Z$19,0)) -> Broker | AK39: Verdeau
K40: Precatório Estadual | L40: Precatório Ceará (Marleiba) | M40: 45685 | N40: =YEAR(M40) -> 2025 | O40: Enio | P40: Broker | Q40: =+INDEX($AA$3:$AA$19,MATCH(P40,$Z$3:$Z$19,0)) -> Broker | AK40: RPC Par
K41: Precatório Estadual | L41: Precatório Bahia | M41: 45688 | N41: =YEAR(M41) -> 2025 | O41: Roberto Roland | P41: Broker | Q41: =+INDEX($AA$3:$AA$19,MATCH(P41,$Z$3:$Z$19,0)) -> Broker | AK41: Valuation Partners
K42: Litigation Finance | L42: Voepass x Latam | M42: 45688 | N42: =YEAR(M42) -> 2025 | O42: Ferro | P42: Advogado | Q42: =+INDEX($AA$3:$AA$19,MATCH(P42,$Z$3:$Z$19,0)) -> Escritório Adv.
K43: Carta | M43: 45688 | N43: =YEAR(M43) -> 2025 | P43: Advogado | Q43: =+INDEX($AA$3:$AA$19,MATCH(P43,$Z$3:$Z$19,0)) -> Escritório Adv. | AK43: Artica
K44: Apresentação | M44: 45688 | N44: =YEAR(M44) -> 2025 | P44: Advogado | Q44: =+INDEX($AA$3:$AA$19,MATCH(P44,$Z$3:$Z$19,0)) -> Escritório Adv. | AK44: Stefano Celano
K45: Direitos Creditórios | L45: Eletrogoes | M45: 45693 | N45: =YEAR(M45) -> 2025 | O45: Franklin Templaton | P45: Advisor | Q45: =+INDEX($AA$3:$AA$19,MATCH(P45,$Z$3:$Z$19,0)) -> Consultoria | AK45: Fernando Piton
K46: Crédito Estruturado | L46: Graal x Odebrecht | M46: 45693 | N46: =YEAR(M46) -> 2025 | O46: Padis Mattar | P46: Advogado | Q46: =+INDEX($AA$3:$AA$19,MATCH(P46,$Z$3:$Z$19,0)) -> Escritório Adv. | AK46: Focus Partners
K47: Crédito | L47: Construtora Porto | M47: 45693 | N47: =YEAR(M47) -> 2025 | O47: Empresário | P47: Empresário / Executivo | Q47: =+INDEX($AA$3:$AA$19,MATCH(P47,$Z$3:$Z$19,0)) -> Empresários / Executivo | AK47: Felippe Lo Bianco
K48: Precatório Estadual | L48: Dep.Estradas de Rodagem - SP | M48: 45693 | N48: =YEAR(M48) -> 2025 | O48: IFINC | P48: Advisor | Q48: =+INDEX($AA$3:$AA$19,MATCH(P48,$Z$3:$Z$19,0)) -> Consultoria | AK48: Remora Capital
K49: Precatório Estadual | L49: Precatório Ceará - Quadra Imobiliária | M49: 45685 | N49: =YEAR(M49) -> 2025 | O49: Enio | P49: Broker | Q49: =+INDEX($AA$3:$AA$19,MATCH(P49,$Z$3:$Z$19,0)) -> Broker | AK49: Northstone
K50: Compra de NPL | L50: Vianna Junior | M50: 45696 | N50: =YEAR(M50) -> 2025 | O50: Joaquim Bastos | P50: Advogado | Q50: =+INDEX($AA$3:$AA$19,MATCH(P50,$Z$3:$Z$19,0)) -> Escritório Adv. | AK50: 18IB
K51: Precatório Estadual | L51: Precatório do Rio | M51: 45698 | N51: =YEAR(M51) -> 2025 | O51: Marco Andre Alencar | P51: Broker | Q51: =+INDEX($AA$3:$AA$19,MATCH(P51,$Z$3:$Z$19,0)) -> Broker | AK51: EY
K52: Precatório Federal | L52: Francisco Honorio | M52: 45698 | N52: =YEAR(M52) -> 2025 | O52: Enio (grupo wapp) | P52: Broker | Q52: =+INDEX($AA$3:$AA$19,MATCH(P52,$Z$3:$Z$19,0)) -> Broker | AK52: Tauá Partners
K53: Compra de NPL | L53: NPL Banco Luso | M53: 45700 | N53: =YEAR(M53) -> 2025 | O53: Banco Luso | P53: Banco | Q53: =+INDEX($AA$3:$AA$19,MATCH(P53,$Z$3:$Z$19,0)) -> Banco
K54: Direto Creditório | L54: Empresa no Amapá x Empresa Canadense | M54: 45700 | N54: =YEAR(M54) -> 2025 | O54: Deyvid Oliveira | P54: Broker | Q54: =+INDEX($AA$3:$AA$19,MATCH(P54,$Z$3:$Z$19,0)) -> Broker
K55: Crédito Estruturado | L55: Seara Agro | M55: 45701 | N55: =YEAR(M55) -> 2025 | O55: JGP FA | P55: Advisor | Q55: =+INDEX($AA$3:$AA$19,MATCH(P55,$Z$3:$Z$19,0)) -> Consultoria
K56: Crédito Estruturado | L56: Adiantamento a Fazenda (Grupo Auxiliar x Familia Paiva) | M56: 45701 | N56: =YEAR(M56) -> 2025 | O56: RPC | P56: Gestora | Q56: =+INDEX($AA$3:$AA$19,MATCH(P56,$Z$3:$Z$19,0)) -> Asset
K57: Crédito Estruturado | L57: Auma | M57: 45700 | N57: =YEAR(M57) -> 2025 | O57: RFA | P57: Advisor | Q57: =+INDEX($AA$3:$AA$19,MATCH(P57,$Z$3:$Z$19,0)) -> Consultoria
K58: Pré precatório | L58: Estre Ambiental | M58: 45705 | N58: =YEAR(M58) -> 2025 | O58: Gabriel Turiano | P58: Advogado | Q58: =+INDEX($AA$3:$AA$19,MATCH(P58,$Z$3:$Z$19,0)) -> Escritório Adv.
K59: Crédito Estruturado | L59: Sencinet | M59: 45705 | N59: =YEAR(M59) -> 2025 | O59: Padis Mattar | P59: Advogado | Q59: =+INDEX($AA$3:$AA$19,MATCH(P59,$Z$3:$Z$19,0)) -> Escritório Adv.
K60: Legal Claims | L60: Projeto Armando Conde | M60: 45706 | N60: =YEAR(M60) -> 2025 | O60: Leite Tosto | P60: Advogado | Q60: =+INDEX($AA$3:$AA$19,MATCH(P60,$Z$3:$Z$19,0)) -> Escritório Adv.
K61: Crédito Estruturado | L61: CRI - Casa Orange | M61: 45706 | N61: =YEAR(M61) -> 2025 | O61: Multinvest | P61: Broker | Q61: =+INDEX($AA$3:$AA$19,MATCH(P61,$Z$3:$Z$19,0)) -> Broker
K62: Precatórios | L62: Tese Tunep | M62: 45706 | N62: =YEAR(M62) -> 2025 | O62: Nippur | P62: Broker | Q62: =+INDEX($AA$3:$AA$19,MATCH(P62,$Z$3:$Z$19,0)) -> Broker
K63: Precatório Estadual | L63: Precatório de SP | M63: 45706 | N63: =YEAR(M63) -> 2025 | O63: Vihtor Carraro | P63: Broker | Q63: =+INDEX($AA$3:$AA$19,MATCH(P63,$Z$3:$Z$19,0)) -> Broker
K64: Crédito Estruturado | L64: Engevix | M64: 45709 | N64: =YEAR(M64) -> 2025 | O64: Empresário | P64: Empresário / Executivo | Q64: =+INDEX($AA$3:$AA$19,MATCH(P64,$Z$3:$Z$19,0)) -> Empresários / Executivo
... K78: Pré precatório | L78: Honorários Sucumbenciais Estre (Turiano) | M78: 45716 | N78: =YEAR(M78) -> 2025 | O78: Empresário | P78: Empresário / Executivo | Q78: =+INDEX($AA$3:$AA$19,MATCH(P78,$Z$3:$Z$19,0)) -> Empresários / Executivo
K79: Debenture | L79: Casas Bahia | M79: 45726 | N79: =YEAR(M79) -> 2025 | O79: Cross sell | P79: Outros | Q79: Outros
K80: Crédito Estruturado | L80: Agro | M80: 45726 | N80: =YEAR(M80) -> 2025 | O80: Horizonte Investimentos | P80: Broker | Q80: =+INDEX($AA$3:$AA$19,MATCH(P80,$Z$3:$Z$19,0)) -> Broker
K81: DIP | L81: Grupo Fasolo | M81: 45726 | N81: =YEAR(M81) -> 2025 | O81: Portofino | P81: Asset | Q81: =+INDEX($AA$3:$AA$19,MATCH(P81,$Z$3:$Z$19,0)) -> Asset
K82: NPL | L82: Canabrava | M82: 45726 | N82: =YEAR(M82) -> 2025 | O82: Vieira Rezende | P82: Advogado | Q82: =+INDEX($AA$3:$AA$19,MATCH(P82,$Z$3:$Z$19,0)) -> Escritório Adv.
K83: NPL | L83: Leilão do Itau | M83: 45726 | N83: =YEAR(M83) -> 2025 | O83: Itau BBA | P83: Banco | Q83: =+INDEX($AA$3:$AA$19,MATCH(P83,$Z$3:$Z$19,0)) -> Banco
K84: NPL | L84: Grupo Fayad | M84: 45726 | N84: =YEAR(M84) -> 2025 | O84: Banco do Brasil | P84: Banco | Q84: =+INDEX($AA$3:$AA$19,MATCH(P84,$Z$3:$Z$19,0)) -> Banco
K85: Precatório Federal | L85: Associação de Educação do Norte Paulista | M85: 45729 | N85: =YEAR(M85) -> 2025 | O85: JGP FA | P85: JGP FA | Q85: =+INDEX($AA$3:$AA$19,MATCH(P85,$Z$3:$Z$19,0)) -> Consultoria
K86: Precatórios Estaduais | L86: Precatórios Estaduais do RJ | M86: 45731 | N86: =YEAR(M86) -> 2025 | O86: Galdino | P86: Advogado | Q86: =+INDEX($AA$3:$AA$19,MATCH(P86,$Z$3:$Z$19,0)) -> Escritório Adv.
K87: Legal Claims | L87: Tese Seguro Habitacional | M87: 45728 | N87: =YEAR(M87) -> 2025 | O87: JGP FA | P87: JGP FA | Q87: =+INDEX($AA$3:$AA$19,MATCH(P87,$Z$3:$Z$19,0)) -> Consultoria
K88: Litigation Finance | M88: 45733 | N88: =YEAR(M88) -> 2025 | O88: Lefosse | P88: Advogado | Q88: =+INDEX($AA$3:$AA$19,MATCH(P88,$Z$3:$Z$19,0)) -> Escritório Adv.
K89: Legal Claims | L89: Walter dos Santos Affonso | M89: 45733 | N89: =YEAR(M89) -> 2025 | O89: Connectas Capital | P89: Broker | Q89: =+INDEX($AA$3:$AA$19,MATCH(P89,$Z$3:$Z$19,0)) -> Broker
K90: DIP | L90: Grupo Monte Alegre | M90: 45734 | N90: =YEAR(M90) -> 2025 | O90: CVPM | P90: Boutique | Q90: =+INDEX($AA$3:$AA$19,MATCH(P90,$Z$3:$Z$19,0)) -> Consultoria
K91: Legal Claim | L91: Derivado de Petro Santa Izabel x Vibra | M91: 45734 | N91: =YEAR(M91) -> 2025 | O91: Connectas Capital | P91: Broker | Q91: =+INDEX($AA$3:$AA$19,MATCH(P91,$Z$3:$Z$19,0)) -> Broker
K92: Crédito Estruturado | L92: FIDES (Cobre) | M92: 45734 | N92: =YEAR(M92) -> 2025 | O92: Ore Investments | P92: Asset | Q92: =+INDEX($AA$3:$AA$19,MATCH(P92,$Z$3:$Z$19,0)) -> Asset
K93: Crédito Estruturado | L93: lotus grains & oilseeds s.a | M93: 45737 | N93: =YEAR(M93) -> 2025 | O93: Sergio Carvalho | P93: Broker | Q93: =+INDEX($AA$3:$AA$19,MATCH(P93,$Z$3:$Z$19,0)) -> Broker
K94: Legal Claim | L94: Petroeng | M94: 45737 | N94: =YEAR(M94) -> 2025 | O94: Empresário | P94: Empresário / Executivo | Q94: =+INDEX($AA$3:$AA$19,MATCH(P94,$Z$3:$Z$19,0)) -> Empresários / Executivo
K95: Crédito Estruturado | L95: Grupo Elfa | M95: 45744 | N95: =YEAR(M95) -> 2025 | O95: JGP FA | P95: JGP FA | Q95: =+INDEX($AA$3:$AA$19,MATCH(P95,$Z$3:$Z$19,0)) -> Consultoria
K96: DIP | L96: Patense | M96: 45747 | N96: =YEAR(M96) -> 2025 | O96: Houlihan Lokey | P96: Boutique | Q96: =+INDEX($AA$3:$AA$19,MATCH(P96,$Z$3:$Z$19,0)) -> Consultoria
K97: Precatórios Estaduais | L97: Precatório Tocantis | M97: 45742 | N97: =YEAR(M97) -> 2025 | O97: GPX Invest | P97: Broker | Q97: =+INDEX($AA$3:$AA$19,MATCH(P97,$Z$3:$Z$19,0)) -> Broker
K98: Legal Claim | L98: TTK x Petrobras | M98: 45742 | N98: =YEAR(M98) -> 2025 | O98: Potenza Capital | P98: Broker | Q98: =+INDEX($AA$3:$AA$19,MATCH(P98,$Z$3:$Z$19,0)) -> Broker
K99: Pré Precatório Federal | L99: Casa de Saúde Dr. Aragão Villar | M99: 45742 | N99: =YEAR(M99) -> 2025 | O99: Connectas Capital | P99: Broker | Q99: =+INDEX($AA$3:$AA$19,MATCH(P99,$Z$3:$Z$19,0)) -> Broker
K100: Precatório Federal | L100: Gradiente | M100: 45744 | N100: =YEAR(M100) -> 2025 | O100: Connectas Capital | P100: Broker | Q100: =+INDEX($AA$3:$AA$19,MATCH(P100,$Z$3:$Z$19,0)) -> Broker
K101: Legal Claim | L101: Mercantil Café | M101: 45747 | N101: =YEAR(M101) -> 2025 | O101: Henrique (JGP) | P101: Empresário / Executivo | Q101: =+INDEX($AA$3:$AA$19,MATCH(P101,$Z$3:$Z$19,0)) -> Empresários / Executivo
K102: DIP | L102: Agrogalaxy | M102: 45751 | N102: =YEAR(M102) -> 2025 | O102: Cross sell | P102: Outros | Q102: Outros
K103: DIP | L103: STEMAC | M103: 45751 | N103: =YEAR(M103) -> 2025 | O103: JGP FA | P103: JGP FA | Q103: =+INDEX($AA$3:$AA$19,MATCH(P103,$Z$3:$Z$19,0)) -> Consultoria
K104: Crédito Estruturado | L104: Surfland | M104: 45751 | N104: =YEAR(M104) -> 2025 | O104: JGP FA | P104: JGP FA | Q104: =+INDEX($AA$3:$AA$19,MATCH(P104,$Z$3:$Z$19,0)) -> Consultoria
K105: NPL | L105: Banco Santos | M105: 45751 | N105: =YEAR(M105) -> 2025 | P105: Banco | Q105: =+INDEX($AA$3:$AA$19,MATCH(P105,$Z$3:$Z$19,0)) -> Banco
K106: Crédito Estruturado | L106: South Star | M106: 45751 | N106: =YEAR(M106) -> 2025 | O106: Ore Investments | P106: Asset | Q106: =+INDEX($AA$3:$AA$19,MATCH(P106,$Z$3:$Z$19,0)) -> Asset
K107: Crédito Estruturado | L107: Resolvvi | M107: 45748 | N107: =YEAR(M107) -> 2025 | P107: Consultoria | Q107: =+INDEX($AA$3:$AA$19,MATCH(P107,$Z$3:$Z$19,0)) -> Consultoria
K108: NPL | L108: Carlos Sanchez (EMS) + BB | M108: 45748 | N108: =YEAR(M108) -> 2025 | P108: Banco | Q108: =+INDEX($AA$3:$AA$19,MATCH(P108,$Z$3:$Z$19,0)) -> Banco
K109: Legal claim | L109: Technip | M109: 45751 | N109: =YEAR(M109) -> 2025 | O109: Broker | P109: Broker | Q109: =+INDEX($AA$3:$AA$19,MATCH(P109,$Z$3:$Z$19,0)) -> Broker
K110: Precatório Federal | L110: Fortaleza | M110: 45751 | N110: =YEAR(M110) -> 2025 | O110: Bruno Advogado | P110: Advogado | Q110: =+INDEX($AA$3:$AA$19,MATCH(P110,$Z$3:$Z$19,0)) -> Escritório Adv.
K111: Legal Claim | L111: Clinica Cristo Rei x White Martins | M111: 45754 | N111: =YEAR(M111) -> 2025 | O111: Alex | P111: Broker | Q111: =+INDEX($AA$3:$AA$19,MATCH(P111,$Z$3:$Z$19,0)) -> Broker
K112: Crédito | L112: Morro Verde | M112: 45754 | N112: =YEAR(M112) -> 2025 | O112: Ore Investments | P112: Asset | Q112: =+INDEX($AA$3:$AA$19,MATCH(P112,$Z$3:$Z$19,0)) -> Asset
K113: Crédito | L113: Grupo Andrade | M113: 45754 | N113: =YEAR(M113) -> 2025 | O113: Felipe Fay | P113: Outros | Q113: Outros
K114: Carteira de crédito | L114: OI | M114: 45754 | N114: =YEAR(M114) -> 2025 | O114: Ativo Liquido | P114: Outros | Q114: Outros
...

Sheet Reestruturação
C2: Nome | D2: Responsável
C3: Allonda
C4: Skyfit
C5: Eveo | D5: Tirar
C6: Grupo Pakera | D6: Tirar
C7: GBS
C8: IUGU | D8: Tirar
C9: Projeto Nimbus | D9: Tirar e Sem espaço para empresa não auditada no book de HY
C10: Grupo Montes Belos | D10: Tirar
C11: Weclix
C12: Usina Ory (Etanol de Milho) | D12: Aprofundar
C13: Braskem | D13: mandar a reportagem
C14: Kimberlite | D14: Falar com Carlos Watanabe (Valuation)
C15: JFL Living
C16: BDG Incorporadora
C17: Cocelpa
C18: BRAM

Sheet Vertical_1812
D2: Casos analisados desde Outubro 2025
C3: # | D3: Ativos Financeiros | E3: Operação | F3: Setor | G3: Status | I3: Entraram | J3: 24
C4: 1 | D4: JFL Living | E4: Crédito Estruturado | F4: Real Estate | G4: Aprovado em Comitê de High Yield | I4: Saídas Reunião Anterior | J4: 15
C5: =+C4+1 -> 2 | D5: Cocelpa | E5: Crédito Estruturado | F5: Papel e Celulose | G5: Proposta Indicativa enviada | I5: Novas Saídas | J5: 27
C6: =+C5+1 -> 3 | D6: Edital BNDES NPL | E6: NPL | F6: Banco | G6: Enviamos os documentos, aguardando resposta | I6: Numero da Lista Anterior | J6: 38
C7: =+C6+1 -> 4 | D7: Oxe Energia | E7: Crédito Estruturado | F7: Energia | G7: Em análise | I7: Casos Ativos | J7: =+J3-J4-J5+J6 -> 20
C8: =+C7+1 -> 5 | D8: Eletrodata | E8: DIP | F8: Engenharia | G8: Aguardando Informações do Modelo
C9: =+C8+1 -> 6 | D9: Carteira da Petrobras - NPL | E9: NPL | F9: O&G | G9: Vamos enviar nossos dados
C10: =+C9+1 -> 7 | D10: Gás Verde | E10: Crédito Estruturado | F10: Energia | G10: Em análise para High Yield
C11: =+C10+1 -> 8 | D11: CI Banco | E11: Crédito Estruturado | F11: Financeiro | G11: Agendando reunião
C12: =+C11+1 -> 9 | D12: Familia Levinsohn - ITCMD | E12: Crédito Estruturado | F12: Agro | G12: Proposta indicativa enviada
C13: =+C12+1 -> 10 | D13: Grupo Nova Ebenézer | E13: NPL | F13: Agro | G13: Aguardando bancos para entender se tem negocio da venda dos creditos 30-35% par
C14: =+C13+1 -> 11 | D14: PDG | E14: NPL | F14: Real Estate | G14: Agendando reunião com a Companhia
C15: =+C14+1 -> 12 | D15: Casas Bahia | E15: Debenture | F15: Varejo | G15: Acompanhar a reestruturação das Casas Bahia - venda @22%PAR
C16: =+C15+1 -> 13 | D16: BJ Grupo | E16: DIP | F16: Combustível | G16: Aguardando informações
C17: =+C16+1 -> 14 | D17: Sencinet | E17: DIP | F17: Tecnologia | G17: Aguardando informações
C18: =+C17+1 -> 15 | D18: Kozma x Campina | E18: NPL | G18: Em análise
C19: =+C18+1 -> 16 | D19: Mave | E19: Crédito Estruturado | F19: Varejo | G19: Em análise
C20: =+C19+1 -> 17 | D20: Sanes | E20: Crédito Estruturado | F20: Alimentos | G20: Em análise
C21: =+C20+1 -> 18 | D21: Enseada | E21: DIP/NPL | F21: Navegação | G21: Em análise
C22: =+C21+1 -> 19 | D22: Allonda | E22: DIP/NPL | F22: Engenharia | G22: G5 em negociação com BOFA
C23: =+C22+1 -> 20 | D23: BRAX | E23: Crédito Estruturado | F23: Esporte | G23: NDA pendente de assinatura
C24: =+C23+1 -> 21 | D24: Dessana Emerald | E24: Crédito Estruturado | F24: Mineração | G24: Operação sem fit com o fundo
C25: =+C24+1 -> 22 | D25: Produza | E25: Crédito Estruturado | F25: Industria | G25: Ramp-up operacional robusto e pouca garantia
C26: =+C25+1 -> 23 | D26: Figueirense | E26: DIP | F26: Esporte | G26: Julgamento de agravos e potencial garantia ainda travada
C27: =+C26+1 -> 24 | D27: Skyfit | E27: Crédito Estruturado | F27: Academia | G27: Spread da proposta distante da nossa taxa
C28: =+C27+1 -> 25 | D28: Usina Ory (Etanol de Milho) | E28: Crédito Estruturado | F28: Energia | G28: Poucas garantias
C29: =+C28+1 -> 26 | D29: Instituiçao SP x Cyrela | E29: Crédito Estruturado | F29: Construção | G29: Sem aprovação da capacidade de pagamento
C30: =+C29+1 -> 27 | D30: Papelex | E30: DIP | F30: Varejo | G30: RJ com poucas garantias
... C50: =+C49+1 -> 47 | D50: Empresa de Cerâmica (Artec) | E50: DIP | F50: Agro | G50: Ativo operacional em garantia
C55: # | D55: Ativos Judiciais | E55: Operação | F55: Status
C56: 1 | D56: Valmont x Pivo | E56: Legal Claim | F56: Em análise, vamos precificar
C57: =+C56+1 -> 2 | D57: Crefisa | E57: Legal Claim | F57: Aguardando reunião com o Serrano
C58: =+C57+1 -> 3 | D58: Incobrasa | E58: Legal Claim | F58: Em análise
C59: =+C58+1 -> 4 | D59: Unipar x Petrobras | E59: Legal Claim | F59: Estão verificando o entendimento da Selic
C60: =+C59+1 -> 5 | D60: Créditos ODB - VLT | E60: Precatório Municipal | F60: Em análise
C61: =+C60+1 -> 6 | D61: Difal Elfa | E61: Legal Claim | F61: Em análise
C62: =+C61+1 -> 7 | D62: Zemax | E62: Pré Precatório Federal | F62: Analisando o envio da proposta
C63: =+C62+1 -> 8 | D63: Full Comex Trading x União | E63: Pré Precatório Federal | F63: Em análise
C64: =+C63+1 -> 9 | D64: Carteira de Precatórios - Estre Ambiental | E64: Precatório | F64: Em análise
C65: =+C64+1 -> 10 | D65: Tomé Carlos x Instituto Chico Mendes (ICMBio) | E65: Pré Precatório Federal | F65: Em análise
C66: =+C65+1 -> 11 | D66: Fast Shop | E66: Legal Claim | F66: Em análise
C67: =+C66+1 -> 12 | D67: PF x Optrel | E67: Legal Claim | F67: Em análise
C68: =+C67+1 -> 13 | D68: Herstel Participações | E68: Pré Precatório Federal | F68: Em análise
... C80: =+C79+1 -> 25 | D80: Inea | E80: Legal Claim | F80: Não
D100: Raizen e Blueway | E100: Legal Claim | F100: Não | G100: 13/10 - Vamos aguardar as informações
D101: Renamar x Fazenda do Estado de SP | E101: Pré-precatório Estado | F101: Não | G101: 13/10 - Fizemos um call, nao parece bom, pode ter uma saida via acordo
D102: Precatório ZPN Produções x São Luis | E102: Precatório Municipal | F102: Não | G102: 06/10 - Fizemos a proposta para o Enio, aguardando retorno
D103: Usina Santa Therezinha x União Federal | E103: Pré-precatório Federal | F103: Não
D104: Indústria Pizzato | E104: Pré-precatório Federal | F104: Não
D105: Precatórios Nova Rio | E105: Precatórios Federal | F105: Não

Sheet Vertical_1610
D2: Casos analisados desde Setembro 2025
C3: # | D3: Ativos Financeiros | E3: Operação | F3: Setor | G3: Status | I3: Entraram | J3: 16 | N3: # | O3: Ativos Financeiros | P3: Operação | Q3: Setor | R3: Status
C4: 1 | D4: Braskem | E4: Debenture | F4: Industria | G4: Concluído. Investimos R$ 2.6m (2% do fundo) @37%PAR | I4: Saídas Reunião Anterior | J4: 17 | N4: 1 | O4: Braskem | P4: Debenture | Q4: Industria | R4: Concluído. Investimos R$ 2.6m (2% do fundo) @37%PAR | S4: =+INDEX(Pipe!N:N,MATCH(O4,Pipe!E:E,0)) -> Concluído
C5: =+C4+1 -> 2 | D5: Familia Levinsohn - ITCMD | E5: Crédito Estruturado | F5: Agro | G5: Proposta indicativa enviada | I5: Novas Saídas | J5: 2 | N5: =+N4+1 -> 2 | O5: Familia Levinsohn - ITCMD | P5: Crédito Estruturado | Q5: Agro | R5: Proposta indicativa enviada | S5: =+INDEX(Pipe!N:N,MATCH(O5,Pipe!E:E,0)) -> #N/A
C6: =+C5+1 -> 3 | D6: Instituiçao SP x Cyrela | E6: Crédito Estruturado | F6: Construção | G6: Proposta enviada | I6: Numero da Lista Anterior | J6: 40 | N6: =+N5+1 -> 3 | O6: Instituiçao SP x Cyrela | P6: Crédito Estruturado | Q6: Construção | R6: Proposta enviada | S6: =+INDEX(Pipe!N:N,MATCH(O6,Pipe!E:E,0)) -> #N/A
C7: =+C6+1 -> 4 | D7: Allonda | E7: DIP/NPL | F7: Engenharia | G7: Estamos preparando proposta indicativa | I7: Casos Ativos | J7: =+J3-J4-J5+J6 -> 37 | N7: =+N6+1 -> 4 | O7: Allonda | P7: DIP/NPL | Q7: Engenharia | R7: Estamos preparando proposta indicativa
C8: =+C7+1 -> 5 | D8: Cocelpa | E8: Crédito Estruturado | F8: Papel e Celulose | G8: Estamos preparando proposta indicativa | N8: =+N7+1 -> 5 | O8: Cocelpa | P8: Crédito Estruturado | Q8: Papel e Celulose | R8: Estamos preparando proposta indicativa
C9: =+C8+1 -> 6 | D9: Papelex | E9: DIP | F9: Varejo | G9: Em análise
C10: =+C9+1 -> 7 | D10: Elba Equipamentos e Serviços | E10: Crédito Estruturado | F10: Aluguel de Equipamentos | G10: Em análise
C11: =+C10+1 -> 8 | D11: Valetão Pneus | E11: DIP/NPL | F11: Varejo | G11: Pendente do envio de informações | N11: =+N8+1 -> 6 | O11: Valetão Pneus | P11: DIP/NPL | Q11: Varejo | R11: Pendente do envio de informações | S11: =+INDEX(Pipe!N:N,MATCH(O11,Pipe!E:E,0)) -> Não
C12: =+C11+1 -> 9 | D12: Cara Preta | E12: Crédito Estruturado | F12: Agro | G12: Pendente de resposta da EQI sobre a distribuição do fundo | I12: meza 20% a.a + 20% kicker | N12: =+N11+1 -> 7 | O12: Cara Preta | P12: Crédito Estruturado | Q12: Agro | R12: Pendente de resposta da EQI sobre a distribuição do fundo | S12: =+INDEX(Pipe!N:N,MATCH(O12,Pipe!E:E,0)) -> Não
C13: =+C12+1 -> 10 | D13: Grupo DTW | F13: Agro
C14: =+C13+1 -> 11
C15: =+C14+1 -> 12 | D15: Usina Ory (Etanol de Milho) | E15: Crédito Estruturado | F15: Energia | G15: Em análise
C16: =+C15+1 -> 13 | D16: Sanes | E16: Crédito Estruturado | F16: Alimentos | G16: Aguardando Informação
C17: =+C16+1 -> 14 | D17: Enseada | E17: DIP/NPL | F17: Navegação | G17: Aguardando Informações
C18: =+C17+1 -> 15 | D18: Tinguá | E18: Crédito Estruturado | F18: Transportes | G18: Em análise
C19: =+C18+1 -> 16 | D19: Cremona Capital | E19: Crédito Estruturado | F19: Consórcio | G19: Entendendo o background dos originadores | N19: =+N12+1 -> 8 | O19: Tinguá | P19: Crédito Estruturado | Q19: Transportes | R19: Em análise | S19: =+INDEX(Pipe!N:N,MATCH(O19,Pipe!E:E,0)) -> Não
C20: =+C19+1 -> 17 | D20: Figueirense | E20: DIP | F20: Esporte | G20: Em análise da RJ | N20: =+N19+1 -> 9 | O20: Cremona Capital | P20: Crédito Estruturado | Q20: Consórcio | R20: Entendendo o background dos originadores | S20: =+INDEX(Pipe!N:N,MATCH(O20,Pipe!E:E,0)) -> Não
C21: =+C20+1 -> 18 | D21: Eletrodata | E21: DIP | F21: Engenharia | G21: Aguardando Informações do Fluxo de Pagamento do DIP | N21: =+N20+1 -> 10 | O21: Figueirense | P21: DIP | Q21: Esporte | R21: Em análise da RJ
C22: =+C21+1 -> 19 | D22: JFL Living | E22: Crédito Estruturado | F22: Real Estate | G22: Operação enviada para High Yield | N22: =+N21+1 -> 11 | O22: Eletrodata | P22: DIP | Q22: Engenharia | R22: Aguardando Informações do Fluxo de Pagamento do DIP | S22: =+INDEX(Pipe!N:N,MATCH(O22,Pipe!E:E,0)) -> Não
C23: =+C22+1 -> 20 | D23: Skyfit | E23: Crédito Estruturado | F23: Academia | G23: Aguardando informações do VDR | N23: =+N22+1 -> 12 | O23: Skyfit | P23: Crédito Estruturado | Q23: Academia | R23: Aguardando informações do VDR | S23: =+INDEX(Pipe!N:N,MATCH(O23,Pipe!E:E,0)) -> Não
C24: =+C23+1 -> 21 | D24: GBS | E24: Crédito Estruturado | F24: Energia | G24: Em análise | N24: =+N23+1 -> 13 | O24: JFL Living | P24: Crédito Estruturado | Q24: Real Estate | R24: Operação enviada para High Yield | S24: =+INDEX(Pipe!N:N,MATCH(O24,Pipe!E:E,0)) -> Não
C25: =+C24+1 -> 22 | D25: Marabraz | E25: Crédito Estruturado | F25: Varejo | G25: Aguardando nova reuniao | N25: =+N24+1 -> 14 | O25: GBS | P25: Crédito Estruturado | Q25: Energia | R25: Em análise | S25: =+INDEX(Pipe!N:N,MATCH(O25,Pipe!E:E,0)) -> Não
C26: =+C25+1 -> 23 | D26: Weclix | E26: NPL | F26: Fibra Óptica | G26: Aguardando envio de informações | N26: =+N25+1 -> 15 | O26: Marabraz | P26: Crédito Estruturado | Q26: Varejo | R26: Aguardando nova reuniao | S26: =+INDEX(Pipe!N:N,MATCH(O26,Pipe!E:E,0)) -> On Hold
C27: =+C26+1 -> 24 | D27: BRAX | E27: Crédito Estruturado | F27: Esporte | G27: NDA pendente de assinatura | N27: =+N26+1 -> 16 | O27: Weclix | P27: NPL | Q27: Fibra Óptica | R27: Aguardando envio de informações | S27: =+INDEX(Pipe!N:N,MATCH(O27,Pipe!E:E,0)) -> Não
C28: =+C27+1 -> 25 | D28: Mineração Dagoberto | E28: Crédito Estruturado | F28: Mineração | G28: Aguardando resolução da transação tributária | N28: =+N27+1 -> 17 | O28: BRAX | P28: Crédito Estruturado | Q28: Esporte | R28: NDA pendente de assinatura | S28: =+INDEX(Pipe!N:N,MATCH(O28,Pipe!E:E,0)) -> Não
C29: =+C28+1 -> 26 | D29: Lavoro | E29: Crédito Estruturado | F29: Agro | G29: Vão buscar outras formas de financiamento | N29: =+N28+1 -> 18 | O29: Mineração Dagoberto | P29: Crédito Estruturado | Q29: Mineração | R29: Aguardando resolução da transação tributária | S29: =+INDEX(Pipe!N:N,MATCH(O29,Pipe!E:E,0)) -> On Hold
C30: =+C29+1 -> 27 | D30: EMAE | E30: Crédito Estruturado | F30: Energia | G30: Garantias de Tenure, Tercio e Ambipar | N30: =+N29+1 -> 19 | O30: Lavoro | P30: Crédito Estruturado | Q30: Agro | R30: Vão buscar outras formas de financiamento | S30: =+INDEX(Pipe!N:N,MATCH(O30,Pipe!E:E,0)) -> Não
C31: =+C30+1 -> 28 | D31: Kimberlite | E31: Crédito Estruturado | F31: Industria | G31: Operaçao sem fit com o fundo | N31: =+N30+1 -> 20 | O31: EMAE | P31: Crédito Estruturado | Q31: Energia | R31: Garantias de Tenure, Tercio e Ambipar | S31: =+INDEX(Pipe!N:N,MATCH(O31,Pipe!E:E,0)) -> On Hold
C32: =+C31+1 -> 29 | D32: Metodista (Trabalhista) | E32: NPL | F32: Grupo de Ensino | G32: Aguardando Cia sobre renegociação de prazos do PRJ | N32: =+N31+1 -> 21 | O32: Kimberlite | P32: Crédito Estruturado | Q32: Industria | R32: Operaçao sem fit com o fundo | S32: =+INDEX(Pipe!N:N,MATCH(O32,Pipe!E:E,0)) -> Não
C33: =+C32+1 -> 30 | D33: Metodista (DIP) | E33: DIP | F33: Grupo de Ensino | G33: Aguardando Cia sobre renegociação de prazos do PRJ | N33: =+N32+1 -> 22 | O33: Metodista (Trabalhista) | P33: NPL | Q33: Grupo de Ensino | R33: Aguardando Cia sobre renegociação de prazos do PRJ | S33: =+INDEX(Pipe!N:N,MATCH(O33,Pipe!E:E,0)) -> Não
... C40: =+C39+1 -> 37 | D40: Riomar | E40: Crédito Estruturado | F40: Industria | G40: Nao tem imoveis que nao operacional pra colocar na operaçao | N40: =+N39+1 -> 29 | O40: BDG Incorporadora | P40: Crédito Estruturado | Q40: Incorporadora | R40: Baixo faturamento e financiamento de obra, garantia operacional | S40: =+INDEX(Pipe!N:N,MATCH(O40,Pipe!E:E,0)) -> Não
C41: =+C40+1 -> 38 | D41: Projeto Endurance | E41: Crédito Estruturado | F41: Logistica | G41: Custo da divida baixo e pouca garantia, ainda operacional | N41: =+N40+1 -> 30 | O41: Riomar | P41: Crédito Estruturado | Q41: Industria | R41: Nao tem imoveis que nao operacional pra colocar na operaçao
N42: =+N41+1 -> 31 | O42: Projeto Endurance | P42: Crédito Estruturado | Q42: Logistica | R42: Custo da divida baixo e pouca garantia, ainda operacional
R46: Pouca garantia, capacidade de pagamento
D47: Casos analisados desde Setembro 2025
C48: # | D48: Ativos Judiciais | E48: Operação | F48: Status
C49: 1 | D49: Empresa Oriente x Precatório Municipal de Macae | E49: Precatorio Municipal | F49: Proposta Enviada
C50: =+C49+1 -> 2 | D50: Precatório ZPN Produções x São Luis | E50: Precatorio Municipal | F50: Proposta Enviada
C51: =+C50+1 -> 3 | D51: Precatório Federal Nova Rio | E51: Precatório Federal | F51: Proposta Enviada
C52: =+C51+1 -> 4 | D52: Raizen e Blueway | E52: Legal Claim | F52: Em análise
C53: =+C52+1 -> 5 | D53: Renamar x Fazenda do Estado de SP | E53: Pré-Precatório | F53: Em análise
C54: =+C53+1 -> 6 | D54: Tomé Carlos x Instituto Chico Mendes (ICMBio) | E54: Pré-Precatório | F54: Em análise
C55: =+C54+1 -> 7 | D55: BRCon | E55: Legal Claim | F55: On Hold - Fundo IV
C56: =+C55+1 -> 8 | D56: B100 x Vibra | E56: Legal Claim | F56: Aguardando novo laudo contábil
C57: =+C56+1 -> 9 | D57: Carteira de Creditos Judiciais - Odebretch | E57: Legal Claim | F57: Em negociação de outros ativos
C58: =+C57+1 -> 10 | D58: Precatório Difusao Cultural Trindade x Estado RS | E58: Precatório Estadual | F58: Recusado
C59: =+C58+1 -> 11 | D59: Andreza Maria x Pernambuco | E59: Precatorio Estadual | F59: Recusado
C60: =+C59+1 -> 12 | D60: BBD Seguros x Thyssen | E60: Legal Claim | F60: Recusado
C61: =+C60+1 -> 13 | D61: HEMOPAC x Maceio | E61: Precatorio Municipal | F61: Recusado
... C69: =+C68+1 -> 21 | D69: Unicard | E69: Legal Claim | F69: Recusado
C70: =+C69+1 -> 22 | D70: Via Norte vs Advogados (Sucumbencia) | E70: Legal Claim | F70: Recusado | G70: =70*99% -> 69.3
C71: =+C70+1 -> 23 | D71: Crédito IAA | E71: Pré Precatório Federal | F71: Recusado

Sheet Vertical_2509
D2: Casos analisados desde Agosto 2025
C3: # | D3: Ativos Financeiros | E3: Operação | F3: Setor | G3: Status | I3: Entraram | J3: 9
C4: 1 | D4: Lavoro | E4: Crédito Estruturado | F4: Agro | G4: TS pendente de assinatura do Patria (sinalização positiva) | I4: Saídas Reunião Anterior | J4: 10 | M4: Grupo Pakera | N4: =INDEX($G$4:$G$72,MATCH(M4,$D$4:$D$72,0)) -> Pouca garantia, capacidade de pagamento | O4: =+INDEX(Pipe!N:N,MATCH(M4,Pipe!E:E,0)) -> Não
C5: =+C4+1 -> 2 | D5: Instituiçao SP x Cyrela | E5: Crédito Estruturado | F5: Construção | G5: Proposta enviada | I5: Novas Saídas | J5: 8 | M5: Empresa Agro | N5: =INDEX($G$4:$G$72,MATCH(M5,$D$4:$D$72,0)) -> Pouco ativo, sem garantia e cheque pequeno | O5: =+INDEX(Pipe!N:N,MATCH(M5,Pipe!E:E,0)) -> Não
C6: =+C5+1 -> 3 | D6: Kimberlite | E6: Crédito Estruturado | F6: Industria | G6: Em análise | I6: Numero da Lista Anterior | J6: 32
C7: =+C6+1 -> 4 | D7: JFL Living | E7: Crédito Estruturado | F7: Real Estate | G7: Em análise | I7: Casos Ativos | J7: =+J3-J4-J5+J6 -> 23 | N7: =INDEX($G$4:$G$72,MATCH(D9,$D$4:$D$72,0)) -> Em análise das matrículas | O7: =+INDEX(Pipe!N:N,MATCH(D9,Pipe!E:E,0)) -> #N/A
C8: =+C7+1 -> 5 | D8: GBS | E8: Crédito Estruturado | F8: Energia | G8: Em análise | N8: =INDEX($G$4:$G$72,MATCH(D5,$D$4:$D$72,0)) -> Proposta enviada | O8: =+INDEX(Pipe!N:N,MATCH(D5,Pipe!E:E,0)) -> #N/A
C9: =+C8+1 -> 6 | D9: Familia Levinsohn - ITCMD | E9: Crédito Estruturado | F9: Agro | G9: Em análise das matrículas | N9: =INDEX($G$4:$G$72,MATCH(#REF!,$D$4:$D$72,0)) -> #REF! | O9: =+INDEX(Pipe!N:N,MATCH(#REF!,Pipe!E:E,0)) -> #REF!
C10: =+C9+1 -> 7 | D10: Metodista (Trabalhista) | E10: NPL | F10: Grupo de Ensino | G10: Aguardando Cia sobre renegociação de prazos do PRJ | N10: =INDEX($G$4:$G$72,MATCH(#REF!,$D$4:$D$72,0)) -> #REF! | O10: =+INDEX(Pipe!N:N,MATCH(#REF!,Pipe!E:E,0)) -> #REF!
C11: =+C10+1 -> 8 | D11: Metodista (DIP) | E11: DIP | F11: Grupo de Ensino | G11: Aguardando Cia sobre renegociação de prazos do PRJ | N11: =INDEX($G$4:$G$72,MATCH(D29,$D$4:$D$72,0)) -> Com risco, nao consegue executar (risco maior com a Orizon) | O11: =+INDEX(Pipe!N:N,MATCH(D29,Pipe!E:E,0)) -> Não
C12: =+C11+1 -> 9 | D12: Cocelpa | E12: Crédito Estruturado | F12: Papel e Celulose | G12: Aguardando envio de informações | N12: =INDEX($G$4:$G$72,MATCH(D23,$D$4:$D$72,0)) -> NDA pendente de assinatura | O12: =+INDEX(Pipe!N:N,MATCH(D23,Pipe!E:E,0)) -> Não
C13: =+C12+1 -> 10 | D13: Skyfit | E13: Crédito Estruturado | F13: Academia | G13: Aguardando informações do VDR | N13: =INDEX($G$4:$G$72,MATCH(D8,$D$4:$D$72,0)) -> Em análise | O13: =+INDEX(Pipe!N:N,MATCH(D8,Pipe!E:E,0)) -> Não
C14: =+C13+1 -> 11 | D14: Allonda | E14: DIP/NPL | F14: Engenharia | G14: Em análise das arbitragens | N14: =INDEX($G$4:$G$72,MATCH(D30,$D$4:$D$72,0)) -> Pouca garantia, capacidade de pagamento | O14: =+INDEX(Pipe!N:N,MATCH(D30,Pipe!E:E,0)) -> Não
C15: =+C14+1 -> 12 | D15: Marabraz | E15: Crédito Estruturado | F15: Varejo | G15: Aguardando nova reuniao | N15: =INDEX($G$4:$G$72,MATCH(D31,$D$4:$D$72,0)) -> Operação sem perfil do fundo | O15: =+INDEX(Pipe!N:N,MATCH(D31,Pipe!E:E,0)) -> Não
C16: =+C15+1 -> 13 | D16: Eletrodata | E16: DIP | F16: Engenharia | G16: Aguardando Informações do Fluxo de Pagamento do DIP | N16: =INDEX($G$4:$G$72,MATCH(D10,$D$4:$D$72,0)) -> Aguardando Cia sobre renegociação de prazos do PRJ | O16: =+INDEX(Pipe!N:N,MATCH(D10,Pipe!E:E,0)) -> Não
C17: =+C16+1 -> 14 | D17: Eveo | E17: Crédito Estruturado | F17: Data Center | G17: Aguardando devolutiva da cia com as propostas que receberam e tambem o % do kicker | N17: =INDEX($G$4:$G$72,MATCH(D11,$D$4:$D$72,0)) -> Aguardando Cia sobre renegociação de prazos do PRJ | O17: =+INDEX(Pipe!N:N,MATCH(D11,Pipe!E:E,0)) -> Não
C18: =+C17+1 -> 15 | D18: ERBE - Carteira de Ativos/Passivos | E18: NPL | F18: Real Estate | G18: Em análise | N18: =INDEX($G$4:$G$72,MATCH(D19,$D$4:$D$72,0)) -> Em análise | O18: =+INDEX(Pipe!N:N,MATCH(D19,Pipe!E:E,0)) -> Não
C19: =+C18+1 -> 16 | D19: IUGU | E19: Crédito Estruturado | F19: Fintech | G19: Em análise | N19: =INDEX($G$4:$G$72,MATCH(D32,$D$4:$D$72,0)) -> Operação sem perfil do fundo | O19: =+INDEX(Pipe!N:N,MATCH(D32,Pipe!E:E,0)) -> Não
C20: =+C19+1 -> 17 | D20: Projeto Nimbus (Data Center Privado) | E20: Crédito Estruturado | F20: Data Center | G20: Em análise | N20: =INDEX($G$4:$G$72,MATCH(D25,$D$4:$D$72,0)) -> Aguardando resolução da transação tributária | O20: =+INDEX(Pipe!N:N,MATCH(D25,Pipe!E:E,0)) -> On Hold
C21: =+C20+1 -> 18 | D21: Grupo Montes Belos | E21: DIP | F21: Transportes | G21: Aguardando envio de informações | N21: =INDEX($G$4:$G$72,MATCH(D20,$D$4:$D$72,0)) -> Em análise | O21: =+INDEX(Pipe!N:N,MATCH(D20,Pipe!E:E,0)) -> Não
C22: =+C21+1 -> 19 | D22: Weclix | E22: NPL | F22: Fibra Óptica | G22: Aguardando envio de informações | N22: =INDEX($G$4:$G$72,MATCH(D21,$D$4:$D$72,0)) -> Aguardando envio de informações | O22: =+INDEX(Pipe!N:N,MATCH(D21,Pipe!E:E,0)) -> Não
C23: =+C22+1 -> 20 | D23: BRAX | E23: Crédito Estruturado | F23: Esporte | G23: NDA pendente de assinatura | N23: =INDEX($G$4:$G$72,MATCH(D22,$D$4:$D$72,0)) -> Aguardando envio de informações | O23: =+INDEX(Pipe!N:N,MATCH(D22,Pipe!E:E,0)) -> Não
C24: =+C23+1 -> 21 | D24: BDG Incorporadora | E24: Crédito Estruturado | F24: Incorporadora | G24: Em análise | N24: =INDEX($G$4:$G$72,MATCH(D12,$D$4:$D$72,0)) -> Aguardando envio de informações | O24: =+INDEX(Pipe!N:N,MATCH(D12,Pipe!E:E,0)) -> Não
C25: =+C24+1 -> 22 | D25: Mineração Dagoberto | E25: Crédito Estruturado | F25: Mineração | G25: Aguardando resolução da transação tributária
C26: =+C25+1 -> 23 | D26: EMAE | E26: Crédito Estruturado | F26: Energia | G26: Aguardando call com a XP
C27: =+C26+1 -> 24 | D27: Eldorado Indústrias | E27: DIP | F27: Industria | G27: Não mandamos proposta
C28: =+C27+1 -> 25 | D28: Grupo Pakera | E28: DIP | F28: Bebidas | G28: Pouca garantia, capacidade de pagamento
C29: =+C28+1 -> 26 | D29: Leva - Motoeletrica | E29: Crédito Estruturado | F29: Automotivo | G29: Com risco, nao consegue executar (risco maior com a Orizon)
C30: =+C29+1 -> 27 | D30: Cooperativa Pindorma | E30: Crédito Estruturado | F30: Agro | G30: Pouca garantia, capacidade de pagamento
C31: =+C30+1 -> 28 | D31: Projeto Cotia | E31: Crédito Estruturado | G31: Operação sem perfil do fundo | M31: =+INDEX(Pipe!N:N,MATCH(Vertical_2509!D33,Pipe!E:E,0)) -> Não | N31: =+INDEX(Pipe!P:P,MATCH(Vertical_2509!D33,Pipe!E:E,0)) -> Vamos negar, risco de fraude devido a cf de recebiveis pouco antes da RJ
C32: =+C31+1 -> 29 | D32: LARGO | E32: Crédito Estruturado | F32: Mineração | G32: Operação sem perfil do fundo | M32: =+INDEX(Pipe!N:N,MATCH(Vertical_2509!D34,Pipe!E:E,0)) -> Não | N32: =+INDEX(Pipe!P:P,MATCH(Vertical_2509!D34,Pipe!E:E,0)) -> 0
C33: =+C32+1 -> 30 | D33: Caetano x Covabra | E33: DIP | F33: Varejo - Supermercado | G33: Risco de fraude devido a cf de recebiveis pouco antes da RJ
C34: =+C33+1 -> 31 | D34: Sweet Fruits | E34: NPL | F34: Alimentos | G34: Não mandamos proposta | N34: =+INDEX(Pipe!P:P,MATCH(Vertical_2509!D14,Pipe!E:E,0)) -> Entedemos que o trabalho de turnaround está sendo executado, mas o caso depende de esforço comercial e melhoria operacional para parar de pé. Em casos assim, precisaríamos de uma estrutura de garantias mais robusta para prosseguirmos com a operação.
C35: =+C34+1 -> 32 | D35: NPLs Hayden | E35: NPL | G35: Valores pequenos
C36: =+C35+1 -> 33 | D36: Grão de Gente | E36: DIP | F36: Varejo | G36: Garantias não suficientes | M36: =+INDEX(Pipe!N:N,MATCH(Vertical_2509!D36,Pipe!E:E,0)) -> Não | N36: =+INDEX(Pipe!P:P,MATCH(Vertical_2509!D36,Pipe!E:E,0)) -> Garantias não suficientes
C37: =+C36+1 -> 34 | D37: NOOA | E37: Crédito Estruturado | F37: Agro | G37: Pouca garantia e taxa baixa
C38: =+C37+1 -> 35 | D38: Carteira do Santander | E38: NPL | F38: Diversos | G38: Não mandamos proposta | M38: =+INDEX(Pipe!N:N,MATCH(Vertical_2509!D37,Pipe!E:E,0)) -> Não | N38: =+INDEX(Pipe!P:P,MATCH(Vertical_2509!D37,Pipe!E:E,0)) -> Pouca garantia e taxa baixa
C39: =+C38+1 -> 36 | D39: Empresa Agro | E39: DIP | F39: Agro | G39: Pouco ativo, sem garantia e cheque pequeno | N39: =+INDEX(Pipe!P:P,MATCH(Vertical_2509!D28,Pipe!E:E,0)) -> RJ em status incial e pouco ativo
C40: =+C39+1 -> 37 | D40: Projeto Cooperativa | E40: Crédito Estruturado | F40: Agro | G40: Garantias não suficientes
C41: =+C40+1 -> 38 | D41: Agro DFG | E41: DIP | F41: Agro | G41: Pouca garantia e taxa baixa | M41: =+INDEX(Pipe!N:N,MATCH(Vertical_2509!D38,Pipe!E:E,0)) -> Não
C42: =+C41+1 -> 39 | D42: Nova Produtiva | E42: Crédito Estruturado | F42: Agro | G42: Pouca capacidade de pagamento e garantias | M42: =+INDEX(Pipe!N:N,MATCH(Vertical_2509!D18,Pipe!E:E,0)) -> Não | N42: BRCON
M43: =+INDEX(Pipe!N:N,MATCH(Vertical_2509!D27,Pipe!E:E,0)) -> Não
M44: =+INDEX(Pipe!N:N,MATCH(Vertical_2509!D26,Pipe!E:E,0)) -> On Hold
M45: =+INDEX(Pipe!N:N,MATCH(Vertical_2509!D39,Pipe!E:E,0)) -> Não | N45: =+INDEX(Pipe!P:P,MATCH(Vertical_2509!D39,Pipe!E:E,0)) -> Pouco ativo, sem garantia e cheque pequeno
M46: =+INDEX(Pipe!N:N,MATCH(Vertical_2509!D40,Pipe!E:E,0)) -> Não | N46: =+INDEX(Pipe!P:P,MATCH(Vertical_2509!D40,Pipe!E:E,0)) -> Garantias não suficientes
D47: Casos analisados desde Julho 2025 | M47: =+INDEX(Pipe!N:N,MATCH(Vertical_2509!D41,Pipe!E:E,0)) -> Não | N47: =+INDEX(Pipe!P:P,MATCH(Vertical_2509!D41,Pipe!E:E,0)) -> Pouca garantia e taxa baixa
C48: # | D48: Ativos Judiciais | E48: Operação | F48: Status | M48: =+INDEX(Pipe!N:N,MATCH(Vertical_2509!D42,Pipe!E:E,0)) -> Não | N48: =+INDEX(Pipe!P:P,MATCH(Vertical_2509!D42,Pipe!E:E,0)) -> Pouca capacidade de pagamento e garantias
C49: 1 | D49: BRCon | E49: Legal Claim | F49: On Hold - Fundo IV
C50: =+C49+1 -> 2 | D50: Andreza Maria x Pernambuco | E50: Precatorio Estadual | F50: Pedimos as infos, aguardando
C51: =+C50+1 -> 3 | D51: Carteira de Creditos Judiciais - Odebretch | E51: Legal Claim | F51: Em negociação
C52: =+C51+1 -> 4 | D52: BBD Seguros x Thyssen | E52: Legal Claim | F52: Em análise
C53: =+C52+1 -> 5 | D53: Empresa Oriente x Precatório Municipal de Macae | E53: Precatorio Municipal | F53: Em análise
C54: =+C53+1 -> 6 | D54: Desapropriação em Curitiba | E54: Pré Precatório Federal | F54: Em análise
C55: =+C54+1 -> 7 | D55: HEMOPAC x Maceio | E55: Precatorio Municipal | F55: Aguardando retorno da proposta
C56: =+C55+1 -> 8 | D56: Hospital Ortopédico x Maceio | E56: Precatorio Municipal | F56: Aguardando retorno da proposta
C57: =+C56+1 -> 9 | D57: B100 x Vibra | E57: Legal Claim | F57: Aguardando novo laudo contábil
C58: =+C57+1 -> 10 | D58: SINDJUS/DF | E58: Pré Precatório Federal | F58: Recusado
C59: =+C58+1 -> 11 | D59: Itabiriçu x Vale | E59: Ação Judicial | F59: Recusado
C60: =+C59+1 -> 12 | D60: Mlub | E60: Legal Claim | F60: Recusado
C61: =+C60+1 -> 13 | D61: Unicard | F61: Recusado
D75: Casos analisados desde Julho 2025
C76: # | D76: Ativos Judiciais | E76: Operação | F76: Status | I76: Entraram | J76: 27
C77: 1 | D77: BRCon | E77: Legal Claim | F77: On Hold - Fundo IV | I77: Saídas Reunião Anterior | J77: 7
C78: =+C77+1 -> 2 | D78: SINDJUS/DF | E78: Pré Precatório Federal | F78: Pedimos as infos, aguardando | I78: Novas Saídas | J78: 20
C79: =+C78+1 -> 3 | D79: Itabiriçu x Vale | E79: Ação Judicial | F79: Em negociação | I79: Numero da Lista Anterior | J79: 16
C80: =+C79+1 -> 4 | D80: Andreza Maria x Pernambuco | E80: Precatorio Estadual | F80: Em análise | I80: Casos Ativos | J80: =+J76-J77-J78+J79 -> 16
C81: =+C80+1 -> 5 | D81: HEMOPAC x Maceio | E81: Precatorio Municipal | F81: Em análise
C82: =+C81+1 -> 6 | D82: Hospital Ortopédico x Maceio | E82: Precatorio Municipal | F82: Em análise
C83: =+C82+1 -> 7 | D83: Familia Horn | E83: Legal Claim | F83: Em análise
C84: =+C83+1 -> 8 | D84: B100 x Vibra | E84: Legal Claim | F84: Em análise
C85: =+C84+1 -> 9 | D85: Mlub | E85: Legal Claim | F85: Em análise
C86: =+C85+1 -> 10 | D86: Carteira de Creditos Judiciais - Odebretch | E86: Legal Claim | F86: Em análise
C87: =+C86+1 -> 11 | D87: CTR Itaboraí x Itaboraí | E87: Precatorio Municipal | F87: Em análise
C88: =+C87+1 -> 12 | D88: CTR Itaboraí x Itaboraí | E88: Precatorio Municipal | F88: Em análise
C89: =+C88+1 -> 13 | D89: Rio Dourado Participações | E89: Legal Claim | F89: Em análise
C90: =+C89+1 -> 14 | D90: BBD Seguros x Thyssen | E90: Legal Claim | F90: Em análise
C91: =+C90+1 -> 15 | D91: Railroad x Vale | E91: Litigation Finance | F91: Em análise
C92: =+C91+1 -> 16 | D92: Unicard | E92: Legal Claim | F92: Em análise
... C119: =+C118+1 -> 43 | D119: Projeto Mate | E119: Ativo Fiscal | F119: Recusado
C125: =+C102+1 -> 27 | D125: Precatório Varca Scatena | E125: Precatório Municipal | F125: Recusado | G125: =+INDEX(Pipe!N:N,MATCH(D125,Pipe!E:E,0)) -> Não
C126: =+C125+1 -> 28 | D126: Precatório Paraná - Balduíno João Bellé | E126: Precatório Estadual | F126: Recusado | G126: =+INDEX(Pipe!N:N,MATCH(D126,Pipe!E:E,0)) -> Não
C127: =+C126+1 -> 29 | D127: Precatório Rio Grande do Sul | E127: Precatório Estadual | F127: Proposta abaixo do esperado | G127: =+INDEX(Pipe!N:N,MATCH(D127,Pipe!E:E,0)) -> Não
C128: =+C127+1 -> 30 | D128: Claim Trabalhista - Oriz | E128: Legal Claim | F128: Proposta abaixo do esperado | G128: =+INDEX(Pipe!N:N,MATCH(D128,Pipe!E:E,0)) -> Não
C129: =+C128+1 -> 31 | D129: Requisição de Pgto ST Cruz | E129: Precatório Federal | F129: Proposta abaixo do esperado | G129: =+INDEX(Pipe!N:N,MATCH(D129,Pipe!E:E,0)) -> Não
C130: =+C129+1 -> 32 | D130: Precatório do RJ - Royalties de Petróleo | E130: Precatório Federal | F130: Proposta abaixo do esperado | G130: =+INDEX(Pipe!N:N,MATCH(D130,Pipe!E:E,0)) -> Não
C131: =+C130+1 -> 33 | D131: Precatórios CNO | E131: Precatórios | F131: Proposta abaixo do esperado | G131: =+INDEX(Pipe!N:N,MATCH(D131,Pipe!E:E,0)) -> Não
C132: =+C131+1 -> 34 | D132: Precatorios Residencial Park | E132: Precatório Estadual | F132: Proposta abaixo do esperado | G132: =+INDEX(Pipe!N:N,MATCH(D132,Pipe!E:E,0)) -> Não
C133: =+C132+1 -> 35 | D133: Tronox - Compulsório Eletrobras | E133: Ação Judicial | F133: Recusado | G133: =+INDEX(Pipe!N:N,MATCH(D133,Pipe!E:E,0)) -> Não
C134: =+C133+1 -> 36 | D134: Precatório Macapá | E134: Precatório Municipal | F134: Recusado | G134: =+INDEX(Pipe!N:N,MATCH(D134,Pipe!E:E,0)) -> Não
C135: =+C134+1 -> 37 | D135: Associados FAACO x Correios | E135: Pré Precatório | F135: Recusado | G135: =+INDEX(Pipe!N:N,MATCH(D135,Pipe!E:E,0)) -> Não
C136: =+C135+1 -> 38 | D136: Precatório Santa Catarina | E136: Precatório Estadual | F136: Recusado | G136: =+INDEX(Pipe!N:N,MATCH(D136,Pipe!E:E,0)) -> Não
C137: =+C136+1 -> 39 | D137: Precatório SP | E137: Precatório Estadual | F137: Recusado | G137: =+INDEX(Pipe!N:N,MATCH(D137,Pipe!E:E,0)) -> Não
... C154: =+C153+1 -> 56 | D154: Antonio Martins x União | E154: Precatório Federal | F154: Recusado | G154: =+INDEX(Pipe!N:N,MATCH(D154,Pipe!E:E,0)) -> Não

Sheet Vertical_2108
D2: Casos analisados desde Julho 2025
C3: # | D3: Ativos Financeiros | E3: Operação | F3: Setor | G3: Status | I3: Entraram | J3: 19
C4: 1 | D4: Gaia Geração | E4: Crédito Estruturado | F4: Energia | G4: Segunda Tranche será investida 22.08 | I4: Saídas Reunião Anterior | J4: 4
C5: =+C4+1 -> 2 | D5: Agrogalaxy | E5: DIP | F5: Agro | G5: Investido R$ 4.5m - Aguardando Definição PF | I5: Novas Saídas | J5: 5
C6: =+C5+1 -> 3 | D6: Trinity | E6: Crédito Estruturado | F6: Energia | G6: Investida | I6: Numero da Lista Anterior | J6: 13
C7: =+C6+1 -> 4 | D7: Skyfit | E7: Crédito Estruturado | F7: Academia | G7: Aguardando informações do VDR | I7: Casos Ativos | J7: =+J3-J4-J5+J6 -> 23
C8: =+C7+1 -> 5 | D8: Marabraz | E8: Crédito Estruturado | F8: Varejo | G8: Reunião Agendada para 22.08
C9: =+C8+1 -> 6 | D9: Caetano x Covabra | E9: DIP | F9: Varejo - Supermercado | G9: Em análise
C10: =+C9+1 -> 7 | D10: Sweet Fruits | E10: NPL | F10: Alimentos | G10: Em análise
C11: =+C10+1 -> 8 | D11: NPLs Hayden | E11: NPL | G11: Em análise
C12: =+C11+1 -> 9 | D12: Allonda | E12: DIP/NPL | F12: Engenharia | G12: Reunião Agendada para 22.08
C13: =+C12+1 -> 10 | D13: Eletrodata | E13: DIP | F13: Engenharia | G13: Aguardando Informações do Fluxo de Pagamento do DIP
C14: =+C13+1 -> 11 | D14: Grão de Gente | E14: DIP | F14: Varejo | G14: Em negociação para envolver o imóvel na transação
C15: =+C14+1 -> 12 | D15: Lavoro | E15: Crédito Estruturado | F15: Agro | G15: Reunião Agendada para 27.08
C16: =+C15+1 -> 13 | D16: NOOA | E16: Crédito Estruturado | F16: Agro | G16: Reunião Agendada 26.08
C17: =+C16+1 -> 14 | D17: Grupo Pakera | E17: DIP | F17: Bebidas | G17: Aguardando Informações
C18: =+C17+1 -> 15 | D18: Eveo | E18: Crédito Estruturado | F18: Data Center | G18: Estamos agendando reunião
C19: =+C18+1 -> 16 | D19: Carteira do Santander | E19: NPL | F19: Diversos | G19: Em análise
C20: =+C19+1 -> 17 | D20: ERBE - Carteira de Ativos/Passivos | E20: NPL | G20: Assinatura do NDA
C21: =+C20+1 -> 18 | D21: Eldorado Indústrias | E21: DIP | F21: Industria | G21: Em análise
C22: =+C21+1 -> 19 | D22: EMAE | E22: Crédito Estruturado | F22: Energia | G22: Aguardando call com a XP
C23: =+C22+1 -> 20 | D23: Empresa Agro | E23: DIP | F23: Agro | G23: Assinatura do NDA
C24: =+C23+1 -> 21 | D24: Projeto Cooperativa | E24: Crédito Estruturado | F24: Agro | G24: Aguardando informações
C25: =+C24+1 -> 22 | D25: Agro DFG | E25: DIP | F25: Agro | G25: Aguardando informações
C26: =+C25+1 -> 23 | D26: Nova Produtiva | E26: Crédito Estruturado | F26: Agro | G26: Solicitamos mais informações
C27: =+C26+1 -> 24 | D27: Adama - Elisa Agro | E27: NPL | F27: Agro | G27: Não enviamos proposta
C28: =+C27+1 -> 25 | D28: Agrobiológica | E28: Crédito Estruturado | F28: Agro | G28: Empresa do mesmo grupo (parte relacionada).
C29: =+C28+1 -> 26 | D29: CDNTV | E29: Crédito Estruturado | F29: Tecnologia | G29: Não enviamos proposta
C30: =+C29+1 -> 27 | D30: Farol D'Aldeia | E30: Crédito Estruturado | F30: Imobiliário | G30: Não enviamos proposta
C31: =+C30+1 -> 28 | D31: Vasco | E31: DIP | F31: Esportes | G31: Proposta Indicativa não aceita
C32: =+C31+1 -> 29 | D32: Imóvel com Locação Aperam | E32: Crédito Estruturado | F32: Indústria | G32: Antecipação de recebíveis que ainda não estao contratados com a Locatário
... C35: =+C34+1 -> 32 | D35: Leilão do Itau - Massificado | E35: NPL | F35: Diversos | G35: Não enviamos proposta
D38: Casos analisados desde Julho 2025
C39: # | D39: Ativos Judiciais | E39: Operação | F39: Status | I39: Entraram | J39: 27
C40: 1 | D40: BRCon | E40: Legal Claim | F40: On Hold - Fundo IV | I40: Saídas Reunião Anterior | J40: 7
C41: =+C40+1 -> 2 | D41: SINDJUS/DF | E41: Pré Precatório Federal | F41: Pedimos as infos, aguardando | I41: Novas Saídas | J41: 20 | N41: Technion x Petrobras
C42: =+C41+1 -> 3 | D42: Itabiriçu x Vale | E42: Ação Judicial | F42: Em negociação | I42: Numero da Lista Anterior | J42: 16 | N42: BRCON
C43: =+C42+1 -> 4 | D43: Andreza Maria x Pernambuco | E43: Precatorio Estadual | F43: Em análise | I43: Casos Ativos | J43: =+J39-J40-J41+J42 -> 16
C44: =+C43+1 -> 5 | D44: HEMOPAC x Maceio | E44: Precatorio Municipal | F44: Em análise
C45: =+C44+1 -> 6 | D45: Hospital Ortopédico x Maceio | E45: Precatorio Municipal | F45: Em análise
C46: =+C45+1 -> 7 | D46: Familia Horn | E46: Legal Claim | F46: Em análise
C47: =+C46+1 -> 8 | D47: B100 x Vibra | E47: Legal Claim | F47: Em análise
C48: =+C47+1 -> 9 | D48: Mlub | E48: Legal Claim | F48: Em análise
C49: =+C48+1 -> 10 | D49: Carteira de Creditos Judiciais - Odebretch | E49: Legal Claim | F49: Em análise
C50: =+C49+1 -> 11 | D50: CTR Itaboraí x Itaboraí | E50: Precatorio Municipal | F50: Em análise
C51: =+C50+1 -> 12 | D51: CTR Itaboraí x Itaboraí | E51: Precatorio Municipal | F51: Em análise
C52: =+C51+1 -> 13 | D52: Rio Dourado Participações | E52: Legal Claim | F52: Em análise
C53: =+C52+1 -> 14 | D53: BBD Seguros x Thyssen | E53: Legal Claim | F53: Em análise
C54: =+C53+1 -> 15 | D54: Railroad x Vale | E54: Litigation Finance | F54: Em análise
C55: =+C54+1 -> 16 | D55: Unicard | E55: Legal Claim | F55: Em análise
... C82: =+C81+1 -> 43 | D82: Projeto Mate | E82: Ativo Fiscal | F82: Recusado
C88: =+C65+1 -> 27 | D88: Precatório Varca Scatena | E88: Precatório Municipal | F88: Recusado | G88: =+INDEX(Pipe!N:N,MATCH(D88,Pipe!E:E,0)) -> Não
C89: =+C88+1 -> 28 | D89: Precatório Paraná - Balduíno João Bellé | E89: Precatório Estadual | F89: Recusado | G89: =+INDEX(Pipe!N:N,MATCH(D89,Pipe!E:E,0)) -> Não
C90: =+C89+1 -> 29 | D90: Precatório Rio Grande do Sul | E90: Precatório Estadual | F90: Proposta abaixo do esperado | G90: =+INDEX(Pipe!N:N,MATCH(D90,Pipe!E:E,0)) -> Não
C91: =+C90+1 -> 30 | D91: Claim Trabalhista - Oriz | E91: Legal Claim | F91: Proposta abaixo do esperado | G91: =+INDEX(Pipe!N:N,MATCH(D91,Pipe!E:E,0)) -> Não
C92: =+C91+1 -> 31 | D92: Requisição de Pgto ST Cruz | E92: Precatório Federal | F92: Proposta abaixo do esperado | G92: =+INDEX(Pipe!N:N,MATCH(D92,Pipe!E:E,0)) -> Não
C93: =+C92+1 -> 32 | D93: Precatório do RJ - Royalties de Petróleo | E93: Precatório Federal | F93: Proposta abaixo do esperado | G93: =+INDEX(Pipe!N:N,MATCH(D93,Pipe!E:E,0)) -> Não
C94: =+C93+1 -> 33 | D94: Precatórios CNO | E94: Precatórios | F94: Proposta abaixo do esperado | G94: =+INDEX(Pipe!N:N,MATCH(D94,Pipe!E:E,0)) -> Não
C95: =+C94+1 -> 34 | D95: Precatorios Residencial Park | E95: Precatório Estadual | F95: Proposta abaixo do esperado | G95: =+INDEX(Pipe!N:N,MATCH(D95,Pipe!E:E,0)) -> Não
C96: =+C95+1 -> 35 | D96: Tronox - Compulsório Eletrobras | E96: Ação Judicial | F96: Recusado | G96: =+INDEX(Pipe!N:N,MATCH(D96,Pipe!E:E,0)) -> Não
C97: =+C96+1 -> 36 | D97: Precatório Macapá | E97: Precatório Municipal | F97: Recusado | G97: =+INDEX(Pipe!N:N,MATCH(D97,Pipe!E:E,0)) -> Não
C98: =+C97+1 -> 37 | D98: Associados FAACO x Correios | E98: Pré Precatório | F98: Recusado | G98: =+INDEX(Pipe!N:N,MATCH(D98,Pipe!E:E,0)) -> Não
C99: =+C98+1 -> 38 | D99: Precatório Santa Catarina | E99: Precatório Estadual | F99: Recusado | G99: =+INDEX(Pipe!N:N,MATCH(D99,Pipe!E:E,0)) -> Não
C100: =+C99+1 -> 39 | D100: Precatório SP | E100: Precatório Estadual | F100: Recusado | G100: =+INDEX(Pipe!N:N,MATCH(D100,Pipe!E:E,0)) -> Não
... C117: =+C116+1 -> 56 | D117: Antonio Martins x União | E117: Precatório Federal | F117: Recusado | G117: =+INDEX(Pipe!N:N,MATCH(D117,Pipe!E:E,0)) -> Não

Sheet Reunião Vertical_1707
D1: Casos analisados desde Maio 2025
C2: # | D2: Ativos Financeiros | E2: Operação | F2: Setor | G2: Status | J2: Entraram | K2: 23
C3: 1 | D3: Gaia Geração | E3: Crédito Estruturado | F3: Energia | G3: Aprovado em Comitê | H3: =INDEX('Reuniao Vertical_1505'!P:P,MATCH('Reunião Vertical_1707'!D3,'Reuniao Vertical_1505'!I:I,0)) -> #N/A | J3: Saídas Reunião Anterior | K3: =21+12 -> 33
C4: =+C3+1 -> 2 | D4: Agrogalaxy | E4: DIP | F4: Agro | G4: Chamada de Capital Realizada | H4: =INDEX('Reuniao Vertical_1505'!P:P,MATCH('Reunião Vertical_1707'!D4,'Reuniao Vertical_1505'!I:I,0)) -> x | J4: Novas Saídas | K4: 12
C5: =+C4+1 -> 3 | D5: Caetano x Covabra | E5: DIP | F5: Varejo - Supermercado | G5: Proposta Assinada | H5: =INDEX('Reuniao Vertical_1505'!P:P,MATCH('Reunião Vertical_1707'!D5,'Reuniao Vertical_1505'!I:I,0)) -> #N/A
C6: =+C5+1 -> 4 | D6: Trinity | E6: Crédito Estruturado | F6: Energia | G6: Investida | H6: =INDEX('Reuniao Vertical_1505'!P:P,MATCH('Reunião Vertical_1707'!D6,'Reuniao Vertical_1505'!I:I,0)) -> x | J6: Numero da Lista Anterior | K6: 35
C7: =+C6+1 -> 5 | D7: Eldorado Indústrias | E7: DIP | F7: Industria | G7: Em análise | H7: =INDEX('Reuniao Vertical_1505'!P:P,MATCH('Reunião Vertical_1707'!D7,'Reuniao Vertical_1505'!I:I,0)) -> #N/A | J7: Casos Ativos | K7: =+K2-K3-K4+K6 -> 13
C8: =+C7+1 -> 6 | D8: Marabraz | E8: Crédito Estruturado | F8: Varejo | G8: Aguardando Informações de novos Imóveis | H8: =INDEX('Reuniao Vertical_1505'!P:P,MATCH('Reunião Vertical_1707'!D8,'Reuniao Vertical_1505'!I:I,0)) -> #N/A
C9: =+C8+1 -> 7 | D9: Allonda | E9: Crédito Estruturado | F9: Engenharia | G9: Em análise | H9: =INDEX('Reuniao Vertical_1505'!P:P,MATCH('Reunião Vertical_1707'!D9,'Reuniao Vertical_1505'!I:I,0)) -> #N/A
C10: =+C9+1 -> 8 | D10: EMAE | E10: Crédito Estruturado | F10: Energia | G10: Aguardando call com a XP | H10: =INDEX('Reuniao Vertical_1505'!P:P,MATCH('Reunião Vertical_1707'!D10,'Reuniao Vertical_1505'!I:I,0)) -> #N/A
C11: =+C10+1 -> 9 | D11: Eletrodata | E11: Crédito Estruturado | F11: Engenharia | G11: Aguardando Informações | H11: =INDEX('Reuniao Vertical_1505'!P:P,MATCH('Reunião Vertical_1707'!D11,'Reuniao Vertical_1505'!I:I,0)) -> #N/A
C12: =+C11+1 -> 10 | D12: Lavoro | E12: Crédito Estruturado | F12: Agro | G12: Aguardando Informações da Estrutura | H12: =INDEX('Reuniao Vertical_1505'!P:P,MATCH('Reunião Vertical_1707'!D12,'Reuniao Vertical_1505'!I:I,0)) -> #N/A
C13: =+C12+1 -> 11 | D13: Adama - Elisa Agro | E13: NPL | F13: Agro | G13: Em análise | H13: =INDEX('Reuniao Vertical_1505'!P:P,MATCH('Reunião Vertical_1707'!D13,'Reuniao Vertical_1505'!I:I,0)) -> #N/A
C14: =+C13+1 -> 12 | D14: Agrobiológica | E14: Crédito Estruturado | F14: Agro | G14: Vamos propor di+20%.a.a | H14: =INDEX('Reuniao Vertical_1505'!P:P,MATCH('Reunião Vertical_1707'!D14,'Reuniao Vertical_1505'!I:I,0)) -> #N/A
C15: =+C14+1 -> 13 | D15: CDNTV | E15: Crédito Estruturado | F15: Tecnologia | G15: Em análise | H15: =INDEX('Reuniao Vertical_1505'!P:P,MATCH('Reunião Vertical_1707'!D15,'Reuniao Vertical_1505'!I:I,0)) -> #N/A
C16: =+C15+1 -> 14 | D16: Leilão do Itau - Atacado | E16: NPL | F16: Leilão NPL | G16: Não enviamos proposta | H16: =INDEX('Reuniao Vertical_1505'!P:P,MATCH('Reunião Vertical_1707'!D16,'Reuniao Vertical_1505'!I:I,0)) -> #N/A
C17: =+C16+1 -> 15 | D17: Falência Cia Nacional de Tecidos | E17: NPL | F17: Industria | G17: Não enviamos proposta | H17: =INDEX('Reuniao Vertical_1505'!P:P,MATCH('Reunião Vertical_1707'!D17,'Reuniao Vertical_1505'!I:I,0)) -> #N/A
C18: =+C17+1 -> 16 | D18: Master Grão | E18: DIP | F18: Agro | G18: Garantia operacional e nao estao em nome da empresa | H18: =INDEX('Reuniao Vertical_1505'!P:P,MATCH('Reunião Vertical_1707'!D18,'Reuniao Vertical_1505'!I:I,0)) -> #N/A
C19: =+C18+1 -> 17 | D19: Novonor | E19: Crédito Estruturado | F19: Infraestrutura | G19: Retorno e Garantias | H19: =INDEX('Reuniao Vertical_1505'!P:P,MATCH('Reunião Vertical_1707'!D19,'Reuniao Vertical_1505'!I:I,0)) -> #N/A
... C27: =+C26+1 -> 25 | D27: Agridrones | E27: CRA | F27: Agro | G27: Retorno abaixo do esperado | H27: =INDEX('Reuniao Vertical_1505'!P:P,MATCH('Reunião Vertical_1707'!D27,'Reuniao Vertical_1505'!I:I,0)) -> #N/A
C28: =+C27+1 -> 26 | D28: Sagrados Corações x BB | E28: NPL | G28: Retorno abaixo do esperado | H28: =INDEX('Reuniao Vertical_1505'!P:P,MATCH('Reunião Vertical_1707'!D28,'Reuniao Vertical_1505'!I:I,0)) -> #N/A
C29: =+C28+1 -> 27 | D29: Patense | E29: DIP | F29: Resíduo Animal | G29: Capacidade de pagamento e Garantias | H29: =INDEX('Reuniao Vertical_1505'!P:P,MATCH('Reunião Vertical_1707'!D29,'Reuniao Vertical_1505'!I:I,0)) -> x
C30: =+C29+1 -> 28 | D30: South Star | E30: Crédito Estruturado | F30: Mineração | G30: Subordinação ao Stream e Op. Equity | H30: =INDEX('Reuniao Vertical_1505'!P:P,MATCH('Reunião Vertical_1707'!D30,'Reuniao Vertical_1505'!I:I,0)) -> x
C31: =+C30+1 -> 29 | D31: Seteloc | E31: Crédito Estruturado | F31: Aluguel de Carros | G31: Sem Retorno | H31: =INDEX('Reuniao Vertical_1505'!P:P,MATCH('Reunião Vertical_1707'!D31,'Reuniao Vertical_1505'!I:I,0)) -> x
C32: =+C31+1 -> 30 | D32: Artec | E32: Crédito Estruturado | F32: Industria | G32: Sem Retorno | H32: =INDEX('Reuniao Vertical_1505'!P:P,MATCH('Reunião Vertical_1707'!D32,'Reuniao Vertical_1505'!I:I,0)) -> x
C33: =+C32+1 -> 31 | D33: Rica Alimentos | E33: DIP | F33: Proteína Animal | G33: Sem Retorno | H33: =INDEX('Reuniao Vertical_1505'!P:P,MATCH('Reunião Vertical_1707'!D33,'Reuniao Vertical_1505'!I:I,0)) -> x
C34: =+C33+1 -> 32 | D34: Galileo e Assespa | E34: NPL | F34: Educação - Falência | G34: A&M pediu prazo para devolutiva | H34: =INDEX('Reuniao Vertical_1505'!P:P,MATCH('Reunião Vertical_1707'!D34,'Reuniao Vertical_1505'!I:I,0)) -> x
C35: =+C34+1 -> 33 | D35: Polígono Venture Debt | E35: NPL | F35: VC | G35: Retorno abaixo do Hurdle | H35: =INDEX('Reuniao Vertical_1505'!P:P,MATCH('Reunião Vertical_1707'!D35,'Reuniao Vertical_1505'!I:I,0)) -> x
C36: =+C35+1 -> 34 | D36: Servi-San | E36: Carteira de Ativos + NPL | F36: Empresa de Serviços | G36: Capacidade de pagamento e Garantias | H36: =INDEX('Reuniao Vertical_1505'!P:P,MATCH('Reunião Vertical_1707'!D36,'Reuniao Vertical_1505'!I:I,0)) -> x
C37: =+C36+1 -> 35 | D37: Acrefort | E37: Crédito Estruturado | F37: Agro | G37: Capacidade de pagamento e Garantias | H37: =INDEX('Reuniao Vertical_1505'!P:P,MATCH('Reunião Vertical_1707'!D37,'Reuniao Vertical_1505'!I:I,0)) -> x
C38: =+C37+1 -> 36 | D38: Hileia | E38: Crédito Estruturado | F38: Alimentício | G38: Estágio Incipiente | H38: =INDEX('Reuniao Vertical_1505'!P:P,MATCH('Reunião Vertical_1707'!D38,'Reuniao Vertical_1505'!I:I,0)) -> x
C39: =+C38+1 -> 37 | D39: Intecnial | E39: DIP | F39: Metalúrgica | G39: Estágio Incipiente | H39: =INDEX('Reuniao Vertical_1505'!P:P,MATCH('Reunião Vertical_1707'!D39,'Reuniao Vertical_1505'!I:I,0)) -> x
C40: =+C39+1 -> 38 | D40: Caso Banco de Investimento | E40: Crédito Estruturado | F40: Financeiro | G40: Negado pelo Produtor | H40: =INDEX('Reuniao Vertical_1505'!P:P,MATCH('Reunião Vertical_1707'!D40,'Reuniao Vertical_1505'!I:I,0)) -> x
... C48: =+C47+1 -> 46 | D48: Morro Verde | E48: NPL + Crédito Estruturado | F48: Mineração | G48: Estágio Incipiente | H48: =INDEX('Reuniao Vertical_1505'!P:P,MATCH('Reunião Vertical_1707'!D48,'Reuniao Vertical_1505'!I:I,0)) -> x
D49: Rede de Academias
D50: TS bridge to FON - Oakberry 50m (20+20+10)
D52: Casos analisados desde Maio 2025
C53: # | D53: Ativos Judiciais | E53: Operação | F53: Status | J53: Entraram | K53: 35
C54: 1 | D54: BRCon | E54: Legal Claim | F54: Proposta aceita para o Fundo IV | G54: =INDEX('Reuniao Vertical_1505'!P:P,MATCH('Reunião Vertical_1707'!D54,'Reuniao Vertical_1505'!I:I,0)) -> x | J54: Saídas Reunião Anterior | K54: 37
C55: =+C54+1 -> 2 | D55: SINDJUS/DF | E55: Pré Precatório Federal | F55: Pedimos as infos, aguardando | G55: =INDEX('Reuniao Vertical_1505'!P:P,MATCH('Reunião Vertical_1707'!D55,'Reuniao Vertical_1505'!I:I,0)) -> #N/A | J55: Novas Saídas | K55: 10
C56: =+C55+1 -> 3 | D56: B100 x Vibra | E56: Legal Claim | F56: Proposa Enviada. Aguardando respostas | G56: =INDEX('Reuniao Vertical_1505'!P:P,MATCH('Reunião Vertical_1707'!D56,'Reuniao Vertical_1505'!I:I,0)) -> #N/A
C57: =+C56+1 -> 4 | D57: Feijó Cavagnoli x BRDistribuidora | E57: Legal Claim | F57: Tinham achado baixo a proposta, aguardando resposta | G57: =INDEX('Reuniao Vertical_1505'!P:P,MATCH('Reunião Vertical_1707'!D57,'Reuniao Vertical_1505'!I:I,0)) -> #N/A | J57: Numero da Lista Anterior | K57: 28
C58: =+C57+1 -> 5 | D58: Itabiriçu x Vale | E58: Ação Judicial | F58: Em negociação | G58: =INDEX('Reuniao Vertical_1505'!P:P,MATCH('Reunião Vertical_1707'!D58,'Reuniao Vertical_1505'!I:I,0)) -> #N/A | J58: Casos Ativos | K58: =+K53-K54-K55+K57 -> 16
C59: =+C58+1 -> 6 | D59: Sanerio x Prefeitura de Duque de Caxias | E59: Precatorio Municipal | F59: Aguardando definiçao da PEC 66 | G59: =INDEX('Reuniao Vertical_1505'!P:P,MATCH('Reunião Vertical_1707'!D59,'Reuniao Vertical_1505'!I:I,0)) -> #N/A
C60: =+C59+1 -> 7 | D60: Achiles Reis x Rio de Janeiro | E60: Precatório Estadual | F60: Enviamos um preço. Aguardando respostas | G60: =INDEX('Reuniao Vertical_1505'!P:P,MATCH('Reunião Vertical_1707'!D60,'Reuniao Vertical_1505'!I:I,0)) -> #N/A
C61: =+C60+1 -> 8 | D61: Mlub | E61: Legal Claim | F61: Proposa Enviada. Aguardando respostas | G61: =INDEX('Reuniao Vertical_1505'!P:P,MATCH('Reunião Vertical_1707'!D61,'Reuniao Vertical_1505'!I:I,0)) -> #N/A
C62: =+C61+1 -> 9 | D62: CITEL x Maceio | E62: Precatorio Municipal | F62: Em análise | G62: =INDEX('Reuniao Vertical_1505'!P:P,MATCH('Reunião Vertical_1707'!D62,'Reuniao Vertical_1505'!I:I,0)) -> #N/A
C63: =+C62+1 -> 10 | D63: HEMOPAC x Maceio | E63: Precatorio Municipal | F63: Em análise | G63: =INDEX('Reuniao Vertical_1505'!P:P,MATCH('Reunião Vertical_1707'!D63,'Reuniao Vertical_1505'!I:I,0)) -> #N/A
C64: =+C63+1 -> 11 | D64: Hospital Ortopédico x Maceio | E64: Precatorio Municipal | F64: Em análise | G64: =INDEX('Reuniao Vertical_1505'!P:P,MATCH('Reunião Vertical_1707'!D64,'Reuniao Vertical_1505'!I:I,0)) -> #N/A
C65: =+C64+1 -> 12 | D65: Fundação Hospital Agro Industria x Maceio | E65: Precatorio Municipal | F65: Em análise | G65: =INDEX('Reuniao Vertical_1505'!P:P,MATCH('Reunião Vertical_1707'!D65,'Reuniao Vertical_1505'!I:I,0)) -> #N/A
C66: =+C65+1 -> 13 | D66: Familia Horn | E66: Legal Claim | F66: Em análise | G66: =INDEX('Reuniao Vertical_1505'!P:P,MATCH('Reunião Vertical_1707'!D66,'Reuniao Vertical_1505'!I:I,0)) -> #N/A | J66: =2.8*4*12 -> 134.4
C67: =+C66+1 -> 14 | D67: Cristiano Aparecido Baptista x Antonio Francisquini | E67: Litigation Finance | F67: Em análise | G67: =INDEX('Reuniao Vertical_1505'!P:P,MATCH('Reunião Vertical_1707'!D67,'Reuniao Vertical_1505'!I:I,0)) -> #N/A
C68: =+C67+1 -> 15 | D68: Andreza Maria x Pernambuco | E68: Precatorio Estadual | F68: Em análise | G68: =INDEX('Reuniao Vertical_1505'!P:P,MATCH('Reunião Vertical_1707'!D68,'Reuniao Vertical_1505'!I:I,0)) -> #N/A
C69: =+C68+1 -> 16 | D69: Honorários Sucumbenciais x Siguler Guff | E69: Precatório | F69: Em análise | G69: =INDEX('Reuniao Vertical_1505'!P:P,MATCH('Reunião Vertical_1707'!D69,'Reuniao Vertical_1505'!I:I,0)) -> #N/A
C70: =+C69+1 -> 17 | D70: Precatório Varca Scatena | E70: Precatório Municipal | F70: Recusado | G70: =INDEX('Reuniao Vertical_1505'!P:P,MATCH('Reunião Vertical_1707'!D70,'Reuniao Vertical_1505'!I:I,0)) -> x
C71: =+C70+1 -> 18 | D71: Precatório Paraná - Balduíno João Bellé | E71: Precatório Estadual | F71: Recusado | G71: =INDEX('Reuniao Vertical_1505'!P:P,MATCH('Reunião Vertical_1707'!D71,'Reuniao Vertical_1505'!I:I,0)) -> #N/A
C72: =+C71+1 -> 19 | D72: Precatório Rio Grande do Sul | E72: Precatório Estadual | F72: Proposta abaixo do esperado | G72: =INDEX('Reuniao Vertical_1505'!P:P,MATCH('Reunião Vertical_1707'!D72,'Reuniao Vertical_1505'!I:I,0)) -> x
C73: =+C72+1 -> 20 | D73: Claim Trabalhista - Oriz | E73: Legal Claim | F73: Proposta abaixo do esperado | G73: =INDEX('Reuniao Vertical_1505'!P:P,MATCH('Reunião Vertical_1707'!D73,'Reuniao Vertical_1505'!I:I,0)) -> x
C74: =+C73+1 -> 21 | D74: Requisição de Pgto ST Cruz | E74: Precatório Federal | F74: Proposta abaixo do esperado | G74: =INDEX('Reuniao Vertical_1505'!P:P,MATCH('Reunião Vertical_1707'!D74,'Reuniao Vertical_1505'!I:I,0)) -> x
C75: =+C74+1 -> 22 | D75: Precatório do RJ - Royalties de Petróleo | E75: Precatório Federal | F75: Proposta abaixo do esperado | G75: x
C76: =+C75+1 -> 23 | D76: Precatórios CNO | E76: Precatórios | F76: Proposta abaixo do esperado | G76: x
C77: =+C76+1 -> 24 | D77: Precatorios Residencial Park | E77: Precatório Estadual | F77: Proposta abaixo do esperado | G77: x
C78: =+C77+1 -> 25 | D78: Tronox - Compulsório Eletrobras | E78: Ação Judicial | F78: Recusado | G78: x
C79: =+C78+1 -> 26 | D79: Precatório Macapá | E79: Precatório Municipal | F79: Recusado | G79: x
C80: =+C79+1 -> 27 | D80: Associados FAACO x Correios | E80: Pré Precatório | F80: Recusado | G80: x
C81: =+C80+1 -> 28 | D81: Precatório Santa Catarina | E81: Precatório Estadual | F81: Recusado | G81: =INDEX('Reuniao Vertical_1505'!P:P,MATCH('Reunião Vertical_1707'!D81,'Reuniao Vertical_1505'!I:I,0)) -> #N/A
C82: =+C81+1 -> 29 | D82: Precatório SP | E82: Precatório Estadual | F82: Recusado | G82: =INDEX('Reuniao Vertical_1505'!P:P,MATCH('Reunião Vertical_1707'!D82,'Reuniao Vertical_1505'!I:I,0)) -> #N/A
C83: =+C82+1 -> 30 | D83: Precatório AM | E83: Precatório Estadual | F83: Recusado | G83: =INDEX('Reuniao Vertical_1505'!P:P,MATCH('Reunião Vertical_1707'!D83,'Reuniao Vertical_1505'!I:I,0)) -> #N/A
C84: =+C83+1 -> 31 | D84: Mangaratiba | E84: Pré Precatório Municipal | F84: Recusado | G84: =INDEX('Reuniao Vertical_1505'!P:P,MATCH('Reunião Vertical_1707'!D84,'Reuniao Vertical_1505'!I:I,0)) -> #N/A
C85: =+C84+1 -> 32 | D85: Fundação Hospitalar de Ibirataia | E85: Precatório Federal | F85: Recusado | G85: =INDEX('Reuniao Vertical_1505'!P:P,MATCH('Reunião Vertical_1707'!D85,'Reuniao Vertical_1505'!I:I,0)) -> #N/A
C86: =+C85+1 -> 33 | D86: CIB Construtora | E86: Pré Precatório Federal | F86: Recusado | G86: =INDEX('Reuniao Vertical_1505'!P:P,MATCH('Reunião Vertical_1707'!D86,'Reuniao Vertical_1505'!I:I,0)) -> #N/A
C87: =+C86+1 -> 34 | D87: Precatório de Alagoas | E87: Precatório Estadual | F87: Recusado | G87: =INDEX('Reuniao Vertical_1505'!P:P,MATCH('Reunião Vertical_1707'!D87,'Reuniao Vertical_1505'!I:I,0)) -> #N/A
C88: =+C87+1 -> 35 | D88: Bebidas Bandeirantes | E88: Legal Claim | F88: Recusado | G88: =INDEX('Reuniao Vertical_1505'!P:P,MATCH('Reunião Vertical_1707'!D88,'Reuniao Vertical_1505'!I:I,0)) -> #N/A
C89: =+C88+1 -> 36 | D89: Projeto Themis - Hapvida | E89: Legal Claim | F89: Recusado | G89: =INDEX('Reuniao Vertical_1505'!P:P,MATCH('Reunião Vertical_1707'!D89,'Reuniao Vertical_1505'!I:I,0)) -> #N/A
C90: =+C89+1 -> 37 | D90: Construtora Itau x Sanepar | E90: Legal Claim | F90: Recusado | G90: =INDEX('Reuniao Vertical_1505'!P:P,MATCH('Reunião Vertical_1707'!D90,'Reuniao Vertical_1505'!I:I,0)) -> #N/A
C91: =+C90+1 -> 38 | D91: JVN Advogados | E91: Litigation Finance | F91: Recusado | G91: =INDEX('Reuniao Vertical_1505'!P:P,MATCH('Reunião Vertical_1707'!D91,'Reuniao Vertical_1505'!I:I,0)) -> #N/A
C92: =+C91+1 -> 39 | D92: Raul Ferreira e Joaquim Ferreira | E92: Precatorio Federal | F92: Recusado | G92: =INDEX('Reuniao Vertical_1505'!P:P,MATCH('Reunião Vertical_1707'!D92,'Reuniao Vertical_1505'!I:I,0)) -> #N/A
... C99: =+C98+1 -> 46 | D99: Antonio Martins x União | E99: Precatório Federal | F99: Recusado | G99: =INDEX('Reuniao Vertical_1505'!P:P,MATCH('Reunião Vertical_1707'!D99,'Reuniao Vertical_1505'!I:I,0)) -> #N/A

Sheet Reuniao Vertical_1505
I2: Casos ativos desde a última | M2: =+MAX(M4:M24) -> 45775
F3: Entraram | G3: 11 | H3: # | I3: Ativos Financeiros | J3: Operação | K3: Setor | L3: Status | Q3: Responsável | R3: Prioridade | S3: To DO
F4: Saídas Reunião Anterior | G4: 15 | H4: 1 | I4: Grupo Monte Alegre | J4: DIP | K4: Agro | L4: Negado pelo Produtor | M4: =+INDEX(Pipe!F:F,MATCH('Reuniao Vertical_1505'!I4,Pipe!E:E,0)) -> 45734 | P4: x | V4: 3 | W4: Patense
F5: Novas Saídas | G5: 13 | H5: =+H4+1 -> 2 | I5: Agrogalaxy | J5: Compra UPI | K5: Agro | L5: Aguardando Certame | M5: =+INDEX(Pipe!F:F,MATCH('Reuniao Vertical_1505'!I5,Pipe!E:E,0)) -> 45751 | P5: x | Q5: Chris | R5: 1 | S5: Data Certame | V5: 3 | W5: South Star
H6: =+H5+1 -> 3 | I6: Grupo Andrade | J6: NPL + DIP | K6: Usina de Cana-de-açucar | L6: Aguardando Comitê | M6: =+INDEX(Pipe!F:F,MATCH('Reuniao Vertical_1505'!I6,Pipe!E:E,0)) -> 45754 | O6: > nao conseguimos fazer as reunioes que queriamos, nao conseguimos fazer proposta e outra pessoa levou | P6: x | R6: 1 | S6: Finalizar DD | V6: 4 | W6: Seteloc
H7: =+H6+1 -> 4 | I7: Sealion Shipping Ltd. | J7: NPL | K7: Navegação | L7: Aguardando devolutiva NBO | M7: =+INDEX(Pipe!F:F,MATCH('Reuniao Vertical_1505'!I30,Pipe!E:E,0)) -> 45726 | P7: x | V7: 3 | W7: Artec
H8: =+H7+1 -> 5 | I8: Patense | J8: DIP | K8: Resíduo Animal | L8: Análises Iniciais | M8: =+INDEX(Pipe!F:F,MATCH('Reuniao Vertical_1505'!I31,Pipe!E:E,0)) -> 45748 | P8: x | Q8: Chris | R8: 3 | V8: 4 | W8: Rica Alimentos
H9: =+H8+1 -> 6 | I9: South Star | J9: Crédito Estruturado | K9: Mineração | L9: Aguardando envio de informações | M9: 45685 | P9: x | Q9: Chris | R9: 3 | S9: Pegar o NDA e pedir as infos | V9: 4 | W9: Galileo e Assespa
H10: =+H9+1 -> 7 | I10: Seteloc | J10: Crédito Estruturado | L10: Aguardando agendamento de reunião | M10: 45764 | P10: x | Q10: Chris | R10: 4 | V10: 4 | W10: Polígono Venture Debt
H11: =+H10+1 -> 8 | I11: Artec | J11: Crédito Estruturado | L11: Em análise | M11: =+INDEX(Pipe!F:F,MATCH('Reuniao Vertical_1505'!I33,Pipe!E:E,0)) -> 45597 | P11: x | Q11: Chris | R11: 3 | S11: Aguardando detalhamento ICMS | V11: 1 | W11: Servi-San
H12: =+H11+1 -> 9 | I12: Rica Alimentos | J12: DIP | K12: Proteína Animal | L12: Em análise | M12: 45747 | P12: x | Q12: Penido/LO | R12: 4 | V12: 3 | W12: Acrefort
H13: =+H12+1 -> 10 | I13: Galileo e Assespa | J13: NPL | K13: Educação - Falência | L13: A&M pediu prazo para devolutiva | M13: =+INDEX(Pipe!F:F,MATCH('Reuniao Vertical_1505'!I34,Pipe!E:E,0)) -> 45754 | P13: x | Q13: Penido/LO | R13: 4 | V13: 3 | W13: Hileia
H14: =+H13+1 -> 11 | I14: Polígono Venture Debt | J14: NPL | K14: VC | L14: Aguardando NDA | M14: =+INDEX(Pipe!F:F,MATCH('Reuniao Vertical_1505'!I9,Pipe!E:E,0)) -> 45751 | P14: x | Q14: LO | R14: 4 | S14: Responder NDA | V14: 2 | W14: Intecnial
H15: =+H14+1 -> 12 | I15: Servi-San | J15: Carteira de Ativos + NPL | K15: Empresa de Serviços | L15: Em análise | M15: =+INDEX(Pipe!F:F,MATCH('Reuniao Vertical_1505'!I35,Pipe!E:E,0)) -> 45744 | P15: x | R15: 1 | S15: Montar estratégi/estrutura da OP. e cobra avaliação dos claims | V15: 2 | W15: Caso Banco de Investimento
H16: =+H15+1 -> 13 | I16: Acrefort | J16: Crédito Estruturado | K16: Agro | L16: Em análise | M16: =+INDEX(Pipe!F:F,MATCH('Reuniao Vertical_1505'!I36,Pipe!E:E,0)) -> 45751 | P16: x | Q16: Chris | R16: 3 | S16: Olhar 21 e/ou 22/05 | V16: 1 | W16: Trinity
H17: =+H16+1 -> 14 | I17: Hileia | J17: Crédito Estruturado | K17: Alimentício | L17: Aguardando NDA | M17: =+INDEX(Pipe!F:F,MATCH('Reuniao Vertical_1505'!I37,Pipe!E:E,0)) -> 45737 | P17: x | Q17: Penido | R17: 3 | S17: Marcar conversar com Troesser
H18: =+H17+1 -> 15 | I18: Intecnial | J18: DIP | K18: Metalúrgica | L18: Indicar possíveis condições | M18: =+INDEX(Pipe!F:F,MATCH('Reuniao Vertical_1505'!I10,Pipe!E:E,0)) -> 45764 | P18: x | Q18: Chris | R18: 2 | S18: Aguardando resposta do valor dos ativos
H19: =+H18+1 -> 16 | I19: Caso Banco de Investimento | J19: Crédito Estruturado | K19: Financeiro | L19: Negado pelo Produtor | M19: =+INDEX(Pipe!F:F,MATCH('Reuniao Vertical_1505'!I11,Pipe!E:E,0)) -> 45775 | P19: x | Q19: Penido | R19: 4
H20: =+H19+1 -> 17 | I20: Trinity | J20: Crédito Estruturado | K20: Energia | L20: Em análise | M20: =+INDEX(Pipe!F:F,MATCH('Reuniao Vertical_1505'!I12,Pipe!E:E,0)) -> 45757 | P20: x | Q20: Penido | R20: 1
F21: =2.332/1.475 -> 1.5810169 | H21: =+H20+1 -> 18 | I21: Eldorado | J21: DIP | K21: Industria | L21: Em análise | P21: x | Q21: Chris | R21: 1 | S21: TS
H22: =+H21+1 -> 19 | I22: Hospital Albert Sabin | J22: Crédito Estruturado | K22: Saúde | L22: Em análise | P22: x | Q22: Penido | R22: 1 | S22: Financiar transação tributária
H23: =+H22+1 -> 20 | I23: Bravante | J23: Crédito Estruturado | K23: Navegação | L23: Em análise | P23: x | Q23: Penido | R23: 1
H24: =+H23+1 -> 21 | I24: FIAGRO Bocom BBM | J24: Crédito Estruturado | K24: Agro | L24: Retorno abaixo do Hurdle | M24: 45684 | P24: x
H25: =+H24+1 -> 22 | I25: Projeto Catarina | J25: Crédito Estruturado | K25: Bebidas | L25: Encaminhado para High Yield | P25: x
H26: =+H25+1 -> 23 | I26: Niraj Towers | J26: Crédito Estruturado | K26: Construção | L26: Capacidade de pagamento e Garantias | P26: x
H27: =+H26+1 -> 24 | I27: Fazenda | J27: Crédito Estruturado | K27: Agro | L27: Capacidade de pagamento e Garantias | P27: x
H28: =+H27+1 -> 25 | I28: Fornecedor Equipamentos - Curitiba | J28: Crédito Estruturado | K28: Aluguel de Equipamentos | L28: Capacidade de pagamento e Garantias | P28: x
H29: =+H28+1 -> 26 | I29: Gebana + Cataratas | J29: Crédito Estruturado | K29: Trading de Grãos | L29: Sem capacidade de pagamento | P29: x
H30: =+H29+1 -> 27 | I30: Grupo Fayad | J30: NPL | K30: Pecuária | L30: Sem Retorno BB | P30: x
H31: =+H30+1 -> 28 | I31: Carlos Sanchez (EMS) + BB | J31: NPL | K31: Novo Fundo | L31: Sem Retorno BB | P31: x
C32: Precatório Fortaleza | D32: Precatório Municipal | H32: =+H31+1 -> 29 | I32: Grupo Marabraz | J32: Crédito Estruturado | K32: Varejo | L32: Problema fiscal | P32: x
C33: Precatório Porto Velho | D33: Precatório Municipal | H33: =+H32+1 -> 30 | I33: Polo Wear | J33: Crédito Estruturado | K33: Varejo | L33: Sem Retorno do cliente | P33: x
C34: Contax | D34: Pré Precatório Federal | H34: =+H33+1 -> 31 | I34: Morro Verde | J34: NPL + Crédito Estruturado | K34: Mineração | L34: Estágio Incipiente | P34: x
C35: Precatório Monteplan | D35: Precatório Estadual | H35: =+H34+1 -> 32 | I35: Grupo Elfa | J35: Crédito Estruturado | K35: Saúde | L35: Encaminhado para High Yield | P35: x
C36: Precatório Rio de Janeiro | D36: Precatório Estadual | H36: =+H35+1 -> 33 | I36: Banco Santos | J36: NPL | K36: Financeiro - Falência | L36: Dificuldade de aquisição dos créditos | P36: x
C37: Precatório Paraná | D37: Precatório Estadual | H37: =+H36+1 -> 34 | I37: Lotus Grains & oilseeds s.a | J37: Crédito Estruturado | K37: Trading | L37: Sem capacidade de pagamento | P37: x
C38: Precatório Belém (SBC +Adv) | D38: Precatório Municipal | H38: =+H37+1 -> 35 | I38: Recebíveis de Café | J38: Antecipação de Recebíveis | K38: Café | L38: Retorno abaixo do Hurdle | P38: x
C39: AGIS Construção | D39: Pré Precatório Federal
C41: Precatório Varca Scatena | D41: Precatório Municipal | I41: Casos ativos desde a última | M41: =+MAX(M43:M55) -> 45754
C42: Precatório Paraná - Balduíno João Bellé | D42: Precatório Estadual | F42: Entraram | G42: 15 | H42: # | I42: Ativos Judiciais | J42: Operação | K42: Setor | L42: Status
C43: Precatório Rio Grande do Sul | D43: Precatório Estadual | F43: Saídas Reunião Anterior | G43: 15 | H43: 1 | I43: BRCon | J43: Legal Claim | K43: Construção | L43: Envio de Minuta | M43: =+INDEX(Pipe!F:F,MATCH('Reuniao Vertical_1505'!I43,Pipe!E:E,0)) -> 45530 | P43: x
F44: Novas Saídas | G44: 11 | H44: =+H43+1 -> 2 | I44: Sealion Brasil | J44: Legal Claim e Precatório | K44: Navegação | L44: Revisando precificação | M44: 45685 | P44: x
H45: =+H44+1 -> 3 | I45: Petroenge x Petrobras | J45: Legal Claim + DIP | K45: Serviços O&G | L45: Aguardando retorno do cedente | M45: 45567 | P45: x
C46: Claim Trabalhista - Oriz | D46: Legal Claim | H46: =+H45+1 -> 4 | I46: Honorários Feira de Santana | J46: Pré precatório Municipal | L46: Investido | M46: 45737 | P46: x
H47: =+H46+1 -> 5 | I47: Precatório Monteplan | J47: Precatório Estadual | L47: Aguardando Comitê | M47: 45742 | P47: x | Q47: =5%*130.15 -> 6.5075
H48: =+H47+1 -> 6 | I48: Precatório Varca Scatena | J48: Precatório Municipal | L48: Em análise | M48: 45716 | P48: x
H49: =+H48+1 -> 7 | I49: Precatório Belém (SBC +Adv) | J49: Precatório Municipal | L49: Em análise | M49: =+INDEX(Pipe!F:F,MATCH('Reuniao Vertical_1505'!I70,Pipe!E:E,0)) -> 45643 | P49: x
H50: =+H49+1 -> 8 | I50: MRV | J50: Legal Claim | K50: Construção | L50: Aguardando devolutiva da proposta | M50: =+INDEX(Pipe!F:F,MATCH('Reuniao Vertical_1505'!I50,Pipe!E:E,0)) -> 45686 | P50: x
C51: Requisição de Pgto ST Cruz | D51: Precatório Federal | H51: =+H50+1 -> 9 | I51: Armando Conde x Cyrella | J51: Legal Claim | K51: Construção | L51: Advogado analisando as infos solicitadas | M51: 45706 | P51: x
C52: Precatório Ceara | D52: Precatório Estadual | H52: =+H51+1 -> 10 | I52: GE e Voith x Furnas | J52: Legal Claim | K52: Construção | L52: Aguardando devolutiva da proposta | M52: =+INDEX(Pipe!F:F,MATCH('Reuniao Vertical_1505'!I52,Pipe!E:E,0)) -> 45715 | P52: x
H53: =+H52+1 -> 11 | I53: Precatórios Rio | J53: Precatório Estadual | L53: Aguardando Ofício | M53: 45731 | P53: x
C54: Auto Pátio Lageado | D54: Precatório Estadual | H54: =+H53+1 -> 12 | I54: Technip | J54: Legal Claim | K54: Energia | L54: Em análise inicial | M54: =+INDEX(Pipe!F:F,MATCH('Reuniao Vertical_1505'!I54,Pipe!E:E,0)) -> 45751 | P54: x
H55: =+H54+1 -> 13 | I55: Clinica Cristo Rei x White Martins | J55: Legal Claim | K55: Gás Natural | L55: Sem valor definido - em monitoramento | M55: =+INDEX(Pipe!F:F,MATCH('Reuniao Vertical_1505'!I55,Pipe!E:E,0)) -> 45754 | P55: x
H56: =+H55+1 -> 14 | I56: Precatório Alagoas | J56: Pré Precatório Federal | L56: Em análise inicial | P56: x
H57: =+H56+1 -> 15 | I57: Requisição de Pgto ST Cruz | J57: Precatório Federal | L57: Em análise | P57: x
H58: =+H57+1 -> 16 | I58: Precatório Ceara | J58: Precatório Estadual | L58: Em análise | P58: x
H59: =+H58+1 -> 17 | I59: Auto Pátio Lageado | J59: Precatório Estadual | L59: Em análise | P59: x
H60: =+H59+1 -> 18 | I60: Precatório Fortaleza | J60: Precatório Municipal | L60: Município com atraso de 4/5 anos | P60: x
H61: =+H60+1 -> 19 | I61: Precatório Porto Velho | J61: Precatório Municipal | L61: prazo de pagamento excede o limite do fundo | P61: x
H62: =+H61+1 -> 20 | I62: Contax | J62: Pré Precatório Federal | L62: Não tinha comprovação de crédito | P62: x
H63: =+H62+1 -> 21 | I63: Precatório Rio de Janeiro | J63: Precatório Estadual | L63: Orçamento 2026 para RJ não entra no JGP Estruturados III. | P63: x
H64: =+H63+1 -> 22 | I64: Precatório Paraná | J64: Precatório Estadual | L64: Prazo de pagamento excede o limite do fundo | P64: x
H65: =+H64+1 -> 23 | I65: AGIS Construção | J65: Pré Precatório Federal | L65: Desalinhamento de preço | P65: x
H66: =+H65+1 -> 24 | I66: Precatório Rio Grande do Sul | J66: Precatório Estadual | L66: Fila de pagamento muito atrasado | P66: x
H67: =+H66+1 -> 25 | I67: Claim Trabalhista - Oriz | J67: Legal Claim | L67: Fora do escopo de atuação | P67: x
H68: =+H67+1 -> 26 | I68: Kerui Método | J68: Litigation Finance | K68: Engenharia | L68: Desisitência dos Acionista | P68: x
H69: =+H68+1 -> 27 | I69: Precatórios Tocantis | J69: Precatório Estadual | L69: Cessão Anterior | P69: x
H70: =+H69+1 -> 28 | I70: Detran - GO | J70: Pré-precatório | K70: Engenharia | L70: Desalinhamento de preço | P70: x

Sheet Originação
H1: Empresário/Executivo
N2: A | O2: A | AK2: JGP FA | AL2: =+AH3 -> 0.20229008 | AO2: Brokers | AP2: =+AL9 -> 0.32442748
B3: a | C3: a | D3: a | E3: a | F3: a | G3: a | H3: a | N3: Thiago Cordeiro - DBV Capital | O3: Broker V | P3: Broker | AF3: JGP FA | AG3: =COUNTIF(H:H,AF3) -> 53 | AH3: =+AG3/$AG$11 -> 0.20229008 | AK3: Escritórios Adv. | AL3: =+AH4 -> 0.1221374 | AO3: Boutiques | AP3: =+AL2+AL8 -> 0.22519084
B4: Precatorio Municipo de contagem | C4: 45583 | D4: 3A Investimentos | E4: =+INDEX($O$3:$O$132,MATCH(D4,$N$3:$N$132,0)) -> 0 | F4: 73 | G4: =+F4/261 -> 0.27969349 | H4: Broker | N4: Emanuel Cavalcanti - Convexa Investimentos | O4: Asset | P4: Asset | T4: JGP FA | U4: =+G77 -> 0.19157088 | AF4: Escritório Adv. | AG4: =COUNTIF(H:H,AF4) -> 32 | AH4: =+AG4/$AG$11 -> 0.1221374 | AK4: Empresários / Executivos | AL4: =+AH5 -> 0.11832061 | AO4: Escritórios Adv. | AP4: =+AL3 -> 0.1221374
B5: Santa Izabel | C5: 45387 | D5: Advisor | E5: =+INDEX($O$3:$O$132,MATCH(D5,$N$3:$N$132,0)) -> 0 | F5: 73 | G5: =+F5/261 -> 0.27969349 | H5: Consultoria | N5: Marco Andre Alencar | O5: Broker A | P5: Broker | T5: Broker A | U5: =+G158 -> 0.038314176 | AF5: Empresário/Executivo | AG5: =COUNTIF(H:H,AF5) -> 31 | AH5: =+AG5/$AG$11 -> 0.11832061 | AK5: Consultorias | AL5: =+AH6 -> 0.095419847 | AO5: Empresários / Executivos | AP5: =+AL4 -> 0.11832061
B6: Hospital Geral El Kadri | C6: 45401 | D6: Advisor | E6: =+INDEX($O$3:$O$132,MATCH(D6,$N$3:$N$132,0)) -> 0 | F6: 73 | G6: =+F6/261 -> 0.27969349 | H6: Consultoria | N6: Jorio Jadjiski | O6: Broker B | P6: Broker | T6: Consultoria A | U6: =+G167 -> 0.034482759 | AF6: Consultoria | AG6: =COUNTIF(H:H,AF6) -> 25 | AH6: =+AG6/$AG$11 -> 0.095419847 | AK6: Assets | AL6: =+AH7 -> 0.061068702 | AO6: Consultorias | AP6: =+AL5 -> 0.095419847
B7: Empresa Chatbot | C7: 45636 | D7: Advisor | E7: =+INDEX($O$3:$O$132,MATCH(D7,$N$3:$N$132,0)) -> 0 | F7: 73 | G7: =+F7/261 -> 0.27969349 | H7: Consultoria | N7: Paulo Viola (assessor) Celso Paes (CFO) | O7: Broker C | P7: Broker | T7: Escritoria Adv A | U7: =+G176 -> 0.022988506 | AF7: Asset | AG7: =COUNTIF(H:H,AF7) -> 16 | AH7: =+AG7/$AG$11 -> 0.061068702 | AK7: Bancos | AL7: =+AH8 -> 0.053435115 | AO7: Assets | AP7: =+AL6 -> 0.061068702
B8: Zamboni | C8: 45643 | D8: Advisor | E8: =+INDEX($O$3:$O$132,MATCH(D8,$N$3:$N$132,0)) -> 0 | F8: 73 | G8: =+F8/261 -> 0.27969349 | H8: Consultoria | N8: Andreia Alonso | O8: Broker D | P8: Broker | T8: Broker B | U8: =+G182 -> 0.022988506 | AF8: Banco | AG8: =COUNTIF(H:H,AF8) -> 14 | AH8: =+AG8/$AG$11 -> 0.053435115 | AK8: Boutiques | AL8: =+AH9 -> 0.022900763 | AO8: Bancos | AP8: =+AL7 -> 0.053435115
B9: Manasa e Tranesco | C9: 45593 | D9: Antonio Lacombe | E9: =+INDEX($O$3:$O$132,MATCH(D9,$N$3:$N$132,0)) -> 0 | F9: 73 | G9: =+F9/261 -> 0.27969349 | H9: Empresário/Executivo | N9: Fernando Galvão (JGP) Vinicius Senger (ARC) | O9: Asset A | P9: Asset | T9: Banco A | U9: =+G188 -> 0.022988506 | AF9: Boutique | AG9: =COUNTIF(H:H,AF9) -> 6 | AH9: =+AG9/$AG$11 -> 0.022900763 | AK9: Brokers | AL9: =+AH10 -> 0.32442748
C10: 45525 | D10: Araujo Fontes | E10: =+INDEX($O$3:$O$132,MATCH(D10,$N$3:$N$132,0)) -> 0 | F10: 73 | G10: =+F10/261 -> 0.27969349 | H10: Boutique | N10: Willian May (JGP FA) | O10: JGP FA | T10: Outros Canais | U10: =1-SUM(U4:U9) -> 0.66666667 | AF10: Broker | AG10: =COUNTIF(H:H,AF10) -> 85 | AH10: =+AG10/$AG$11 -> 0.32442748
B11: Diagnosis x Iasep | C11: 45548 | D11: BB Asset | E11: =+INDEX($O$3:$O$132,MATCH(D11,$N$3:$N$132,0)) -> 0 | F11: 73 | G11: =+F11/261 -> 0.27969349 | H11: Asset | N11: Erick e Diogo (Moelis) | O11: Boutique A | P11: Boutique | AG11: =+SUM(AG3:AG10) -> 262
B12: Light | C12: 45478 | D12: BeeCap | E12: =+INDEX($O$3:$O$132,MATCH(D12,$N$3:$N$132,0)) -> 0 | F12: 73 | G12: =+F12/261 -> 0.27969349 | H12: Asset | N12: Fernando Kunzel (JGP FA) | O12: JGP FA
B13: Arkhe Engenharia | C13: 45560 | D13: BX Capital | E13: =+INDEX($O$3:$O$132,MATCH(D13,$N$3:$N$132,0)) -> 0 | F13: 73 | G13: =+F13/261 -> 0.27969349 | H13: Broker | N13: JGP FA | O13: JGP FA | T13: Outros Canais | U13: =+U10 -> 0.66666667
B14: Novo Mundo | C14: 45541 | D14: Caique Melo / Aventos | E14: =+INDEX($O$3:$O$132,MATCH(D14,$N$3:$N$132,0)) -> 0 | F14: 73 | G14: =+F14/261 -> 0.27969349 | H14: Broker | N14: Henrique (JGP) | O14: Originação própria | T14: Banco A | U14: =+U9 -> 0.022988506
B15: Cromex | C15: 45638 | D15: Camilo (MMSO) / Taua Partners | E15: =+INDEX($O$3:$O$132,MATCH(D15,$N$3:$N$132,0)) -> 0 | F15: 73 | G15: =+F15/261 -> 0.27969349 | H15: Escritório Adv. | N15: Gregory Pagot | O15: Broker E | P15: Broker | T15: Broker B | U15: =+U8 -> 0.022988506
B16: Aquisiçao de ativos judiciais | C16: 45637 | D16: Connectas Capital | E16: =+INDEX($O$3:$O$132,MATCH(D16,$N$3:$N$132,0)) -> 0 | F16: 73 | G16: =+F16/261 -> 0.27969349 | H16: Broker | N16: QMS Capital | O16: Asset B | P16: Asset | T16: Escritoria Adv A | U16: =+U7 -> 0.022988506
B17: Tuper | C17: 45401 | D17: Credit Suisse | E17: =+INDEX($O$3:$O$132,MATCH(D17,$N$3:$N$132,0)) -> 0 | F17: 73 | G17: =+F17/261 -> 0.27969349 | H17: Banco | N17: ARC Capital | O17: Asset A | P17: Asset | T17: Consultoria A | U17: =+U6 -> 0.034482759
B18: DETRAN - GO | C18: 45643 | D18: Data Traffic | E18: =+INDEX($O$3:$O$132,MATCH(D18,$N$3:$N$132,0)) -> 0 | F18: 73 | G18: =+F18/261 -> 0.27969349 | H18: Empresário/Executivo | N18: Itau BBA | O18: Banco A | P18: Banco | T18: Broker A | U18: =+U5 -> 0.038314176
C19: 45614 | D19: Deyvid Oliveira | E19: =+INDEX($O$3:$O$132,MATCH(D19,$N$3:$N$132,0)) -> 0 | F19: 73 | G19: =+F19/261 -> 0.27969349 | H19: Broker | N19: Heartman House | O19: Consultoria A | P19: Consultoria | T19: JGP FA | U19: =+U4 -> 0.19157088
B20: Estre Ambiental | C20: 45425 | D20: Diego Ressureição | E20: =+INDEX($O$3:$O$132,MATCH(D20,$N$3:$N$132,0)) -> 0 | F20: 73 | G20: =+F20/261 -> 0.27969349 | H20: Escritório Adv. | N20: Leonardo Campos Melo | O20: Broker F | P20: Broker
B21: Precatórios do Estado do PR | C21: 45315 | D21: Emanuel Cavalcanti - Convexa Investimentos | E21: =+INDEX($O$3:$O$132,MATCH(D21,$N$3:$N$132,0)) -> Asset | F21: 73 | G21: =+F21/261 -> 0.27969349 | H21: Asset | N21: Vela Capital | O21: Asset B | P21: Asset
B22: Epropi | C22: 45440 | D22: Epropi | E22: =+INDEX($O$3:$O$132,MATCH(D22,$N$3:$N$132,0)) -> 0 | F22: 73 | G22: =+F22/261 -> 0.27969349 | H22: Empresário/Executivo | N22: Raphael Martins (Souto Correa) | O22: Escritório Adv A | P22: Escritório Adv
B23: Semeato | C23: 45520 | D23: FTI | E23: =+INDEX($O$3:$O$132,MATCH(D23,$N$3:$N$132,0)) -> 0 | F23: 73 | G23: =+F23/261 -> 0.27969349 | H23: Consultoria | N23: Vicente Barros (Amavic)
C24: 45636 | D24: FTI | E24: =+INDEX($O$3:$O$132,MATCH(D24,$N$3:$N$132,0)) -> 0 | F24: 73 | G24: =+F24/261 -> 0.27969349 | H24: Consultoria | N24: ExFin Advisory | O24: Consultoria C | P24: Consultoria
B25: Juízo Federal de Umuarama - José Teixeira | C25: 45461 | D25: Grupo SS | E25: =+INDEX($O$3:$O$132,MATCH(D25,$N$3:$N$132,0)) -> 0 | F25: 73 | G25: =+F25/261 -> 0.27969349 | H25: JGP FA | N25: João Pedro Santos (A&M) | O25: Consultoria B | P25: Consultoria
B26: Precatório do Pará | C26: 45469 | D26: Grupo SS | E26: =+INDEX($O$3:$O$132,MATCH(D26,$N$3:$N$132,0)) -> 0 | F26: 73 | G26: =+F26/261 -> 0.27969349 | H26: JGP FA | N26: Eduardo Bastos (A&M) | O26: Consultoria B | P26: Consultoria
B27: FIDC AGRO Iron Capital | C27: 45637 | D27: Iron Capital | E27: =+INDEX($O$3:$O$132,MATCH(D27,$N$3:$N$132,0)) -> 0 | F27: 73 | G27: =+F27/261 -> 0.27969349 | H27: Asset | N27: Guilherme Sertorio | O27: Broker G | P27: Broker
B28: Arbitragem da Método | C28: 45527 | D28: Ivo | E28: =+INDEX($O$3:$O$132,MATCH(D28,$N$3:$N$132,0)) -> 0 | F28: 73 | G28: =+F28/261 -> 0.27969349 | H28: Empresário/Executivo | N28: Originação Própria | O28: Originação própria
B29: Yara | C29: 45322 | D29: José Afonso (VBSO) | E29: =+INDEX($O$3:$O$132,MATCH(D29,$N$3:$N$132,0)) -> 0 | F29: 73 | G29: =+F29/261 -> 0.27969349 | H29: Escritório Adv. | N29: Paulo Viola | O29: Broker C | P29: Broker
B30: Precatório RS | C30: 45457 | D30: Jose Ribeiro (BLS) | E30: =+INDEX($O$3:$O$132,MATCH(D30,$N$3:$N$132,0)) -> 0 | F30: 73 | G30: =+F30/261 -> 0.27969349 | H30: Escritório Adv. | N30: Souto Correa | O30: Escritório Adv B | P30: Escritório Adv
C31: 45639 | D31: K3 Investimentos | E31: =+INDEX($O$3:$O$132,MATCH(D31,$N$3:$N$132,0)) -> 0 | F31: 73 | G31: =+F31/261 -> 0.27969349 | H31: Broker | N31: Santander | O31: Banco B | P31: Banco
B32: Precatorios Municipais OEC | C32: 45546 | D32: Lucas Cive | E32: =+INDEX($O$3:$O$132,MATCH(D32,$N$3:$N$132,0)) -> 0 | F32: 73 | G32: =+F32/261 -> 0.27969349 | H32: Broker | N32: DJA Invest | O32: Consultoria D | P32: Consultoria
B33: Construtora x União | C33: 45622 | D33: Luciano Monetaire | E33: =+INDEX($O$3:$O$132,MATCH(D33,$N$3:$N$132,0)) -> 0 | F33: 73 | G33: =+F33/261 -> 0.27969349 | H33: Broker | N33: JGP FA - Rafael Dale | O33: JGP FA
B34: Precatorio Desapropriação | C34: 45523 | D34: Luesley | E34: =+INDEX($O$3:$O$132,MATCH(D34,$N$3:$N$132,0)) -> 0 | F34: 73 | G34: =+F34/261 -> 0.27969349 | H34: Broker | N34: Broker | O34: Broker B | P34: Broker
B35: Pré Precatório Federal - Hospital Psiquiátricos | C35: 45572 | D35: M Invest | E35: =+INDEX($O$3:$O$132,MATCH(D35,$N$3:$N$132,0)) -> 0 | F35: 73 | G35: =+F35/261 -> 0.27969349 | H35: Broker | N35: WhatsApp | O35: Originação própria
B36: Precatorio TUNEP | C36: 45572 | D36: M Invest | E36: =+INDEX($O$3:$O$132,MATCH(D36,$N$3:$N$132,0)) -> 0 | F36: 73 | G36: =+F36/261 -> 0.27969349 | H36: Broker | N36: Pedro Cavalcanti Rafael Solon | O36: Originação própria
B37: José Bonifácio | C37: 45636 | D37: Makalu | E37: =+INDEX($O$3:$O$132,MATCH(D37,$N$3:$N$132,0)) -> 0 | F37: 73 | G37: =+F37/261 -> 0.27969349 | H37: Asset | N37: Thomas | O37: Escritório Adv C | P37: Escritório Adv
B38: Brandili | C38: 45401 | D38: Manchester Investimentos | E38: =+INDEX($O$3:$O$132,MATCH(D38,$N$3:$N$132,0)) -> 0 | F38: 73 | G38: =+F38/261 -> 0.27969349 | H38: Broker | N38: Quadra | O38: Asset C | P38: Asset
C39: 45503 | D39: Marcelo Bortman (Konscio) | E39: =+INDEX($O$3:$O$132,MATCH(D39,$N$3:$N$132,0)) -> 0 | F39: 73 | G39: =+F39/261 -> 0.27969349 | H39: Escritório Adv. | N39: Advogado | O39: Escritório Adv D | P39: Escritório Adv
B40: Lupatech | C40: 45530 | D40: Marcus (CFO) | E40: =+INDEX($O$3:$O$132,MATCH(D40,$N$3:$N$132,0)) -> 0 | F40: 73 | G40: =+F40/261 -> 0.27969349 | H40: Empresário/Executivo | N40: BlueOak | O40: Asset D | P40: Asset
B41: Techna x Petrobras | C41: 45453 | D41: Marta | E41: =+INDEX($O$3:$O$132,MATCH(D41,$N$3:$N$132,0)) -> 0 | F41: 73 | G41: =+F41/261 -> 0.27969349 | H41: Empresário/Executivo | N41: Francisco Carneiro | O41: Broker Y | P41: Broker
B42: Evolve | C42: 45597 | D42: Meros Capital | E42: =+INDEX($O$3:$O$132,MATCH(D42,$N$3:$N$132,0)) -> 0 | F42: 73 | G42: =+F42/261 -> 0.27969349 | H42: Asset | N42: JGP FA/w1 | O42: JGP FA
B43: Método | C43: 45567 | D43: Método | E43: =+INDEX($O$3:$O$132,MATCH(D43,$N$3:$N$132,0)) -> 0 | F43: 73 | G43: =+F43/261 -> 0.27969349 | H43: Empresário/Executivo | N43: Thiago | O43: Broker H | P43: Broker
B44: Pre precatorio | C44: 45520 | D44: Moix | E44: =+INDEX($O$3:$O$132,MATCH(D44,$N$3:$N$132,0)) -> 0 | F44: 73 | G44: =+F44/261 -> 0.27969349 | H44: Broker | N44: Dauricio Advogados | O44: Escritório Adv E | P44: Escritório Adv
B45: MPE e Coimex | C45: 45643 | D45: MPE | E45: =+INDEX($O$3:$O$132,MATCH(D45,$N$3:$N$132,0)) -> 0 | F45: 73 | G45: =+F45/261 -> 0.27969349 | H45: Empresário/Executivo | N45: Vega Asset | O45: Asset E | P45: Asset
B46: Gramado Parks | C46: 45446 | D46: Nikos Investimento | E46: =+INDEX($O$3:$O$132,MATCH(D46,$N$3:$N$132,0)) -> 0 | F46: 73 | G46: =+F46/261 -> 0.27969349 | H46: Broker | N46: Advisor
B47: FIDC de precatório e consignado público | C47: 45594 | D47: Octante Capital | E47: =+INDEX($O$3:$O$132,MATCH(D47,$N$3:$N$132,0)) -> 0 | F47: 73 | G47: =+F47/261 -> 0.27969349 | H47: Asset | N47: José Afonso (VBSO)
B48: Precatorio da Paraiba | C48: 45520 | D48: Octo Capital | E48: =+INDEX($O$3:$O$132,MATCH(D48,$N$3:$N$132,0)) -> 0 | F48: 73 | G48: =+F48/261 -> 0.27969349 | H48: Broker | N48: Thales Neves (Zeal Soluçoes)
B49: Recebíveis | C49: 45527 | D49: Olimpia Partners | E49: =+INDEX($O$3:$O$132,MATCH(D49,$N$3:$N$132,0)) -> 0 | F49: 73 | G49: =+F49/261 -> 0.27969349 | H49: Broker | N49: Bruno Ribeiro | O49: Broker K | P49: Broker
B50: Zeus x CNI | C50: 45460 | D50: Padre Viol | E50: =+INDEX($O$3:$O$132,MATCH(D50,$N$3:$N$132,0)) -> 0 | F50: 73 | G50: =+F50/261 -> 0.27969349 | H50: Broker | N50: Banco | O50: Banco C | P50: Banco
C51: 45524 | D51: Papini | E51: =+INDEX($O$3:$O$132,MATCH(D51,$N$3:$N$132,0)) -> 0 | F51: 73 | G51: =+F51/261 -> 0.27969349 | H51: Escritório Adv. | N51: Banco do Brasil | O51: Banco D | P51: Banco
B52: Farmacia Independente | C52: 45643 | D52: Patria | E52: =+INDEX($O$3:$O$132,MATCH(D52,$N$3:$N$132,0)) -> 0 | F52: 73 | G52: =+F52/261 -> 0.27969349 | H52: Asset | N52: Credit Suisse
B53: UTC e Eletrobras | C53: 45460 | D53: Pereira Advogados | E53: =+INDEX($O$3:$O$132,MATCH(D53,$N$3:$N$132,0)) -> 0 | F53: 73 | G53: =+F53/261 -> 0.27969349 | H53: Escritório Adv. | N53: Manchester Investimentos
C54: 45401 | D54: Placido Castelo | E54: =+INDEX($O$3:$O$132,MATCH(D54,$N$3:$N$132,0)) -> 0 | F54: 73 | G54: =+F54/261 -> 0.27969349 | H54: Escritório Adv. | N54: Placido Castelo
B55: Legal Claims - PWC | C55: 45560 | D55: PWC | E55: =+INDEX($O$3:$O$132,MATCH(D55,$N$3:$N$132,0)) -> 0 | F55: 73 | G55: =+F55/261 -> 0.27969349 | H55: Consultoria | N55: João Felipe Jucá | O55: Broker I | P55: Broker
B56: Trimonte | C56: 45541 | D56: Rafael Papini | E56: =+INDEX($O$3:$O$132,MATCH(D56,$N$3:$N$132,0)) -> 0 | F56: 73 | G56: =+F56/261 -> 0.27969349 | H56: Escritório Adv. | N56: Alvarez & Marsal | O56: Consultoria B | P56: Consultoria
B57: Data Traffic | D57: Rafael Papini | E57: =+INDEX($O$3:$O$132,MATCH(D57,$N$3:$N$132,0)) -> 0 | F57: 73 | G57: =+F57/261 -> 0.27969349 | H57: Escritório Adv. | N57: Diego Ressureição
D58: Rafael Solon | E58: =+INDEX($O$3:$O$132,MATCH(D58,$N$3:$N$132,0)) -> 0 | F58: 73 | G58: =+F58/261 -> 0.27969349 | H58: Escritório Adv. | N58: Luiz Evangelista | O58: Broker J | P58: Broker
B59: Mendesprev | C59: 45624 | D59: Ramos de Luca | E59: =+INDEX($O$3:$O$132,MATCH(D59,$N$3:$N$132,0)) -> 0 | F59: 73 | G59: =+F59/261 -> 0.27969349 | H59: Escritório Adv. | N59: Rodrigo Klamt
B60: Juventude e Agenco Eng. | C60: 45541 | D60: Rio Capital | E60: =+INDEX($O$3:$O$132,MATCH(D60,$N$3:$N$132,0)) -> 0 | F60: 73 | G60: =+F60/261 -> 0.27969349 | H60: Asset | N60: Galdino | O60: Escritório Adv F | P60: Escritório Adv
B61: Ação indenizatoria | C61: 45583 | D61: Roberto Rusu | E61: =+INDEX($O$3:$O$132,MATCH(D61,$N$3:$N$132,0)) -> 0 | F61: 73 | G61: =+F61/261 -> 0.27969349 | H61: Broker | N61: Carlos Libera | O61: Consultoria | P61: Consultoria
B62: CESP - Cerâmica Guerra | C62: 45436 | D62: Rodrigo Klamt | E62: =+INDEX($O$3:$O$132,MATCH(D62,$N$3:$N$132,0)) -> 0 | F62: 73 | G62: =+F62/261 -> 0.27969349 | H62: Broker | N62: Nikos Investimento
B63: Fabricante de artigo médicos - Lemgruber | C63: 45461 | D63: Rodrigo Klamt | E63: =+INDEX($O$3:$O$132,MATCH(D63,$N$3:$N$132,0)) -> 0 | F63: 73 | G63: =+F63/261 -> 0.27969349 | H63: Broker | N63: Epropi
B64: Zaeli | C64: 45503 | D64: Rodrigo Klamt | E64: =+INDEX($O$3:$O$132,MATCH(D64,$N$3:$N$132,0)) -> 0 | F64: 73 | G64: =+F64/261 -> 0.27969349 | H64: Broker | N64: Leandro Vasconcellos | O64: Broker L | P64: Broker
B65: OI | C65: 45621 | D65: RPC | E65: =+INDEX($O$3:$O$132,MATCH(D65,$N$3:$N$132,0)) -> 0 | F65: 73 | G65: =+F65/261 -> 0.27969349 | H65: Empresário/Executivo | N65: Grupo de SS | O65: Originação própria
B66: Luciano | C66: 45534 | D66: Site de RI | E66: =+INDEX($O$3:$O$132,MATCH(D66,$N$3:$N$132,0)) -> 0 | F66: 73 | G66: =+F66/261 -> 0.27969349 | H66: Broker | N66: Marta
D67: SITE RI | E67: =+INDEX($O$3:$O$132,MATCH(D67,$N$3:$N$132,0)) -> 0 | F67: 73 | G67: =+F67/261 -> 0.27969349 | H67: Broker | N67: Jose Ribeiro (BLS)
B68: Instituição de Ensino | C68: 45541 | D68: Special Sits Hub/Fernando Piton | E68: =+INDEX($O$3:$O$132,MATCH(D68,$N$3:$N$132,0)) -> 0 | F68: 73 | G68: =+F68/261 -> 0.27969349 | H68: Consultoria | N68: Padre Viol
B69: Superbac | C69: 45597 | D69: Taua Partners | E69: =+INDEX($O$3:$O$132,MATCH(D69,$N$3:$N$132,0)) -> 0 | F69: 73 | G69: =+F69/261 -> 0.27969349 | H69: Consultoria | N69: Pereira Advogados
B70: Ricardo Jacomassi | C70: 45503 | D70: TCP Partners | E70: =+INDEX($O$3:$O$132,MATCH(D70,$N$3:$N$132,0)) -> 0 | F70: 73 | G70: =+F70/261 -> 0.27969349 | H70: Consultoria | N70: Email do Spiller | O70: Originação própria
B71: ICMS | C71: 45541 | D71: TCP Partners | E71: =+INDEX($O$3:$O$132,MATCH(D71,$N$3:$N$132,0)) -> 0 | F71: 73 | G71: =+F71/261 -> 0.27969349 | H71: Consultoria | N71: Grupo SS
B72: DFG Agro | C72: 45386 | D72: Thales Neves (Zeal Soluçoes) | E72: =+INDEX($O$3:$O$132,MATCH(D72,$N$3:$N$132,0)) -> 0 | F72: 73 | G72: =+F72/261 -> 0.27969349 | H72: Consultoria | N72: Banco Pine | O72: Banco E | P72: Banco
B73: Keiper | C73: 45553 | D73: Tosto Adv | E73: =+INDEX($O$3:$O$132,MATCH(D73,$N$3:$N$132,0)) -> 0 | F73: 73 | G73: =+F73/261 -> 0.27969349 | H73: Escritório Adv. | N73: W Capital
B74: Labortex | C74: 45583 | D74: Tosto Adv | E74: =+INDEX($O$3:$O$132,MATCH(D74,$N$3:$N$132,0)) -> 0 | F74: 73 | G74: =+F74/261 -> 0.27969349 | H74: Escritório Adv. | N74: BeeCap
B75: Data Traffic e DNIT | C75: 45337 | D75: Vicente Barros (Amavic) | E75: =+INDEX($O$3:$O$132,MATCH(D75,$N$3:$N$132,0)) -> 0 | F75: 73 | G75: =+F75/261 -> 0.27969349 | H75: Broker | N75: Luesley
B76: Leve Saude | C76: 45474 | D76: W Capital | E76: =+INDEX($O$3:$O$132,MATCH(D76,$N$3:$N$132,0)) -> 0 | F76: 73 | G76: =+F76/261 -> 0.27969349 | H76: JGP FA | N76: TCP Partners
B77: Grupo SMH | C77: - | D77: Fernando Kunzel (JGP FA) | E77: =+INDEX($O$3:$O$132,MATCH(D77,$N$3:$N$132,0)) -> JGP FA | F77: 50 | G77: =+F77/261 -> 0.19157088 | H77: JGP FA | N77: Julio Santos | O77: Broker M | P77: Broker
B78: Inplac | C78: - | D78: JGP FA | E78: =+INDEX($O$3:$O$132,MATCH(D78,$N$3:$N$132,0)) -> JGP FA | F78: 50 | G78: =+F78/261 -> 0.19157088 | H78: JGP FA | N78: Marcelo Bortman (Konscio)
B79: Dock Brasil | C79: 45366 | D79: JGP FA | E79: =+INDEX($O$3:$O$132,MATCH(D79,$N$3:$N$132,0)) -> JGP FA | F79: 50 | G79: =+F79/261 -> 0.19157088 | H79: JGP FA | N79: Renato Gorni - RMR Corporate | O79: Broker U | P79: Broker
B80: Armco | D80: JGP FA | E80: =+INDEX($O$3:$O$132,MATCH(D80,$N$3:$N$132,0)) -> JGP FA | F80: 50 | G80: =+F80/261 -> 0.19157088 | H80: JGP FA | N80: João Gabriel Rosa | O80: Broker N | P80: Broker
B81: Hotel Trump | D81: JGP FA | E81: =+INDEX($O$3:$O$132,MATCH(D81,$N$3:$N$132,0)) -> JGP FA | F81: 50 | G81: =+F81/261 -> 0.19157088 | H81: JGP FA | N81: FTI
B82: OBDI | C82: 45337 | D82: JGP FA | E82: =+INDEX($O$3:$O$132,MATCH(D82,$N$3:$N$132,0)) -> JGP FA | F82: 50 | G82: =+F82/261 -> 0.19157088 | H82: JGP FA | N82: Octo Capital
B83: Armazem do Grão | C83: 45342 | D83: JGP FA | E83: =+INDEX($O$3:$O$132,MATCH(D83,$N$3:$N$132,0)) -> JGP FA | F83: 50 | G83: =+F83/261 -> 0.19157088 | H83: JGP FA | N83: Moix
B84: Vitalmar | C84: 45366 | D84: JGP FA | E84: =+INDEX($O$3:$O$132,MATCH(D84,$N$3:$N$132,0)) -> JGP FA | F84: 50 | G84: =+F84/261 -> 0.19157088 | H84: JGP FA | N84: Orama IB | O84: Banco F | P84: Banco
B85: Jailton - Quero meus direitos | C85: 45366 | D85: JGP FA | E85: =+INDEX($O$3:$O$132,MATCH(D85,$N$3:$N$132,0)) -> JGP FA | F85: 50 | G85: =+F85/261 -> 0.19157088 | H85: JGP FA | N85: Araujo Fontes
B86: Usina Ester | C86: 45366 | D86: JGP FA | E86: =+INDEX($O$3:$O$132,MATCH(D86,$N$3:$N$132,0)) -> JGP FA | F86: 50 | G86: =+F86/261 -> 0.19157088 | H86: JGP FA | N86: Olimpia Partners
B87: Usina Aysu | C87: 45366 | D87: JGP FA | E87: =+INDEX($O$3:$O$132,MATCH(D87,$N$3:$N$132,0)) -> JGP FA | F87: 50 | G87: =+F87/261 -> 0.19157088 | H87: JGP FA | N87: Alexandre Muller | O87: Originação própria | P87: Originação própria
B88: Eletrobras | C88: 45366 | D88: JGP FA | E88: =+INDEX($O$3:$O$132,MATCH(D88,$N$3:$N$132,0)) -> JGP FA | F88: 50 | G88: =+F88/261 -> 0.19157088 | H88: JGP FA | N88: Papini
B89: Família Popescu | C89: 45377 | D89: JGP FA | E89: =+INDEX($O$3:$O$132,MATCH(D89,$N$3:$N$132,0)) -> JGP FA | F89: 50 | G89: =+F89/261 -> 0.19157088 | H89: JGP FA | N89: Acacio | O89: Broker P | P89: Broker
B90: Hidronorte | C90: 45377 | D90: JGP FA | E90: =+INDEX($O$3:$O$132,MATCH(D90,$N$3:$N$132,0)) -> JGP FA | F90: 50 | G90: =+F90/261 -> 0.19157088 | H90: JGP FA | N90: Ivo
B91: Cia Açucareira Vale do Ceará Mirim | C91: 45379 | D91: JGP FA | E91: =+INDEX($O$3:$O$132,MATCH(D91,$N$3:$N$132,0)) -> JGP FA | F91: 50 | G91: =+F91/261 -> 0.19157088 | H91: JGP FA | N91: Marcus (CFO)
B92: Rio Turia (Bunge) | D92: JGP FA | E92: =+INDEX($O$3:$O$132,MATCH(D92,$N$3:$N$132,0)) -> JGP FA | F92: 50 | G92: =+F92/261 -> 0.19157088 | H92: JGP FA | N92: Site de RI
B93: Usina Capricho | C93: 45390 | D93: JGP FA | E93: =+INDEX($O$3:$O$132,MATCH(D93,$N$3:$N$132,0)) -> JGP FA | F93: 50 | G93: =+F93/261 -> 0.19157088 | H93: JGP FA | N93: Antonio Penido
B94: Precatorio Estadual da Bahia | C94: 45401 | D94: JGP FA | E94: =+INDEX($O$3:$O$132,MATCH(D94,$N$3:$N$132,0)) -> JGP FA | F94: 50 | G94: =+F94/261 -> 0.19157088 | H94: JGP FA | N94: Rafael Papini
B95: Camargo Correa | C95: 45436 | D95: JGP FA | E95: =+INDEX($O$3:$O$132,MATCH(D95,$N$3:$N$132,0)) -> JGP FA | F95: 50 | G95: =+F95/261 -> 0.19157088 | H95: JGP FA | N95: Special Sits Hub/Fernando Piton
B96: Terra Fértil | C96: 45441 | D96: JGP FA | E96: =+INDEX($O$3:$O$132,MATCH(D96,$N$3:$N$132,0)) -> JGP FA | F96: 50 | G96: =+F96/261 -> 0.19157088 | H96: JGP FA | N96: Rio Capital
B97: Sergio Luiz | C97: 45449 | D97: JGP FA | E97: =+INDEX($O$3:$O$132,MATCH(D97,$N$3:$N$132,0)) -> JGP FA | F97: 50 | G97: =+F97/261 -> 0.19157088 | H97: JGP FA | N97: Caique Melo / Aventos
B98: Minter | C98: 45464 | D98: JGP FA | E98: =+INDEX($O$3:$O$132,MATCH(D98,$N$3:$N$132,0)) -> JGP FA | F98: 50 | G98: =+F98/261 -> 0.19157088 | H98: JGP FA | N98: Lucas Cive
B99: ATMA (Contax) | C99: 45468 | D99: JGP FA | E99: =+INDEX($O$3:$O$132,MATCH(D99,$N$3:$N$132,0)) -> JGP FA | F99: 50 | G99: =+F99/261 -> 0.19157088 | H99: JGP FA | N99: BB Asset
B100: Claudio Vinicius | D100: JGP FA | E100: =+INDEX($O$3:$O$132,MATCH(D100,$N$3:$N$132,0)) -> JGP FA | F100: 50 | G100: =+F100/261 -> 0.19157088 | H100: JGP FA | N100: BX Capital
...

Sheet Output
B2: # | C2: Tipo de Operação | D2: Nome | E2: Data | F2: Originador | G2: Status da Operação | H2: Responsável
B3: 1 | C3: Legal Claims | D3: BRCON | E3: 45530 | F3: Broker | G3: 17/02 - Acreditamos em uma piora do risco de crédito e piora do processo 28/02 - Analisar o impacto da piora do processo no prazo de recebimento e reprecificar | H3: Todos
B4: =+B3+1 -> 2 | C4: Litigation Finance | D4: Método | E4: 45567 | F4: Empresário / Executivo | G4: 28/02 - Discussão da proposta com a Companhia | H4: Luiza
B5: =+B4+1 -> 3 | C5: Crédito | D5: Evolve | E5: 45597 | F5: Meros Capital | G5: 26/02 - Recebemos a proposta deles pela 2x 28/02 - Reunião presencial no dia 10/03 para definir os termos ou não seguir com a transação | H5: Todos
B6: =+B5+1 -> 4 | C6: Credito | D6: Polo Wear | E6: 45597 | F6: JGP FA | G6: 17/02 - Acharam o kicker e a multa de pre pagamento altas 24/02 - Respondemos as preocupaçoes dele, aguardamos uma devolutiva | H6: Todos
B7: =+B6+1 -> 5 | C7: DIP | D7: Cocelpa | E7: 45614 | F7: JGP FA | G7: 06/01 - Pendente do recebimento de informações solicitadas em Dez/24 | H7: Christopher/Antonio
B8: =+B7+1 -> 6 | C8: Precatorio Estadual | D8: Quartier Ipanema | E8: 45636 | F8: JGP FA | G8: 03/02 - Março vai ter reuniao de reeleiçao de sindico, estao aguardando isso para venda do crédito 28/02 - Vamos cobrar uma resposta ao final de março | H8: Todos
B9: =+B8+1 -> 7 | C9: Legal Claims | D9: DETRAN - GO | E9: 45643 | F9: Empresário / Executivo | G9: 24/02 - Castro nos voltou falando que estão pegando cópia dos autos. Vamos aguardar | H9: Hugo
B10: =+B9+1 -> 8 | C10: Crédito RJ | D10: Portal Agro | E10: 45663 | F10: (X2W) Consultoria | G10: 28/02 - Ainda não possuem um levantamento completo da dívida da RJ. Vamos aguardar | H10: Christopher/Antonio
B11: =+B10+1 -> 9 | C11: Crédito Estruturado | D11: Bravante | E11: 45674 | F11: Alvarez& Marsal | G11: 28/02 - Recebemos informações no dia 24/02. Em análise | H11: Christopher/Antonio
B12: =+B11+1 -> 10 | C12: Crédito Estruturado | D12: Itagres | E12: 45680 | F12: Stark Investimentos (Consultoria) | G12: 28/02 - Em análise | H12: Christopher
B13: =+B12+1 -> 11 | C13: Crédito Trabalhista | D13: Galileu e Assespa | E13: 45684 | F13: Alvarez& Marsal | G13: 26/02 - Fizemos o FUP na A&M. Aguardando resposta | H13: Antonio
B14: =+B13+1 -> 12 | C14: DIP | D14: Grupo Lagos de Itaipava | E14: 45687 | F14: Broker | G14: 24/02- Analisamos melhor a oportunidade e entendemos que ainda esta em estágio inicial, não possuem todas as informações que comporiam o QGC 27/02 - Vamos falar com o CFO para entender melhor a RJ (10/02) | H14: Christopher
B15: =+B14+1 -> 13 | C15: Legal Claims | D15: MRV | E15: 45686 | F15: Broker | G15: 27/02 - Enviamos uma proposta não vinculante. Aguardando resposta | H15: Todos
... B35: =+B34+1 -> 33 | C35: Precatório Municipal | D35: Valença | E35: 45715 | F35: JGP FA | G35: 28/02 - Em análise | H35: Hugo
B37: # | C37: Tipo de Operação | D37: Nome | E37: Data | F37: Originador | G37: Status da Operação | H37: Responsável | L37: Detalhamento
C38: Crédito Estruturado e DIP
B39: 1 | C39: Crédito Estruturado | D39: Evolve | E39: 45597 | F39: Meros Capital | G39: 26/02 - Recebemos a proposta deles pela 2x 28/02 - Reunião presencial no dia 10/03 para definir os termos ou não seguir com a transação | H39: Todos | J39: . | L39: Academia quer levantar 50mm, estamos propondo dívida na holding e um fidc na empresa
B40: =+B39+1 -> 2 | C40: Crédito Estruturado | D40: Polo Wear | E40: 45597 | F40: JGP FA | G40: 17/02 - Acharam o kicker e a multa de pre pagamento altas 24/02 - Respondemos as preocupaçoes dele, aguardamos uma devolutiva | H40: Todos | J40: . | L40: 70mm para empresa liberar os imoveis que estao em garantia e tb kgiro
B41: =+B40+1 -> 3 | C41: DIP | D41: Cocelpa | E41: 45614 | F41: JGP FA | G41: 06/01 - Pendente do recebimento de informações solicitadas em Dez/24 | H41: Christopher/Antonio | L41: Produção de papel e embalagem. A Cocelpa hoje está em recuperação judicial e os sócios (estão brigados e não se falam) estão com patrimonio bloqueado. Eles possuem hoje um acordo para pagar a vista a divida fiscal e gostariam de fazer uma divida na empresa com garantias no imóvel que fica em Araucaria-PR
B42: =+B41+1 -> 4 | C42: DIP | D42: Portal Agro | E42: 45663 | F42: (X2W) Consultoria | G42: 28/02 - Ainda não possuem um levantamento completo da dívida da RJ. Vamos aguardar | H42: Christopher/Antonio | L42: Companhia Agro em RJ, expectativa de captaçao de um DIP de 50mm para comprar insumos. Possuem ativos operacionais para venda e pagamento do empréstimo. Alem disso há ativos, na RJ, livres para garantia
B43: =+B42+1 -> 5 | C43: Crédito Estruturado | D43: Bravante | E43: 45674 | F43: Alvarez& Marsal | G43: 28/02 - Recebemos informações no dia 24/02. Em análise | H43: Christopher/Antonio | L43: CDI+10% - topam segregar patrimonio, entender se uma RJ pode atrapalhar isso. Financiar a compra de 2 barcaças, com pat segregado, como garantia tem AF das barcaças, os contratos
B44: =+B43+1 -> 6 | C44: Crédito Estruturado | D44: Itagres | E44: 45680 | F44: Stark Investimentos (Consultoria) | G44: 28/02 - Em análise | H44: Christopher | L44: Porcelana em SC, 8 anos Rj, não operacional, 40mm em imoveis n operacionais, fazenda em jaguaruna 40mm, VGV de 500mm mas faseado em mtos anos.Tem duas UPIs operacionais, tubarao vale 53mm bali pagar 30mm, UoP da venda para pagar classe I e II que da 27mm. Tem fabrica em mossoró, Oriz Partners quer levar no artigo 166, 70mm pra construir. Passivo 40mm concursal 40mm extra e 90mm, ja sindicalizou os extra . 20mm de imovel para pagar a extra.
B45: =+B44+1 -> 7 | C45: DIP | D45: Grupo Lagos de Itaipava | E45: 45687 | F45: Broker | G45: 24/02- Analisamos melhor a oportunidade e entendemos que ainda esta em estágio inicial, não possuem todas as informações que comporiam o QGC 27/02 - Vamos falar com o CFO para entender melhor a RJ (10/02) | H45: Christopher | L45: 30mm, em RJ, castelo de itaipava
B46: =+B45+1 -> 8 | C46: Crédito Estruturado | D46: Aluguel de Freezer da Metalfrio | E46: 45686 | F46: Oriz | G46: 20/02 - Enviaram VDR, vamos analisar mas com disclaimer que os socios são complicados | H46: Christopher/Antonio
B47: =+B46+1 -> 9 | C47: Crédito Estruturado | D47: Odebrecht | E47: 45693 | F47: Advogado | G47: 28/02 - Vamos cobrar após receber sencinet (outra op. enviado pelo Padis Mattar) | H47: Luiza | L47: Graal quer comprar um acionista minoritario e quer como garantia esse crédito contra a ODB
B48: =+B47+1 -> 10 | C48: Crédito Estruturado | D48: Seara Agro | E48: 45701 | F48: JGP FA | G48: 20/02 - Sócio complicado 28/02 - Voltar com feedback dps do carnaval | H48: Antonio | L48: Divida extraconcursal de 300mm, algum parceiro para comprar essa dívida.
B49: =+B48+1 -> 11 | C49: Crédito Estruturado | D49: Sencinet | E49: 45705 | F49: Advogado | G49: 28/02 - NDA assinado, pendente de recebimento das informações | H49: Christopher/Antonio | L49: Empresa especializada em soluções de conectividade e segurança digital
B50: =+B49+1 -> 12 | C50: Crédito Estruturado | D50: Engevix | E50: 45709 | F50: Empresário / Executivo | G50: 28/02 - vamos falar com o adv de floripa para entender melhor as ações | H50: Luiza/Hugo | L50: Estão com USD 20M com Prisma (Lucas Canhoto), querem resolver os 20m ou pelo menos 10M. Garantia : Cotas de FIDC que tem claim contra Petrobras 320 M (sentença deve sair em uma semana), R$ 80 contra eletrobrás. Tem um novo contrato para 4 navios no estaleiro que podem tentar ceder um pouco para pagar tb
B51: =+B50+1 -> 13 | C51: Crédito Estruturado | D51: Benge x Plenitude Bank | E51: 45712 | F51: Advogado | G51: 28/02 - Faremos reunião com Castro Barros para entender das oportunidades | H51: Todos
B52: =+B51+1 -> 14 | C52: DIP | D52: Benge | E52: 45712 | F52: Advogado | G52: 28/02 - Faremos reunião com Castro Barros para entender das oportunidades | H52: Todos
B53: =+B52+1 -> 15 | C53: DIP | D53: Projeto Brodeaux (St. Marche) | E53: 45713 | F53: FTI | G53: 28/02 - Vamos pedir mais informações | H53: Christopher/Antonio
B54: =+B53+1 -> 16 | C54: Crédito Estruturado | D54: Allievo | E54: 45713 | F54: Acionista | G54: 25/02 - Enviaram as informações sobre a estrutura societária. Entender a possibilidade de adicionar garantias, açoes de outras investidas | H54: Christopher | J54: .
B55: =+B54+1 -> 17 | C55: Crédito Trabalhista | D55: Galileu e Assespa | E55: 45684 | F55: Alvarez& Marsal | G55: 26/02 - Fizemos o FUP na A&M. Aguardando resposta | H55: Antonio
C56: Legal Claims
B57: =+B55+1 -> 18 | C57: Legal Claims | D57: BRCON | E57: 45530 | F57: Broker | G57: 17/02 - Acreditamos em uma piora do risco de crédito e piora do processo 28/02 - Analisar o impacto da piora do processo no prazo de recebimento e reprecificar | H57: Todos
B58: =+B57+1 -> 19 | C58: Legal Claims | D58: DETRAN - GO | E58: 45643 | F58: Empresário / Executivo | G58: 24/02 - Castro nos voltou falando que estão pegando cópia dos autos. Vamos aguardar | H58: Hugo
B59: =+B58+1 -> 20 | C59: Legal Claims | D59: Construtora Moraes Sampaio | E59: 45685 | F59: Rio Investimentos | G59: 20/02 - Aguardando informações adicionais solicitadas | H59: Luiza
B60: =+B59+1 -> 21 | C60: Legal Claims | D60: Eletrogoes | E60: 45693 | F60: Franklin Templaton | G60: 27/02 - Mandamos proposta não vinculante. | H60: Hugo/Luiza
B61: =+B60+1 -> 22 | C61: Legal Claims | D61: Empresa no Amapá x Empresa Canadense | E61: 45700 | F61: Broker | G61: 27/02 - Solicitamos numero do contrato e honorários contratuais | H61: Hugo
B62: =+B61+1 -> 23 | C62: Legal Claims | D62: Projeto Armando Conde | E62: 45706 | F62: Advogado | G62: 28/02 - Em análise | H62: Hugo
B63: =+B62+1 -> 24 | C63: Legal Claims | D63: GE e VOITH x Furnas | E63: 45715 | F63: Originação Própria | G63: 28/02 - Enviamos uma proposta não vinculante | H63: Luiza
B64: =+B63+1 -> 25 | C64: Legal Claims | D64: MRV | E64: 45686 | F64: Broker | G64: 27/02 - Enviamos uma proposta não vinculante. Aguardando resposta | H64: Todos
B65: =+B64+1 -> 26 | C65: Litigation Finance | D65: Método | E65: 45567 | F65: Empresário / Executivo | G65: 28/02 - Discussão da proposta com a Companhia | H65: Luiza
B66: =+B65+1 -> 27 | C66: Litigation Finance | D66: Voepass x Latam | E66: 45688 | F66: Advogado | G66: 24/02 - vao enviar o custo de lessor e falaram que so vao fazer o litigation junto com o credito estruturado | H66: Luiza/Antonio | J66: .
B67: =+B66+1 -> 28 | C67: Litigation Finance | D67: Benge x Petrobras | E67: 45712 | F67: Advogado | G67: 28/02 - Faremos reunião com Castro Barros para entender das oportunidades | H67: Todos
B68: =+B67+1 -> 29 | C68: NPL | D68: Sylvamo x Multiformas | E68: 45715 | F68: Advogado | G68: 28/02 - Aguardando informações | H68: Todos
B69: =+B68+1 -> 30 | C69: Precatorio Estadual | D69: Quartier Ipanema | E69: 45636 | F69: JGP FA | G69: 03/02 - Março vai ter reuniao de reeleiçao de sindico, estao aguardando isso para venda do crédito 28/02 - Vamos cobrar uma resposta ao final de março | H69: Todos | J69: .
B70: =+B69+1 -> 31 | C70: Precatório Estadual | D70: Sealion | E70: 45685 | F70: Broker | G70: 14/02 - Enviamos proposta 28/02 - FUP dps do Carnaval | H70: Luiza | J70: .
B71: =+B70+1 -> 32 | C71: Pré precatório | D71: Estre Ambiental | E71: 45705 | F71: Advogado | G71: 28/02 - Em análise | H71: Hugo
B72: =+B71+1 -> 33 | C72: Precatório Municipal | D72: Valença | E72: 45715 | F72: JGP FA | G72: 28/02 - Em análise | H72: Hugo

Sheet Reuniao Vertical_old
I1: Casos ativos nos ultimos 60 dias | M1: =+MAX(M3:M35) -> 45775
H2: # | I2: Ativos Financeiros | J2: Operação | K2: Setor | L2: Status
C3: Polígono Venture Debt | D3: NPL | H3: 1 | I3: Grupo Monte Alegre | J3: DIP | K3: Agro | L3: Discussão de Proposta | M3: =+INDEX(Pipe!F:F,MATCH('Reuniao Vertical_old'!I3,Pipe!E:E,0)) -> 45734
C4: Precatório Varca Scatena | D4: Precatório Municipal | H4: =+H3+1 -> 2 | I4: Agrogalaxy | J4: Compra UPI | K4: Agro | L4: Alteração Regulamento do Fundo | M4: =+INDEX(Pipe!F:F,MATCH('Reuniao Vertical_old'!I4,Pipe!E:E,0)) -> 45751
C5: Precatório Paraná - Balduíno João Bellé | D5: Precatório Estadual | H5: =+H4+1 -> 3 | I5: Grupo Andrade | J5: NPL + DIP | K5: Usina de Cana-de-açucar | L5: Aguardando Retorno da NBO | M5: =+INDEX(Pipe!F:F,MATCH('Reuniao Vertical_old'!I5,Pipe!E:E,0)) -> 45754 | O5: > nao conseguimos fazer as reunioes que queriamos, nao conseguimos fazer proposta e outra pessoa levou
C6: Precatório Rio Grande do Sul | D6: Precatório Estadual | H6: =+H5+1 -> 4 | I6: Grupo Fayad | J6: NPL | K6: Pecuária | L6: Aguardando Retorno do BB | M6: =+INDEX(Pipe!F:F,MATCH('Reuniao Vertical_old'!I6,Pipe!E:E,0)) -> 45726
C7: Gebana + Cataratas | D7: Crédito Estruturado | H7: =+H6+1 -> 5 | I7: Carlos Sanchez (EMS) + BB | J7: NPL | K7: Novo Fundo | L7: Aguardando Retorno do BB | M7: =+INDEX(Pipe!F:F,MATCH('Reuniao Vertical_old'!I7,Pipe!E:E,0)) -> 45748
C8: Relação Libelula | D8: Carteira de Ativos | H8: =+H7+1 -> 6 | I8: Sealion Shipping Ltd. | J8: NPL | K8: Navegação | L8: Aguardando assinatura de NDA e retorno advisor americanos | M8: 45685
C9: Claim Trabalhista - Oriz | D9: Legal Claim | H9: =+H8+1 -> 7 | I9: Grupo Marabraz | J9: Crédito Estruturado | K9: Varejo | L9: Aguardando informações de Garantias Adicionais | M9: 45764
C10: Empresa Agro (Algodão) - Acrefort | D10: Crédito Estruturado | G10: x | H10: =+H9+1 -> 8 | I10: Polo Wear | J10: Crédito Estruturado | K10: Varejo | L10: Aguardando Devolutiva | M10: =+INDEX(Pipe!F:F,MATCH('Reuniao Vertical_old'!I10,Pipe!E:E,0)) -> 45597
C11: Fazenda | D11: Crédito Estruturado | H11: =+H10+1 -> 9 | I11: Patense | J11: DIP | K11: Resíduo Animal | L11: Análises Iniciais | M11: 45747
C12: Fornecedor Equipamentos - Curitiba | D12: Crédito Estruturado | G12: x | H12: =+H11+1 -> 10 | I12: Morro Verde | J12: NPL + Crédito Estruturado | K12: Mineração | L12: Estágio Incipiente | M12: =+INDEX(Pipe!F:F,MATCH('Reuniao Vertical_old'!I12,Pipe!E:E,0)) -> 45754
C13: Hileia | D13: Crédito Estruturado | H13: =+H12+1 -> 11 | I13: South Star | J13: Crédito Estruturado | K13: Mineração | L13: Reunião Inicial 17/04 | M13: =+INDEX(Pipe!F:F,MATCH('Reuniao Vertical_old'!I13,Pipe!E:E,0)) -> 45751
C14: Requisição de Pgto ST Cruz | D14: Precatório Federal | H14: =+H13+1 -> 12 | I14: Grupo Elfa | J14: Crédito Estruturado | K14: Saúde | L14: Encaminhado para High Yield | M14: =+INDEX(Pipe!F:F,MATCH('Reuniao Vertical_old'!I14,Pipe!E:E,0)) -> 45744
C15: Precatório Ceara | D15: Precatório Estadual | H15: =+H14+1 -> 13 | I15: Banco Santos | J15: NPL | K15: Financeiro - Falência | L15: Definindo potencial abordagem | M15: =+INDEX(Pipe!F:F,MATCH('Reuniao Vertical_old'!I15,Pipe!E:E,0)) -> 45751
C16: Intecnial | D16: DIP | G16: x | H16: =+H15+1 -> 14 | I16: Lotus Grains & oilseeds s.a | J16: Crédito Estruturado | K16: Trading | L16: Aguardando Reunião Inicial 25/04 | M16: =+INDEX(Pipe!F:F,MATCH('Reuniao Vertical_old'!I16,Pipe!E:E,0)) -> 45737
C17: Auto Pátio Lageado | D17: Precatório Estadual | H17: =+H16+1 -> 15 | I17: Seteloc | J17: Crédito Estruturado | M17: =+INDEX(Pipe!F:F,MATCH('Reuniao Vertical_old'!I17,Pipe!E:E,0)) -> 45764
C18: Projeto Catarina | D18: Crédito Estruturado | H18: =+H17+1 -> 16 | I18: Artec | J18: Crédito Estruturado | M18: =+INDEX(Pipe!F:F,MATCH('Reuniao Vertical_old'!I18,Pipe!E:E,0)) -> 45775
C19: Niraj Towers | D19: Crédito Estruturado | H19: =+H18+1 -> 17 | I19: Rica Alimentos | J19: DIP | K19: Proteína Animal | L19: Aguardando informações | M19: =+INDEX(Pipe!F:F,MATCH('Reuniao Vertical_old'!I19,Pipe!E:E,0)) -> 45757
H20: =+H19+1 -> 18 | I20: Galileo e Assespa | J20: NPL | K20: Educação - Falência | L20: Aguardando devolutiva da A&M | M20: 45684
H21: =+H20+1 -> 19 | I21: Evolve | J21: Crédito Estruturado | K21: Academia | L21: M&A c/ estratégico | M21: =+INDEX(Pipe!F:F,MATCH('Reuniao Vertical_old'!I21,Pipe!E:E,0)) -> 45597
H22: =+H21+1 -> 20 | I22: Grupo Lagos de Itaipava | J22: NPL + DIP | K22: Hotelaria | L22: Trativas Encerradas | M22: =+INDEX(Pipe!F:F,MATCH('Reuniao Vertical_old'!I22,Pipe!E:E,0)) -> 45687
H23: =+H22+1 -> 21 | I23: Sencinet | J23: Crédito Estruturado | K23: Tecnologia | L23: Trativas Encerradas | M23: =+INDEX(Pipe!F:F,MATCH('Reuniao Vertical_old'!I23,Pipe!E:E,0)) -> 45705
H24: =+H23+1 -> 22 | I24: Grupo Fasolo | J24: NPL + DIP | K24: Agro | L24: Trativas Encerradas | M24: =+INDEX(Pipe!F:F,MATCH('Reuniao Vertical_old'!I24,Pipe!E:E,0)) -> 45726
H25: =+H24+1 -> 23 | I25: STEMAC | J25: DIP | K25: Gerador de Energia | L25: Trativas Encerradas | M25: =+INDEX(Pipe!F:F,MATCH('Reuniao Vertical_old'!I25,Pipe!E:E,0)) -> 45751
H26: =+H25+1 -> 24 | I26: Carteira de Crédito da OI | J26: NPL | K26: Telecom | L26: Trativas Encerradas | M26: 45754
H27: =+H26+1 -> 25 | I27: Graal x Odebrecht | J27: NPL | K27: Construção | L27: Trativas Encerradas | M27: =+INDEX(Pipe!F:F,MATCH('Reuniao Vertical_old'!I27,Pipe!E:E,0)) -> 45693
H28: =+H27+1 -> 26 | I28: Casas Bahia | J28: NPL | K28: Varejo | L28: Reprovada em análise | M28: =+INDEX(Pipe!F:F,MATCH('Reuniao Vertical_old'!I28,Pipe!E:E,0)) -> 45726
H29: =+H28+1 -> 27 | I29: FIDES (Cobre) | J29: Crédito Estruturado | K29: Mineração Cobre | L29: Trativas Encerradas - Ore classificou como ativo incipiente | M29: =+INDEX(Pipe!F:F,MATCH('Reuniao Vertical_old'!I29,Pipe!E:E,0)) -> 45734
H30: =+H29+1 -> 28 | I30: Surfland | J30: Crédito Estruturado | K30: Turismo | L30: Trativas Encerradas | M30: =+INDEX(Pipe!F:F,MATCH('Reuniao Vertical_old'!I30,Pipe!E:E,0)) -> 45751
H31: =+H30+1 -> 29 | I31: Seara Agro | J31: Crédito Estruturado | K31: Agro | L31: Trativas Encerradas | M31: =+INDEX(Pipe!F:F,MATCH('Reuniao Vertical_old'!I31,Pipe!E:E,0)) -> 45701
H32: =+H31+1 -> 30 | I32: Engevix | J32: Crédito Estruturado | K32: Estaleiro / Engenharia | L32: Trativas Encerradas | M32: =+INDEX(Pipe!F:F,MATCH('Reuniao Vertical_old'!I32,Pipe!E:E,0)) -> 45709
H33: =+H32+1 -> 31 | I33: St.Marche | J33: DIP | K33: Varejo | L33: Trativas Encerradas | M33: =+INDEX(Pipe!F:F,MATCH('Reuniao Vertical_old'!I33,Pipe!E:E,0)) -> 45329
H34: =+H33+1 -> 32 | I34: Allievo x Mottu | J34: Crédito Estruturado | K34: Fundo / Serviços | L34: Trativas Encerradas | M34: 45713
H35: =+H34+1 -> 33 | I35: Benge | J35: NPL + DIP + Claim | K35: Indústria | L35: Trativas Encerradas | M35: =+INDEX(Pipe!F:F,MATCH('Reuniao Vertical_old'!I35,Pipe!E:E,0)) -> 45712
M40: =+MAX(M42:M69) -> 45764
H41: # | I41: Ativos Judiciais | J41: Operação | K41: Setor | L41: Status
H42: 1 | I42: BRCon | J42: Legal Claim | K42: Construção | L42: Discussão de Proposta | M42: =+INDEX(Pipe!F:F,MATCH('Reuniao Vertical_old'!I42,Pipe!E:E,0)) -> 45530
H43: =+H42+1 -> 2 | I43: Sealion Brasil | J43: Legal Claim e Precatório | K43: Navegação | L43: Avaliando valor dos claims | M43: 45685
H44: =+H43+1 -> 3 | I44: Kerui Método | J44: Litigation Finance | K44: Engenharia | L44: Aprovado, vamos liquidar até 30/04 (R$ 5,5m) | M44: 45567
H45: =+H44+1 -> 4 | I45: Petroenge x Petrobras | J45: Legal Claim + DIP | K45: Serviços O&G | L45: Discussão de Proposta | M45: 45737
H46: =+H45+1 -> 5 | I46: Precatórios Tocantis | J46: Precatório Estadual | L46: Discussão de Proposta | M46: 45742
H47: =+H46+1 -> 6 | I47: Honorários Feira de Santana | J47: Pré precatório Municipal | L47: Investido | M47: 45716
H48: =+H47+1 -> 7 | I48: Detran - GO | J48: Pré-precatório | K48: Engenharia | L48: Revisando informações enviadas | M48: =+INDEX(Pipe!F:F,MATCH('Reuniao Vertical_old'!I48,Pipe!E:E,0)) -> 45643
H49: =+H48+1 -> 8 | I49: MRV | J49: Legal Claim | K49: Construção | L49: Aguardando devolutiva da proposta | M49: =+INDEX(Pipe!F:F,MATCH('Reuniao Vertical_old'!I49,Pipe!E:E,0)) -> 45686
H50: =+H49+1 -> 9 | I50: Armando Conde x Cyrella | J50: Legal Claim | K50: Construção | L50: Advogado analisando as infos solicitadas | M50: 45706
H51: =+H50+1 -> 10 | I51: GE e Voith x Furnas | J51: Legal Claim | K51: Construção | L51: Discussão de Proposta | M51: =+INDEX(Pipe!F:F,MATCH('Reuniao Vertical_old'!I51,Pipe!E:E,0)) -> 45715
H52: =+H51+1 -> 11 | I52: Precatórios Rio | J52: Precatório Estadual | L52: Aguardando Ofício | M52: 45731
H53: =+H52+1 -> 12 | I53: Technip | J53: Legal Claim | K53: Energia | L53: Em análise inicial | M53: =+INDEX(Pipe!F:F,MATCH('Reuniao Vertical_old'!I53,Pipe!E:E,0)) -> 45751
H54: =+H53+1 -> 13 | I54: Clinica Cristo Rei x White Martins | J54: Legal Claim | K54: Gás Natural | L54: Em análise inicial | M54: =+INDEX(Pipe!F:F,MATCH('Reuniao Vertical_old'!I54,Pipe!E:E,0)) -> 45754
H55: =+H54+1 -> 14 | I55: Hidroservice | J55: Legal Claim | K55: Engenharia | L55: Trativas Encerradas | M55: =+INDEX(Pipe!F:F,MATCH('Reuniao Vertical_old'!I55,Pipe!E:E,0)) -> 45757
H56: =+H55+1 -> 15 | I56: TTK x Petrobras | J56: Legal Claim | K56: Construção | L56: Trativas Encerradas | M56: =+INDEX(Pipe!F:F,MATCH('Reuniao Vertical_old'!I56,Pipe!E:E,0)) -> 45742
H57: =+H56+1 -> 16 | I57: Gradiente | J57: Precatório Federal | K57: Eletrônicos | L57: Trativas Encerradas | M57: =+INDEX(Pipe!F:F,MATCH('Reuniao Vertical_old'!I57,Pipe!E:E,0)) -> 45744
H58: =+H57+1 -> 17 | I58: Precatório Fortaleza | J58: Precatório | L58: Trativas Encerradas | M58: =+INDEX(Pipe!F:F,MATCH('Reuniao Vertical_old'!I58,Pipe!E:E,0)) -> 45764
H59: =+H58+1 -> 18 | I59: Rede Bandeirantes | J59: Legal Claim | K59: Mídia | L59: Trativas Encerradas | M59: =+INDEX(Pipe!F:F,MATCH('Reuniao Vertical_old'!I59,Pipe!E:E,0)) -> 45757
H60: =+H59+1 -> 19 | I60: Voepass x Latam | J60: Litigation Finance | K60: Aviação | L60: Trativas Encerradas | M60: =+INDEX(Pipe!F:F,MATCH('Reuniao Vertical_old'!I60,Pipe!E:E,0)) -> 45688
H61: =+H60+1 -> 20 | I61: Precatório Valença | J61: Precatório Municipal | L61: Trativas Encerradas | M61: 45715
H62: =+H61+1 -> 21 | I62: Construtora x Sanepar | J62: Legal Claim | K62: Construção | L62: Trativas Encerradas | M62: 45716
H63: =+H62+1 -> 22 | I63: Associação de Educação do Norte Paulista | J63: Precatório Federal | L63: Trativas Encerradas | M63: =+INDEX(Pipe!F:F,MATCH('Reuniao Vertical_old'!I63,Pipe!E:E,0)) -> 45729
H64: =+H63+1 -> 23 | I64: Walter dos Santos Affonso x CTBU | J64: Legal Claim | K64: Logística | L64: Trativas Encerradas | M64: 45733
H65: =+H64+1 -> 24 | I65: Derivado de Petro Santa Izabel x Vibra | J65: Legal Claim | K65: O&G | L65: Trativas Encerradas | M65: =+INDEX(Pipe!F:F,MATCH('Reuniao Vertical_old'!I65,Pipe!E:E,0)) -> 45734
H66: =+H65+1 -> 25 | I66: Casa de Saúde Aragão - Precatório | J66: Precatório Federal | K66: Tese SUS | L66: Trativas Encerradas | M66: 45742
H67: =+H66+1 -> 26 | I67: Estre Ambiental | J67: Pré precatório | L67: Trativas Encerradas | M67: 45705
H68: =+H67+1 -> 27 | I68: Tese Tunep | J68: Precatório | K68: Tunep | L68: Trativas Encerradas | M68: =+INDEX(Pipe!F:F,MATCH('Reuniao Vertical_old'!I68,Pipe!E:E,0)) -> 45706
H69: =+H68+1 -> 28 | I69: Concremix | J69: Legal Claim | K69: Construção | L69: Trativas Encerradas | M69: =+INDEX(Pipe!F:F,MATCH('Reuniao Vertical_old'!I69,Pipe!E:E,0)) -> 45712

Sheet Sheet2
K1: DIP/Exit Financing | N1: NPL
C2: a | D2: a | E2: a | F2: a | G2: a | H2: a | K2: Direitos Creditórios | N2: Outros
C3: 1 | D3: Precatórios | E3: Precatórios do Estado do RN | F3: 45303 | G3: Não | H3: Precatório Estadual | P3: DIP/Exit Financing
C4: =+C3+1 -> 2 | D4: Precatórios | E4: Precatórios do Estado do MT | F4: 45307 | G4: Não | H4: Precatório Estadual | P4: Direitos Creditórios
